Workbook

Sheet Datos - Gastos
A1: Conceptos de gastos/ingresos | C1: Orígenes/destinos gastos e ingresos
A2: Pago Claude/Cursor | C2: Regalo recibida
A3: Salidas a cenar/almorzar | C3: Caja de seguridad
A4: Juntadas a cenar/almorzar | C4: Cta. Comitente Petrini
A5: Salidas a desyunar/merendar | C5: Superfondos Santander
A6: Juntadas a desayunar/merendar | C6: Caja de Ahorro Santander (ARS)
A7: Salidas a tomar algo | C7: Caja de Ahorro Santander (USD)
A8: Fiestas | C8: Mercado Pago
A9: Auto | C9: Brubank
A10: Celular | C10: Efectivo
A11: Farmacia/Cosméticos
A12: Ropa
A13: Súper
A14: Gimnasio
A15: Psicóloga
A16: Delivery
A17: Regalos
A18: Mascotas
A19: Entradas fiestas/conciertos/otros eventos
A20: Pago de honorarios Quantum
A21: Pago de honorarios Axis
A22: Otros honorarios
... A30: Compras varias

Sheet Gastos julio
B1: Datos del periodo | J1: Tenencia - Inicio | K1: USD | L1: ARS | N1: Tenencia - Fin | O1: USD | P1: ARS | R1: Diferencia | S1: USD | T1: ARS
B2: Año: | C2: 2026 | J2: Regalo recibida | K2: 10000 | L2: =K2*$D$7 -> 14890000 | N2: Regalo recibida | O2: =K2+SUMIF($E$24:$E$99,$N2,$C$24:$C$99)+SUMIF($E$24:$E$99,$N2,$D$24:$D$99) -> 10000 | P2: =O2*$D$7 -> 14890000 | R2: Regalo recibida | S2: =IFERROR(IF(O2>K2,O2-K2,K2-O2),0) -> 0 | T2: =IFERROR(IF(P2>L2,P2-L2,L2-P2),0) -> 0
B3: Mes: | C3: julio | J3: Caja de seguridad | K3: 500 | L3: =K3*$D$7 -> 744500 | N3: Caja de seguridad | O3: 500 | P3: =L3+SUMIF($E$24:$E$99,$N3,$C$24:$C$99)+SUMIF($E$24:$E$99,$N3,$D$24:$D$99) -> 744500 | R3: Caja de seguridad | S3: =IFERROR(IF(O3>K3,O3-K3,K3-O3),0) -> 0 | T3: =IFERROR(IF(P3>L3,P3-L3,L3-P3),0) -> 0
B4: Cantidad de días: | C4: =DAY(EOMONTH(DATE($C$2,MATCH($C$3,{"enero";"febrero";"marzo";"abril";"mayo";"junio";"julio";"agosto";"septiembre";"octubre";"noviembre";"diciembre"},0),1),0)) -> 31 | J4: Cta. Comitente Petrini | K4: =L4/$C$7 -> 302.20447 | L4: 447262.62 | N4: Cta. Comitente Petrini | O4: =IFERROR(P4/$C$8,"") -> 1128.2621 | P4: =L4+SUMIF($E$24:$E$99,$N4,$C$24:$C$99)+SUMIF($E$24:$E$99,$N4,$D$24:$D$99) -> 1647262.6 | R4: Cta. Comitente Petrini | S4: =IFERROR(IF(O4>K4,O4-K4,K4-O4),0) -> 826.0576 | T4: =IFERROR(IF(P4>L4,P4-L4,L4-P4),0) -> 1200000
J5: Superfondos Santander | K5: =L5/$C$7 -> 2160.0629 | L5: 3196893 | N5: Superfondos Santander | O5: =IFERROR(P5/$C$8,"") -> 929.01971 | P5: =L5+SUMIF($E$24:$E$99,$N5,$C$24:$C$99)+SUMIF($E$24:$E$99,$N5,$D$24:$D$99) -> 1356368.8 | R5: Superfondos Santander | S5: =IFERROR(IF(O5>K5,O5-K5,K5-O5),0) -> 1231.0432 | T5: =IFERROR(IF(P5>L5,P5-L5,L5-P5),0) -> 1840524.3
B6: Tc | C6: Compra | D6: Venta | J6: Caja de Ahorro Santander (ARS) | K6: =L6/$C$7 -> 253.20725 | L6: 374746.73 | N6: Caja de Ahorro Santander (ARS) | O6: =IFERROR(P6/$C$8,"") -> 1429.739 | P6: =L6+SUMIF($E$24:$E$99,$N6,$C$24:$C$99)+SUMIF($E$24:$E$99,$N6,$D$24:$D$99) -> 2087418.9 | R6: Caja de Ahorro Santander (ARS) | S6: =IFERROR(IF(O6>K6,O6-K6,K6-O6),0) -> 1176.5317 | T6: =IFERROR(IF(P6>L6,P6-L6,L6-P6),0) -> 1712672.2
B7: =DATE($C$2,MATCH($C$3,{"enero";"febrero";"marzo";"abril";"mayo";"junio";"julio";"agosto";"septiembre";"octubre";"noviembre";"diciembre"},0),1) -> 46204 | C7: 1480 | D7: 1489 | J7: Caja de Ahorro Santander (USD) | K7: 0.52 | L7: =K7*$D$7 -> 774.28 | N7: Caja de Ahorro Santander (USD) | O7: =K7+SUM(C17:C19)-SUM(D17:D19) -> 4.74 | P7: =O7*$D$8 -> 7157.4 | R7: Caja de Ahorro Santander (USD) | S7: =IFERROR(IF(O7>K7,O7-K7,K7-O7),0) -> 4.22 | T7: =IFERROR(IF(P7>L7,P7-L7,L7-P7),0) -> 6383.12
B8: =DATE($C$2,MATCH($C$3,{"enero";"febrero";"marzo";"abril";"mayo";"junio";"julio";"agosto";"septiembre";"octubre";"noviembre";"diciembre"},0),C4) -> 46234 | C8: 1460 | D8: 1510 | J8: Mercado Pago | K8: =L8/$C$7 -> 0.38181757 | L8: 565.09 | N8: Mercado Libre | O8: =IFERROR(P8/$C$8,"") -> 0.38704795 | P8: =L8+SUMIF($E$24:$E$99,$N8,$C$24:$C$99)+SUMIF($E$24:$E$99,$N8,$D$24:$D$99) -> 565.09 | R8: Mercado Libre | S8: =IFERROR(IF(O8>K8,O8-K8,K8-O8),0) -> 0.0052303776 | T8: =IFERROR(IF(P8>L8,P8-L8,L8-P8),0) -> 0
J9: Brubank | K9: =L9/$C$7 -> 0.00091891892 | L9: 1.36 | N9: Brubank | O9: =IFERROR(P9/$C$8,"") -> 0.00093150685 | P9: =L9+SUMIF($E$24:$E$99,$N9,$C$24:$C$99)+SUMIF($E$24:$E$99,$N9,$D$24:$D$99) -> 1.36 | R9: Brubank | S9: =IFERROR(IF(O9>K9,O9-K9,K9-O9),0) -> 1.258793e-05 | T9: =IFERROR(IF(P9>L9,P9-L9,L9-P9),0) -> 0
J10: Efectivo | K10: =L10/$C$7 -> 27.027027 | L10: 40000 | N10: Efectivo | O10: =IFERROR(P10/$C$8,"") -> 3.4246575 | P10: =L10+SUMIF($E$24:$E$99,$N10,$C$24:$C$99)+SUMIF($E$24:$E$99,$N10,$D$24:$D$99) -> 5000 | R10: Efectivo | S10: =IFERROR(IF(O10>K10,O10-K10,K10-O10),0) -> 23.602369 | T10: =IFERROR(IF(P10>L10,P10-L10,L10-P10),0) -> 35000
J12: Total | K12: =SUM(K2:K10) -> 13243.404 | L12: =SUM(L2:L10) -> 19694743 | N12: Total | O12: =SUM(O2:O9) -> 13992.149 | P12: =SUM(P2:P9) -> 20733274 | R12: Total | S12: =SUM(S2:S9) -> 3237.8577 | T12: =SUM(T2:T9) -> 4759579.6
B15: Compra/venta USD | J15: Análisis gastos e ingresos
B16: Nro. | C16: Ingresos | D16: Gastos | E16: Origen/Destino | F16: Concepto | G16: Descripción | H16: Fecha | J16: Concepto | K16: Acumulado egresos | L16: Acumulado ingresos | M16: Composición egresos | N16: Composición ingresos
B17: 1 | C17: 270 | E17: Caja de Ahorro Santander (USD) | F17: Pago tarjetas de crédito | G17: Compra USD p pagar tarjetas | H17: 46209 | J17: Pago Claude/Cursor | K17: =SUMIF($F$24:$F$99,$J17,$D$24:$D$99) -> 0 | L17: =SUMIF($F$24:$F$99,$J17,$C$24:$C$99) -> 16000 | M17: =IFERROR(K17/SUM(K$17:K$32),"") -> 0 | N17: =IFERROR(L17/SUM(L$17:L$32),"") -> 0.0040689308
B18: 2 | D18: 265.78 | E18: Caja de Ahorro Santander (USD) | F18: Pago tarjetas de crédito | G18: Pago tarjetas | H18: 46209 | J18: Salidas a cenar/almorzar | K18: =SUMIF($F$24:$F$99,$J18,$C$24:$C$99)+SUMIF($F$24:$F$99,$J18,$D$24:$D$99) -> -139930 | L18: =SUMIF($F$24:$F$99,$J18,$C$24:$C$99) -> 40050 | M18: =IFERROR(K18/SUM(K$17:K$32),"") -> -0.070832453 | N18: =IFERROR(L18/SUM(L$17:L$32),"") -> 0.010185042
J19: Salidas a desyunar/merendar | K19: =SUMIF($F$24:$F$99,$J19,$C$24:$C$99)+SUMIF($F$24:$F$99,$J19,$D$24:$D$99) -> -110800 | L19: =SUMIF($F$24:$F$99,$J19,$C$24:$C$99) -> 34200 | M19: =IFERROR(K19/SUM(K$17:K$32),"") -> -0.05608687 | N19: =IFERROR(L19/SUM(L$17:L$32),"") -> 0.0086973397
J20: Salidas a tomar algo | K20: =SUMIF($F$24:$F$99,$J20,$C$24:$C$99)+SUMIF($F$24:$F$99,$J20,$D$24:$D$99) -> -33000 | L20: =SUMIF($F$24:$F$99,$J20,$C$24:$C$99) -> 32000 | M20: =IFERROR(K20/SUM(K$17:K$32),"") -> -0.016704573 | N20: =IFERROR(L20/SUM(L$17:L$32),"") -> 0.0081378617
J21: Fiestas | K21: =SUMIF($F$24:$F$99,$J21,$C$24:$C$99)+SUMIF($F$24:$F$99,$J21,$D$24:$D$99) -> 0 | L21: =SUMIF($F$24:$F$99,$J21,$C$24:$C$99) -> 0 | M21: =IFERROR(K21/SUM(K$17:K$32),"") -> 0 | N21: =IFERROR(L21/SUM(L$17:L$32),"") -> 0
B22: Movimientos en ARS | J22: Auto | K22: =SUMIF($F$24:$F$99,$J22,$C$24:$C$99)+SUMIF($F$24:$F$99,$J22,$D$24:$D$99) -> -76600 | L22: =SUMIF($F$24:$F$99,$J22,$C$24:$C$99) -> 0 | M22: =IFERROR(K22/SUM(K$17:K$32),"") -> -0.038774858 | N22: =IFERROR(L22/SUM(L$17:L$32),"") -> 0
B23: Nro. | C23: Ingresos | D23: Gastos | E23: Origen/Destino | F23: Concepto | G23: Descripción | H23: Fecha | J23: Farmacia/Cosméticos | K23: =SUMIF($F$24:$F$99,$J23,$C$24:$C$99)+SUMIF($F$24:$F$99,$J23,$D$24:$D$99) -> -33852.49 | L23: =SUMIF($F$24:$F$99,$J23,$C$24:$C$99) -> 1439.91 | M23: =IFERROR(K23/SUM(K$17:K$32),"") -> -0.017136103 | N23: =IFERROR(L23/SUM(L$17:L$32),"") -> 0.00036618089
B24: 1 | D24: -18700 | E24: Efectivo | F24: Auto | G24: Cochera cumple Sofi H | H24: 46204 | J24: Ropa | K24: =SUMIF($F$24:$F$99,$J24,$C$24:$C$99)+SUMIF($F$24:$F$99,$J24,$D$24:$D$99) -> 0 | L24: =SUMIF($F$24:$F$99,$J24,$C$24:$C$99) -> 0 | M24: =IFERROR(K24/SUM(K$17:K$32),"") -> 0 | N24: =IFERROR(L24/SUM(L$17:L$32),"") -> 0
B25: 2 | C25: 16000 | E25: Caja de Ahorro Santander (ARS) | F25: Pago Claude/Cursor | G25: Transferencia IM | H25: 46205 | J25: Súper | K25: =SUMIF($F$24:$F$99,$J25,$C$24:$C$99)+SUMIF($F$24:$F$99,$J25,$D$24:$D$99) -> 0 | L25: =SUMIF($F$24:$F$99,$J25,$C$24:$C$99) -> 0 | M25: =IFERROR(K25/SUM(K$17:K$32),"") -> 0 | N25: =IFERROR(L25/SUM(L$17:L$32),"") -> 0
B26: 3 | D26: -4800 | E26: Caja de Ahorro Santander (ARS) | F26: Delivery | G26: Coca cena Sofi H | H26: 46205 | J26: Delivery | K26: =SUMIF($F$24:$F$99,$J26,$C$24:$C$99)+SUMIF($F$24:$F$99,$J26,$D$24:$D$99) -> -71557.6 | L26: =SUMIF($F$24:$F$99,$J26,$C$24:$C$99) -> 153000 | M26: =IFERROR(K26/SUM(K$17:K$32),"") -> -0.036222399 | N26: =IFERROR(L26/SUM(L$17:L$32),"") -> 0.038909151
B27: 4 | D27: -3900 | E27: Caja de Ahorro Santander (ARS) | F27: Auto | G27: Cochera | H27: 46205 | J27: Regalos | K27: =SUMIF($F$24:$F$99,$J27,$C$24:$C$99)+SUMIF($F$24:$F$99,$J27,$D$24:$D$99) -> 53200 | L27: =SUMIF($F$24:$F$99,$J27,$C$24:$C$99) -> 67500 | M27: =IFERROR(K27/SUM(K$17:K$32),"") -> 0.026929797 | N27: =IFERROR(L27/SUM(L$17:L$32),"") -> 0.017165802
B28: 5 | D28: -45759 | E28: Caja de Ahorro Santander (ARS) | F28: Delivery | G28: Comida cena Sofi H | H28: 46205 | J28: Entradas fiestas/conciertos | K28: =SUMIF($F$24:$F$99,$J28,$C$24:$C$99)+SUMIF($F$24:$F$99,$J28,$D$24:$D$99) -> 0 | L28: =SUMIF($F$24:$F$99,$J28,$C$24:$C$99) -> 0 | M28: =IFERROR(K28/SUM(K$17:K$32),"") -> 0 | N28: =IFERROR(L28/SUM(L$17:L$32),"") -> 0
B29: 6 | C29: 20000 | E29: Caja de Ahorro Santander (ARS) | F29: Delivery | G29: Dev. Lomito Sofi H | H29: 46205 | J29: Pago de honorarios Quantum | K29: =SUMIF($F$24:$F$99,$J29,$C$24:$C$99)+SUMIF($F$24:$F$99,$J29,$D$24:$D$99) -> 2084047 | L29: =SUMIF($F$24:$F$99,$J29,$C$24:$C$99) -> 2084047 | M29: =IFERROR(K29/SUM(K$17:K$32),"") -> 1.0549429 | N29: =IFERROR(L29/SUM(L$17:L$32),"") -> 0.52999019
B30: 7 | D30: -1000524.3 | E30: Superfondos Santander | F30: Rescates FCI | G30: Rescate p invertir en Petrini | H30: 46205 | J30: Pago de honorarios Axis | K30: =SUMIF($F$24:$F$99,$J30,$C$24:$C$99)+SUMIF($F$24:$F$99,$J30,$D$24:$D$99) -> 304000 | L30: =SUMIF($F$24:$F$99,$J30,$C$24:$C$99) -> 304000 | M30: =IFERROR(K30/SUM(K$17:K$32),"") -> 0.15388455 | N30: =IFERROR(L30/SUM(L$17:L$32),"") -> 0.077309686
B31: 8 | C31: 1000524.3 | E31: Caja de Ahorro Santander (ARS) | F31: Rescates FCI | G31: Rescate p invertir en Petrini | H31: 46205 | J31: Otros honorarios | K31: =SUMIF($F$24:$F$99,$J31,$C$24:$C$99)+SUMIF($F$24:$F$99,$J31,$D$24:$D$99) -> 0 | L31: =SUMIF($F$24:$F$99,$J31,$C$24:$C$99) -> 0 | M31: =IFERROR(K31/SUM(K$17:K$32),"") -> 0 | N31: =IFERROR(L31/SUM(L$17:L$32),"") -> 0
B32: 9 | D32: -1200000 | E32: Caja de Ahorro Santander (ARS) | F32: Ahorros/inversiones | G32: Transferencia a Petrini | H32: 46205 | J32: Ahorros/inversiones | K32: =SUMIF($F$24:$F$99,$J32,$C$24:$C$99)+SUMIF($F$24:$F$99,$J32,$D$24:$D$99) -> 0 | L32: =SUMIF($F$24:$F$99,$J32,$C$24:$C$99) -> 1200000 | M32: =IFERROR(K32/SUM(K$17:K$32),"") -> 0 | N32: =IFERROR(L32/SUM(L$17:L$32),"") -> 0.30516981
B33: 10 | C33: 1200000 | E33: Cta. Comitente Petrini | F33: Ahorros/inversiones | G33: Compra S&P 500 y fondo CER | H33: 46205 | J33: Pago tarjetas de crédito | K33: =SUMIF($F$24:$F$99,$J33,$C$24:$C$99)+SUMIF($F$24:$F$99,$J33,$D$24:$D$99) -> -692782.22 | L33: =SUMIF($F$24:$F$99,$J33,$C$24:$C$99) -> 3.62 | M33: =IFERROR(K33/SUM(K$17:K$32),"") -> -0.3506858 | N33: =IFERROR(L33/SUM(L$17:L$32),"") -> 9.205956e-07
B34: 11 | D34: -1000 | E34: Caja de Ahorro Santander (ARS) | F34: Auto | G34: Estacionamiento Chacana | H34: 46206
B35: 12 | D35: -27700 | E35: Caja de Ahorro Santander (ARS) | F35: Salidas a desyunar/merendar | G35: Desayuno Cielo Cherry Season | H35: 46207 | J35: Superfondos Santander
B36: 13 | D36: -43600 | E36: Caja de Ahorro Santander (ARS) | F36: Salidas a desyunar/merendar | G36: Merienda Parce IM, CA, IP | H36: 46207 | J36: Superfondos Santander | K36: 46209 | L36: 46216 | M36: 46223 | N36: 46230
B37: 14 | C37: 11200 | E37: Caja de Ahorro Santander (ARS) | F37: Salidas a desyunar/merendar | G37: Dev. Isa Parce | H37: 46207 | J37: Calculado | K37: =$L$5+SUMIFS($C$24:$C$99,$E$24:$E$99,$N5,$H$24:$H$99,"<"&K$36)+SUMIFS($D$24:$D$99,$E$24:$E$99,$N5,$H$24:$H$99,"<="&K$36) -> 1496368.8 | L37: =$L$5+SUMIFS($C$24:$C$99,$E$24:$E$99,$N5,$H$24:$H$99,"<"&L$36)+SUMIFS($D$24:$D$99,$E$24:$E$99,$N5,$H$24:$H$99,"<="&L$36) -> 1496368.8 | M37: =$L$5+SUMIFS($C$24:$C$99,$E$24:$E$99,$N5,$H$24:$H$99,"<"&M$36)+SUMIFS($D$24:$D$99,$E$24:$E$99,$N5,$H$24:$H$99,"<="&M$36) -> 1496368.8 | N37: =$L$5+SUMIFS($C$24:$C$99,$E$24:$E$99,$N5,$H$24:$H$99,"<"&N$36)+SUMIFS($D$24:$D$99,$E$24:$E$99,$N5,$H$24:$H$99,"<="&N$36) -> 1356368.8
B38: 15 | D38: -1300 | E38: Efectivo | F38: Regalos | G38: Semáforo | H38: 46207 | J38: Real | K38: 1496893 | L38: 1500051 | M38: 1506505.4 | N38: 1373248.7
B39: 16 | C39: 6000 | E39: Caja de Ahorro Santander (ARS) | F39: Salidas a desyunar/merendar | G39: Dev. Cielo Parce | H39: 46208 | J39: Rendimiento (neto) | K39: =IF(K38="","",K38-K37) -> 524.24 | L39: =IF(L38="","",L38-L37) -> 3682.2 | M39: =IF(M38="","",M38-M37) -> 10136.61 | N39: =IF(N38="","",N38-N37) -> 16879.9
B40: 17 | D40: -700000 | E40: Superfondos Santander | F40: Rescates FCI | G40: Rescate p comprar USD p pagar tarjeta de crédito | H40: 46209 | J40: Rendimiento (%) | K40: =IF(K39="","",((K38-K37)/K37)) -> 0.00035034145 | L40: =IF(L39="","",((L38-L37)/L37)) -> 0.002460757 | M40: =IF(M39="","",((M38-M37)/M37)) -> 0.006774139 | N40: =IF(N39="","",((N38-N37)/N37)) -> 0.012444919
B41: 18 | C41: 700000 | E41: Caja de Ahorro Santander (ARS) | F41: Rescates FCI | G41: Rescate p comprar USD p pagar tarjeta de crédito | H41: 46209
B42: 19 | D42: -280942.71 | E42: Caja de Ahorro Santander (ARS) | F42: Pago tarjetas de crédito | G42: Pago VISA ARS | H42: 46209 | J42: Petrini
B43: 20 | D43: -407700 | E43: Caja de Ahorro Santander (ARS) | F43: Pago tarjetas de crédito | G43: Compra USD para pago VISA y AMEX USD | H43: 46209 | J43: Fecha | K43: 46209 | L43: 46216 | M43: 46223 | N43: 46230
B44: 21 | C44: 65500 | E44: Caja de Ahorro Santander (ARS) | F44: Pago de honorarios Axis | G44: Semana 1 mes de julio | H44: 46209 | J44: Tenencia calculada | K44: =$L$4+SUMIFS($D$24:$D$99,$G$24:$G$99,"Transferencia a Petrini",$H$24:$H$99,"<"&K$36)*-1+SUMIFS($D$24:$D$99,$G$24:$G$99,"Transferencia de Petrini",$H$24:$H$99,"<"&K$36) -> 1647262.6 | L44: =$L$4+SUMIFS($D$24:$D$99,$G$24:$G$99,"Transferencia a Petrini",$H$24:$H$99,"<"&L$36)*-1+SUMIFS($D$24:$D$99,$G$24:$G$99,"Transferencia de Petrini",$H$24:$H$99,"<"&L$36) -> 1647262.6 | M44: =$L$4+SUMIFS($D$24:$D$99,$G$24:$G$99,"Transferencia a Petrini",$H$24:$H$99,"<"&M$36)*-1+SUMIFS($D$24:$D$99,$G$24:$G$99,"Transferencia de Petrini",$H$24:$H$99,"<"&M$36) -> 1647262.6 | N44: =$L$4+SUMIFS($D$24:$D$99,$G$24:$G$99,"Transferencia a Petrini",$H$24:$H$99,"<"&N$36)*-1+SUMIFS($D$24:$D$99,$G$24:$G$99,"Transferencia de Petrini",$H$24:$H$99,"<"&N$36) -> 1647262.6
B45: 22 | D45: -53000 | E45: Caja de Ahorro Santander (ARS) | F45: Gimnasio | G45: Julio | H45: 46209 | J45: Tenencia real | K45: 1649566.6 | L45: 1652959.3 | M45: 1648847.9 | N45: 1660541.3
B46: 23 | D46: -4143.13 | E46: Caja de Ahorro Santander (ARS) | F46: Pago tarjetas de crédito | G46: Saldo ARS AMEX | H46: 46211 | J46: Rendimiento (neto) | K46: =IF(K45="","",K45-K44) -> 2303.95 | L46: =IF(L45="","",L45-L44) -> 5696.67 | M46: =IF(M45="","",M45-M44) -> 1585.29 | N46: =IF(N45="","",N45-N44) -> 13278.65
B47: 24 | D47: -40000 | E47: Caja de Ahorro Santander (ARS) | F47: Psicóloga | G47: 1ra sesión julio psico | H47: 46211 | J47: Rendimiento (%) | K47: =IF(K46="","",((K45-K44)/K44)) -> 0.0013986537 | L47: =IF(L46="","",((L45-L44)/L44)) -> 0.0034582646 | M47: =IF(M46="","",((M45-M44)/M44)) -> 0.00096237842 | N47: =IF(N46="","",((N45-N44)/N44)) -> 0.0080610401
B48: 25 | C48: 103000 | E48: Caja de Ahorro Santander (ARS) | F48: Delivery | G48: Cena primos | H48: 46211
B49: 26 | D49: -120000 | E49: Caja de Ahorro Santander (ARS) | F49: Delivery | G49: Cena primos | H49: 46211
B50: 27 | D50: -3500 | E50: Caja de Ahorro Santander (ARS) | F50: Delivery | G50: Hielo | H50: 46211
B51: 28 | D51: -17115 | E51: Caja de Ahorro Santander (ARS) | F51: Delivery | G51: Medialunas | H51: 46214
B52: 29 | C52: 30000 | E52: Caja de Ahorro Santander (ARS) | F52: Delivery | G52: Regalo padres | H52: 46214
B53: 30 | C53: 67500 | E53: Caja de Ahorro Santander (ARS) | F53: Pago de honorarios Axis | G53: Semana 2 julio | H53: 46216
B54: 31 | D54: -6883.6 | E54: Caja de Ahorro Santander (ARS) | F54: Delivery | G54: La Celeste partido Arg | H54: 46220
B55: 32 | D55: -2000 | E55: Caja de Ahorro Santander (ARS) | F55: Auto | G55: Estacionamiento Chacana | H55: 46220
B56: 33 | D56: -35400 | E56: Caja de Ahorro Santander (ARS) | F56: Salidas a desyunar/merendar | G56: Desayuno Sofia | H56: 46220
B57: 34 | C57: 17000 | E57: Caja de Ahorro Santander (ARS) | F57: Salidas a desyunar/merendar | G57: Transf Desayuno Sofia | H57: 46220
B58: 35 | C58: 3.62 | E58: Caja de Ahorro Santander (ARS) | F58: Pago tarjetas de crédito | G58: Pago interés por saldo en cuenta | H58: 46220
B59: 36 | D59: -31000 | E59: Caja de Ahorro Santander (ARS) | F59: Salidas a cenar/almorzar | G59: 3k con las chicas Q | H59: 46221
B60: 37 | D60: -10000 | E60: Caja de Ahorro Santander (ARS) | F60: Salidas a cenar/almorzar | G60: 3k con las chicas Q - propina | H60: 46221
B61: 38 | D61: =(73100+7000)*-1 -> -80100 | E61: Caja de Ahorro Santander (ARS) | F61: Salidas a cenar/almorzar | G61: Almuerzo Bros Igna | H61: 46221
B62: 39 | C62: =36550+3500 -> 40050 | E62: Caja de Ahorro Santander (ARS) | F62: Salidas a cenar/almorzar | G62: Almuerzo Bros Igna | H62: 46221
B63: 40 | D63: -8000 | E63: Caja de Ahorro Santander (ARS) | F63: Salidas a desyunar/merendar | G63: Café trabajo MV | H63: 46221
B64: 41 | D64: -11180 | E64: Caja de Ahorro Santander (ARS) | F64: Salidas a cenar/almorzar | G64: Almuerzo final mundial Brana | H64: 46222
B65: 42 | C65: 106500 | E65: Caja de Ahorro Santander (ARS) | F65: Pago de honorarios Axis | G65: Semana 3 julio | H65: 46223
B66: 43 | D66: -34100 | E66: Caja de Ahorro Santander (ARS) | F66: Salidas a cenar/almorzar | G66: Almuerzo final mundial Brana | H66: 46223
B67: 44 | D67: -42386.74 | E67: Caja de Ahorro Santander (ARS) | F67: Pago monotributo | G67: 46174 | H67: 46223
B68: 45 | D68: -13000 | E68: Caja de Ahorro Santander (ARS) | F68: Regalos | G68: regalo jopi | H68: 46224
B69: 46 | D69: -13300 | E69: Caja de Ahorro Santander (ARS) | F69: Salidas a desyunar/merendar | G69: café shopping | H69: 46224
B70: 47 | D70: -40000 | E70: Superfondos Santander | F70: Rescates FCI | G70: Rescate p pagar psico | H70: 46225
B71: 48 | C71: 40000 | E71: Caja de Ahorro Santander (ARS) | F71: Rescates FCI | G71: Rescate p pagar psico | H71: 46225
B72: 49 | D72: -45000 | E72: Caja de Ahorro Santander (ARS) | F72: Psicóloga | G72: 2da sesión julio psico | H72: 46225
B73: 50 | C73: 22500 | E73: Caja de Ahorro Santander (ARS) | F73: Regalos | G73: Transf Lu regalo Co | H73: 46225
B74: 51 | C74: 22500 | E74: Caja de Ahorro Santander (ARS) | F74: Regalos | G74: Transf Fede regalo Co | H74: 46225
B75: 52 | C75: 22500 | E75: Caja de Ahorro Santander (ARS) | F75: Regalos | G75: Transf Joaco regalo Co | H75: 46225
B76: 53 | D76: -22980 | E76: Caja de Ahorro Santander (ARS) | F76: Telas e insumos p costura | G76: Telas sastrero | H76: 46225
B77: 54 | D77: -10000 | E77: Caja de Ahorro Santander (ARS) | F77: Telas e insumos p costura | G77: Hilo, portacarreteles, tijera | H77: 46225
B78: 55 | D78: -4000 | E78: Efectivo | F78: Auto | G78: Estacionamiento centro | H78: 46225
B79: 56 | D79: -4000 | E79: Efectivo | F79: Salidas a tomar algo | G79: Cerveza tresca | H79: 46227
B80: 57 | C80: 64500 | E80: Caja de Ahorro Santander (ARS) | F80: Pago de honorarios Axis | G80: semana 4 julio | H80: 46227
B81: 58 | C81: 100000 | E81: Caja de Ahorro Santander (ARS) | F81: Rescates FCI | G81: Rescate p finde | H81: 46227
B82: 59 | D82: -100000 | E82: Superfondos Santander | F82: Rescates FCI | G82: Rescate p finde | H82: 46227
B83: 60 | D83: -45000 | E83: Caja de Ahorro Santander (ARS) | F83: Salidas a tomar algo | G83: Vino Francis | H83: 46227
B84: 61 | D84: -2000 | E84: Efectivo | F84: Salidas a tomar algo | G84: Propina | H84: 46227
B85: 62 | C85: 16000 | E85: Caja de Ahorro Santander (ARS) | F85: Salidas a tomar algo | G85: Transferencia So | H85: 46227
B86: 63 | C86: 16000 | E86: Caja de Ahorro Santander (ARS) | F86: Salidas a tomar algo | G86: Transferencia Cielo | H86: 46227
B87: 64 | D87: -14000 | E87: Caja de Ahorro Santander (ARS) | F87: Salidas a tomar algo | G87: Transferencia Cielo entrada Boticario | H87: 46227
B88: 65 | D88: -26500 | E88: Caja de Ahorro Santander (ARS) | F88: Delivery | G88: Gohan sábado al mediodía | H88: 46228
B89: 66 | D89: -17000 | E89: Caja de Ahorro Santander (ARS) | F89: Salidas a desyunar/merendar | G89: Budín Bra | H89: 46228
B90: 67 | D90: -9599.4 | E90: Caja de Ahorro Santander (ARS) | F90: Farmacia/Cosméticos | G90: Farmacity | H90: 46228
B91: 68 | C91: 1439.91 | E91: Caja de Ahorro Santander (ARS) | F91: Farmacia/Cosméticos | G91: Farmacity | H91: 46228
B92: 69 | D92: -42000 | E92: Caja de Ahorro Santander (ARS) | F92: Auto | G92: Nafta | H92: 46594
B93: 70 | C93: 29790 | E93: Caja de Ahorro Santander (ARS) | F93: Psicóloga | G93: Reintegro julio | H93: 46231
B94: 71 | D94: -53000 | E94: Caja de Ahorro Santander (ARS) | F94: Gimnasio | G94: agosto | H94: 46231
B95: 72 | D95: -25693 | E95: Caja de Ahorro Santander (ARS) | F95: Farmacia/Cosméticos | G95: Cepillo de dientes NB | H95: 46232
B96: 73 | D96: -13600 | E96: Caja de Ahorro Santander (ARS) | F96: Salidas a cenar/almorzar | G96: Helado cremolatti | H96: 46232
B97: 74 | D97: -5000 | E97: Efectivo | F97: Auto | G97: Chequeo batería | H97: 46233
B98: 75 | C98: 2084047 | E98: Caja de Ahorro Santander (ARS) | F98: Pago de honorarios Quantum | G98: Sueldo julio | H98: 46234
B99: 76 | D99: -25000 | E99: Caja de Ahorro Santander (ARS) | F99: Transferencias Jo | G99: prestamo salida | H99: 46234

Sheet Gastos agosto
B1: Datos del periodo | J1: Tenencia - Inicio | K1: USD | L1: ARS | N1: Tenencia - Fin | O1: USD | P1: ARS | R1: Diferencia | S1: USD | T1: ARS
B2: Año: | C2: 2026 | J2: Regalo recibida | K2: ='Gastos julio'!O2 -> 10000 | L2: =K2*D7 -> 15100000 | N2: Regalo recibida | O2: =K2+SUMIF($E$24:$E$173,$N2,$C$24:$C$173)+SUMIF($E$24:$E$173,$N2,$D$24:$D$173) -> 10000 | P2: =O2*$D$7 -> 15100000 | R2: Regalo recibida | S2: =IFERROR(IF(O2>K2,O2-K2,K2-O2),0) -> 0 | T2: =IFERROR(IF(P2>L2,P2-L2,L2-P2),0) -> 0
B3: Mes: | C3: agosto | J3: Caja de seguridad | K3: ='Gastos julio'!O3 -> 500 | L3: =K3*D7 -> 755000 | N3: Caja de seguridad | O3: =K3 -> 500 | P3: =L3+SUMIF($E$24:$E$173,$N3,$C$24:$C$173)+SUMIF($E$24:$E$173,$N3,$D$24:$D$173) -> 755000 | R3: Caja de seguridad | S3: =IFERROR(IF(O3>K3,O3-K3,K3-O3),0) -> 0 | T3: =IFERROR(IF(P3>L3,P3-L3,L3-P3),0) -> 0
B4: Cantidad de días: | C4: =DAY(EOMONTH(DATE($C$2,MATCH($C$3,{"enero";"febrero";"marzo";"abril";"mayo";"junio";"julio";"agosto";"septiembre";"octubre";"noviembre";"diciembre"},0),1),0)) -> 31 | J4: Cta. Comitente Petrini | K4: ='Gastos julio'!O4 -> 1128.2621 | L4: ='Gastos julio'!P4 -> 1647262.6 | N4: Cta. Comitente Petrini | O4: =IFERROR(P4/$C$8,"") -> 1113.0153 | P4: =L4+SUMIF($E$24:$E$173,$N4,$C$24:$C$173)+SUMIF($E$24:$E$173,$N4,$D$24:$D$173) -> 1647262.6 | R4: Cta. Comitente Petrini | S4: =IFERROR(IF(O4>K4,O4-K4,K4-O4),0) -> 15.246785 | T4: =IFERROR(IF(P4>L4,P4-L4,L4-P4),0) -> 0
J5: Superfondos Santander | K5: ='Gastos julio'!O5 -> 929.01971 | L5: ='Gastos julio'!P5 -> 1356368.8 | N5: Superfondos Santander | O5: =IFERROR(P5/$C$8,"") -> 1950.2492 | P5: =L5+SUMIF($E$24:$E$173,$N5,$C$24:$C$173)+SUMIF($E$24:$E$173,$N5,$D$24:$D$173) -> 2886368.8 | R5: Superfondos Santander | S5: =IFERROR(IF(O5>K5,O5-K5,K5-O5),0) -> 1021.2295 | T5: =IFERROR(IF(P5>L5,P5-L5,L5-P5),0) -> 1530000
B6: Tc | C6: Compra | D6: Venta | J6: Caja de Ahorro Santander (ARS) | K6: ='Gastos julio'!O6 -> 1429.739 | L6: ='Gastos julio'!P6 -> 2087418.9 | N6: Caja de Ahorro Santander (ARS) | O6: =IFERROR(P6/$C$8,"") -> 1446.3709 | P6: =L6+SUMIF($E$24:$E$173,$N6,$C$24:$C$173)+SUMIF($E$24:$E$173,$N6,$D$24:$D$173) -> 2140629 | R6: Caja de Ahorro Santander (ARS) | S6: =IFERROR(IF(O6>K6,O6-K6,K6-O6),0) -> 16.631932 | T6: =IFERROR(IF(P6>L6,P6-L6,L6-P6),0) -> 53210.04
B7: =DATE($C$2,MATCH($C$3,{"enero";"febrero";"marzo";"abril";"mayo";"junio";"julio";"agosto";"septiembre";"octubre";"noviembre";"diciembre"},0),1) -> 46235 | C7: 1460 | D7: 1510 | J7: Caja de Ahorro Santander (USD) | K7: ='Gastos julio'!O7 -> 4.74 | L7: =K7*D7 -> 7157.4 | N7: Caja de Ahorro Santander (USD) | O7: =K7+SUM(C17:C19)+SUM(D17:D19) -> 9.91 | P7: =O7*$D$8 -> 15211.85 | R7: Caja de Ahorro Santander (USD) | S7: =IFERROR(IF(O7>K7,O7-K7,K7-O7),0) -> 5.17 | T7: =IFERROR(IF(P7>L7,P7-L7,L7-P7),0) -> 8054.45
B8: =DATE($C$2,MATCH($C$3,{"enero";"febrero";"marzo";"abril";"mayo";"junio";"julio";"agosto";"septiembre";"octubre";"noviembre";"diciembre"},0),C4) -> 46265 | C8: 1480 | D8: 1535 | J8: Mercado Pago | K8: ='Gastos julio'!O8 -> 0.38704795 | L8: ='Gastos julio'!P8 -> 565.09 | N8: Mercado Libre | O8: =IFERROR(P8/$C$8,"") -> 0.38181757 | P8: =L8+SUMIF($E$24:$E$173,$N8,$C$24:$C$173)+SUMIF($E$24:$E$173,$N8,$D$24:$D$173) -> 565.09 | R8: Mercado Libre | S8: =IFERROR(IF(O8>K8,O8-K8,K8-O8),0) -> 0.0052303776 | T8: =IFERROR(IF(P8>L8,P8-L8,L8-P8),0) -> 0
J9: Brubank | K9: ='Gastos julio'!O9 -> 0.00093150685 | L9: ='Gastos julio'!P9 -> 1.36 | N9: Brubank | O9: =IFERROR(P9/$C$8,"") -> 0.00091891892 | P9: =L9+SUMIF($E$24:$E$173,$N9,$C$24:$C$173)+SUMIF($E$24:$E$173,$N9,$D$24:$D$173) -> 1.36 | R9: Brubank | S9: =IFERROR(IF(O9>K9,O9-K9,K9-O9),0) -> 1.258793e-05 | T9: =IFERROR(IF(P9>L9,P9-L9,L9-P9),0) -> 0
J10: Efectivo | K10: ='Gastos julio'!O10 -> 3.4246575 | L10: ='Gastos julio'!P10 -> 5000 | N10: Efectivo | O10: =IFERROR(P10/$C$8,"") -> 0 | P10: =L10+SUMIF($E$24:$E$173,$N10,$C$24:$C$173)+SUMIF($E$24:$E$173,$N10,$D$24:$D$173) -> 0 | R10: Efectivo | S10: =IFERROR(IF(O10>K10,O10-K10,K10-O10),0) -> 3.4246575 | T10: =IFERROR(IF(P10>L10,P10-L10,L10-P10),0) -> 5000
J12: Total | K12: =SUM(K2:K10) -> 13995.573 | L12: =SUM(L2:L10) -> 20958774 | N12: Total | O12: =SUM(O2:O9) -> 15019.928 | P12: =SUM(P2:P9) -> 22545039 | R12: Total | S12: =SUM(S2:S9) -> 1058.2834 | T12: =SUM(T2:T9) -> 1591264.5
B15: Compra/venta USD | J15: Análisis gastos e ingresos
B16: Nro. | C16: Ingresos | D16: Gastos | E16: Origen/Destino | F16: Concepto | G16: Descripción | H16: Fecha | J16: Concepto | K16: Acumulado egresos | L16: Acumulado ingresos | M16: Composición egresos | N16: Composición ingresos
B17: 1 | C17: 52.3 | E17: Caja de Ahorro Santander (USD) | F17: Pago tarjetas de crédito | G17: Compra USD para pagos tarjetas de crédito | H17: 46244 | J17: Pago Claude/Cursor | K17: =SUMIF($F$24:$F$173,$J17,$D$24:$D$173) -> 0 | L17: =SUMIF($F$24:$F$173,$J17,$C$24:$C$173) -> 60150 | M17: =IFERROR(K17/SUM(K$17:K$32),"") -> 0 | N17: =IFERROR(L17/SUM(L$17:L$32),"") -> 0.017455166
B18: 2 | D18: -37.14 | E18: Caja de Ahorro Santander (USD) | F18: Pago tarjetas de crédito | G18: Pago VISA USD | H18: 46244 | J18: Salidas a cenar/almorzar | K18: =SUMIF($F$24:$F$173,$J18,$C$24:$C$173)+SUMIF($F$24:$F$173,$J18,$D$24:$D$173) -> -255130.74 | L18: =SUMIF($F$24:$F$173,$J18,$C$24:$C$173) -> 21000 | M18: =IFERROR(K18/SUM(K$17:K$32),"") -> -0.11892798 | N18: =IFERROR(L18/SUM(L$17:L$32),"") -> 0.0060940731
B19: 3 | D19: -9.99 | E19: Caja de Ahorro Santander (USD) | F19: Pago tarjetas de crédito | G19: Pago AMEX USD | H19: 46244 | J19: Salidas a desyunar/merendar | K19: =SUMIF($F$24:$F$173,$J19,$C$24:$C$173)+SUMIF($F$24:$F$173,$J19,$D$24:$D$173) -> -25100 | L19: =SUMIF($F$24:$F$173,$J19,$C$24:$C$173) -> 0 | M19: =IFERROR(K19/SUM(K$17:K$32),"") -> -0.011700246 | N19: =IFERROR(L19/SUM(L$17:L$32),"") -> 0
J20: Salidas a tomar algo | K20: =SUMIF($F$24:$F$173,$J20,$C$24:$C$173)+SUMIF($F$24:$F$173,$J20,$D$24:$D$173) -> -75330 | L20: =SUMIF($F$24:$F$173,$J20,$C$24:$C$173) -> 41370 | M20: =IFERROR(K20/SUM(K$17:K$32),"") -> -0.035114722 | N20: =IFERROR(L20/SUM(L$17:L$32),"") -> 0.012005324
J21: Fiestas | K21: =SUMIF($F$24:$F$173,$J21,$C$24:$C$173)+SUMIF($F$24:$F$173,$J21,$D$24:$D$173) -> -24600 | L21: =SUMIF($F$24:$F$173,$J21,$C$24:$C$173) -> 0 | M21: =IFERROR(K21/SUM(K$17:K$32),"") -> -0.011467173 | N21: =IFERROR(L21/SUM(L$17:L$32),"") -> 0
B22: Movimientos en ARS | J22: Auto | K22: =SUMIF($F$24:$F$173,$J22,$C$24:$C$173)+SUMIF($F$24:$F$173,$J22,$D$24:$D$173) -> -125000 | L22: =SUMIF($F$24:$F$173,$J22,$C$24:$C$173) -> 50000 | M22: =IFERROR(K22/SUM(K$17:K$32),"") -> -0.058268156 | N22: =IFERROR(L22/SUM(L$17:L$32),"") -> 0.014509698
B23: Nro. | C23: Ingresos | D23: Gastos | E23: Origen/Destino | F23: Concepto | G23: Descripción | H23: Fecha | J23: Farmacia/Cosméticos | K23: =SUMIF($F$24:$F$173,$J23,$C$24:$C$173)+SUMIF($F$24:$F$173,$J23,$D$24:$D$173) -> -6686.31 | L23: =SUMIF($F$24:$F$173,$J23,$C$24:$C$173) -> 0 | M23: =IFERROR(K23/SUM(K$17:K$32),"") -> -0.0031167916 | N23: =IFERROR(L23/SUM(L$17:L$32),"") -> 0
B24: 1 | D24: -10000 | E24: Caja de Ahorro Santander (ARS) | F24: Salidas a desyunar/merendar | G24: Torta hábito | H24: 46235 | J24: Ropa | K24: =SUMIF($F$24:$F$173,$J24,$C$24:$C$173)+SUMIF($F$24:$F$173,$J24,$D$24:$D$173) -> 0 | L24: =SUMIF($F$24:$F$173,$J24,$C$24:$C$173) -> 0 | M24: =IFERROR(K24/SUM(K$17:K$32),"") -> 0 | N24: =IFERROR(L24/SUM(L$17:L$32),"") -> 0
B25: 2 | D25: -61200 | E25: Caja de Ahorro Santander (ARS) | F25: Salidas a tomar algo | G25: Tresca sofias | H25: 46235 | J25: Súper | K25: =SUMIF($F$24:$F$173,$J25,$C$24:$C$173)+SUMIF($F$24:$F$173,$J25,$D$24:$D$173) -> 0 | L25: =SUMIF($F$24:$F$173,$J25,$C$24:$C$173) -> 0 | M25: =IFERROR(K25/SUM(K$17:K$32),"") -> 0 | N25: =IFERROR(L25/SUM(L$17:L$32),"") -> 0
B26: 3 | D26: -50000 | E26: Caja de Ahorro Santander (ARS) | F26: Auto | G26: Nafta | H26: 46236 | J26: Delivery | K26: =SUMIF($F$24:$F$173,$J26,$C$24:$C$173)+SUMIF($F$24:$F$173,$J26,$D$24:$D$173) -> -18000 | L26: =SUMIF($F$24:$F$173,$J26,$C$24:$C$173) -> 19500 | M26: =IFERROR(K26/SUM(K$17:K$32),"") -> -0.0083906145 | N26: =IFERROR(L26/SUM(L$17:L$32),"") -> 0.0056587822
B27: 4 | C27: 68500 | E27: Caja de Ahorro Santander (ARS) | F27: Pago de honorarios Axis | G27: Semana 5 julio | H27: 46236 | J27: Regalos | K27: =SUMIF($F$24:$F$173,$J27,$C$24:$C$173)+SUMIF($F$24:$F$173,$J27,$D$24:$D$173) -> -12850 | L27: =SUMIF($F$24:$F$173,$J27,$C$24:$C$173) -> 396000 | M27: =IFERROR(K27/SUM(K$17:K$32),"") -> -0.0059899664 | N27: =IFERROR(L27/SUM(L$17:L$32),"") -> 0.11491681
B28: 5 | C28: 29700 | E28: Caja de Ahorro Santander (ARS) | F28: Salidas a tomar algo | G28: Devolución So H tresca | H28: 46236 | J28: Entradas fiestas/conciertos | K28: =SUMIF($F$24:$F$173,$J28,$C$24:$C$173)+SUMIF($F$24:$F$173,$J28,$D$24:$D$173) -> 0 | L28: =SUMIF($F$24:$F$173,$J28,$C$24:$C$173) -> 0 | M28: =IFERROR(K28/SUM(K$17:K$32),"") -> 0 | N28: =IFERROR(L28/SUM(L$17:L$32),"") -> 0
B29: 6 | D29: -40000 | E29: Caja de Ahorro Santander (ARS) | F29: Salidas a cenar/almorzar | G29: Devolución Igna Std | H29: 46236 | J29: Pago de honorarios Quantum | K29: =SUMIF($F$24:$F$173,$J29,$C$24:$C$173)+SUMIF($F$24:$F$173,$J29,$D$24:$D$173) -> 2094451.1 | L29: =SUMIF($F$24:$F$173,$J29,$C$24:$C$173) -> 2094451.1 | M29: =IFERROR(K29/SUM(K$17:K$32),"") -> 0.97631845 | N29: =IFERROR(L29/SUM(L$17:L$32),"") -> 0.60779706
B30: 7 | D30: -5000 | E30: Efectivo | F30: Salidas a cenar/almorzar | G30: Propina | H30: 46236 | J30: Pago de honorarios Axis | K30: =SUMIF($F$24:$F$173,$J30,$C$24:$C$173)+SUMIF($F$24:$F$173,$J30,$D$24:$D$173) -> 423500 | L30: =SUMIF($F$24:$F$173,$J30,$C$24:$C$173) -> 423500 | M30: =IFERROR(K30/SUM(K$17:K$32),"") -> 0.19741251 | N30: =IFERROR(L30/SUM(L$17:L$32),"") -> 0.12289714
B31: 8 | C31: 1900000 | E31: Superfondos Santander | F31: Inversiones FCI | G31: Suscripción sueldo julio | H31: 46237 | J31: Otros honorarios | K31: =SUMIF($F$24:$F$173,$J31,$C$24:$C$173)+SUMIF($F$24:$F$173,$J31,$D$24:$D$173) -> 170000 | L31: =SUMIF($F$24:$F$173,$J31,$C$24:$C$173) -> 340000 | M31: =IFERROR(K31/SUM(K$17:K$32),"") -> 0.079244692 | N31: =IFERROR(L31/SUM(L$17:L$32),"") -> 0.098665945
B32: 9 | D32: -1900000 | E32: Caja de Ahorro Santander (ARS) | F32: Inversiones FCI | G32: Suscripción sueldo julio | H32: 46237 | J32: Ahorros/inversiones | K32: =SUMIF($F$24:$F$173,$J32,$C$24:$C$173)+SUMIF($F$24:$F$173,$J32,$D$24:$D$173) -> 0 | L32: =SUMIF($F$24:$F$173,$J32,$C$24:$C$173) -> 0 | M32: =IFERROR(K32/SUM(K$17:K$32),"") -> 0 | N32: =IFERROR(L32/SUM(L$17:L$32),"") -> 0
B33: 10 | D33: -20000 | E33: Caja de Ahorro Santander (ARS) | F33: Auto | G33: Lavado auto | H33: 46237 | J33: Pago tarjetas de crédito | K33: =SUMIF($F$24:$F$173,$J33,$C$24:$C$173)+SUMIF($F$24:$F$173,$J33,$D$24:$D$173) -> -309765.61 | L33: =SUMIF($F$24:$F$173,$J33,$C$24:$C$173) -> 52.3 | M33: =IFERROR(K33/SUM(K$17:K$32),"") -> -0.14439577 | N33: =IFERROR(L33/SUM(L$17:L$32),"") -> 1.5177144e-05
B34: 11 | D34: -35000 | E34: Caja de Ahorro Santander (ARS) | F34: Salidas a cenar/almorzar | G34: Edición 1: La cocina rica rica de Pacho | H34: 46238
B35: 12 | D35: -6686.31 | E35: Caja de Ahorro Santander (ARS) | F35: Farmacia/Cosméticos | G35: Tampones | H35: 46238 | J35: Superfondos Santander
B36: 13 | D36: -37500 | E36: Caja de Ahorro Santander (ARS) | F36: Delivery | G36: Burgers Igna | H36: 46238 | J36: Superfondos Santander | K36: 46237 | L36: 46244 | M36: 46251 | N36: 46258 | O36: 46265
B37: 14 | C37: 19500 | E37: Caja de Ahorro Santander (ARS) | F37: Delivery | G37: Dev burgers Igna | H37: 46238 | J37: Calculado | K37: =$L$5+SUMIFS($C$24:$C$173,$E$24:$E$173,$N5,$H$24:$H$173,"<="&K$36)+SUMIFS($D$24:$D$173,$E$24:$E$173,$N5,$H$24:$H$173,"<="&K$36) -> 3256368.8 | L37: =$L$5+SUMIFS($C$24:$C$173,$E$24:$E$173,$N5,$H$24:$H$173,"<"&L$36)+SUMIFS($D$24:$D$173,$E$24:$E$173,$N5,$H$24:$H$173,"<="&L$36) -> 2876368.8 | M37: =$L$5+SUMIFS($C$24:$C$173,$E$24:$E$173,$N5,$H$24:$H$173,"<"&M$36)+SUMIFS($D$24:$D$173,$E$24:$E$173,$N5,$H$24:$H$173,"<="&M$36) -> 3026368.8 | N37: =$L$5+SUMIFS($C$24:$C$173,$E$24:$E$173,$N5,$H$24:$H$173,"<"&N$36)+SUMIFS($D$24:$D$173,$E$24:$E$173,$N5,$H$24:$H$173,"<="&N$36) -> 2776368.8 | O37: =$L$5+SUMIFS($C$24:$C$173,$E$24:$E$173,$N5,$H$24:$H$173,"<"&O$36)+SUMIFS($D$24:$D$173,$E$24:$E$173,$N5,$H$24:$H$173,"<="&O$36) -> 2886368.8
B38: 15 | D38: -16900 | E38: Caja de Ahorro Santander (ARS) | F38: Salidas a cenar/almorzar | G38: Vino cena Nacho | H38: 46239 | J38: Real | K38: 3275661.5 | L38: 2905138.8 | M38: 3065231.6 | N38: 2826525.1 | O38: 2947715
B39: 16 | D39: -7000 | E39: Caja de Ahorro Santander (ARS) | F39: Celular | G39: Compra datos | H39: 46240 | J39: Rendimiento (neto) | K39: =IF(K38="","",K38-K37) -> 19292.69 | L39: =IF(L38="","",L38-L37) -> 28770 | M39: =IF(M38="","",M38-M37) -> 38862.82 | N39: =IF(N38="","",N38-N37) -> 50156.38 | O39: =IF(O38="","",O38-O37) -> 61346.18
B40: 17 | D40: -45000 | E40: Caja de Ahorro Santander (ARS) | F40: Psicóloga | G40: 1ra sesión agosto psico | H40: 46240 | J40: Rendimiento (%) | K40: =IF(K39="","",((K38-K37)/K37)) -> 0.0059246023 | L40: =IF(L39="","",((L38-L37)/L37)) -> 0.010002195 | M40: =IF(M39="","",((M38-M37)/M37)) -> 0.012841403 | N40: =IF(N39="","",((N38-N37)/N37)) -> 0.01806546 | O40: =IF(O39="","",((O38-O37)/O37)) -> 0.021253757
B41: 18 | D41: -80000 | E41: Superfondos Santander | F41: Rescates FCI | G41: Rescate p psico | H41: 46240
B42: 19 | C42: 80000 | E42: Caja de Ahorro Santander (ARS) | F42: Rescates FCI | G42: Rescate p psico | H42: 46240 | J42: Petrini
B43: 20 | D43: -14800 | E43: Caja de Ahorro Santander (ARS) | F43: Salidas a cenar/almorzar | G43: Lomitos 348 | H43: 46240 | J43: Fecha | K43: 46237 | L43: 46244 | M43: 46251 | N43: 46258 | O43: 46265
B44: 21 | D44: -93250.74 | E44: Caja de Ahorro Santander (ARS) | F44: Salidas a cenar/almorzar | G44: Compras SMP | H44: 46241 | J44: Tenencia calculada | K44: =$L$4+SUMIFS($D$24:$D$173,$G$24:$G$173,"Transferencia a Petrini",$H$24:$H$173,"<"&K$36)*-1+SUMIFS($D$24:$D$173,$G$24:$G$173,"Transferencia de Petrini",$H$24:$H$173,"<"&K$36) -> 1647262.6 | L44: =$L$4+SUMIFS($D$24:$D$173,$G$24:$G$173,"Transferencia a Petrini",$H$24:$H$173,"<"&L$36)*-1+SUMIFS($D$24:$D$173,$G$24:$G$173,"Transferencia de Petrini",$H$24:$H$173,"<"&L$36) -> 1647262.6 | M44: =$L$4+SUMIFS($D$24:$D$173,$G$24:$G$173,"Transferencia a Petrini",$H$24:$H$173,"<"&M$36)*-1+SUMIFS($D$24:$D$173,$G$24:$G$173,"Transferencia de Petrini",$H$24:$H$173,"<"&M$36) -> 1647262.6 | N44: =$L$4+SUMIFS($D$24:$D$173,$G$24:$G$173,"Transferencia a Petrini",$H$24:$H$173,"<"&N$36)*-1+SUMIFS($D$24:$D$173,$G$24:$G$173,"Transferencia de Petrini",$H$24:$H$173,"<"&N$36) -> 1647262.6 | O44: =$L$4+SUMIFS($D$24:$D$173,$G$24:$G$173,"Transferencia a Petrini",$H$24:$H$173,"<"&O$36)*-1+SUMIFS($D$24:$D$173,$G$24:$G$173,"Transferencia de Petrini",$H$24:$H$173,"<"&O$36) -> 1647262.6
B45: 22 | D45: -150000 | E45: Superfondos Santander | F45: Rescates FCI | G45: Rescate p finde | H45: 46241 | J45: Tenencia real | K45: 1658392.3 | L45: 1680876.1 | M45: 1687843 | N45: 1682587.4 | O45: 1694129.2
B46: 23 | C46: 150000 | E46: Caja de Ahorro Santander (ARS) | F46: Rescates FCI | G46: Rescate p finde | H46: 46241 | J46: Rendimiento (neto) | K46: =IF(K45="","",K45-K44) -> 11129.67 | L46: =IF(L45="","",L45-L44) -> 33613.43 | M46: =IF(M45="","",M45-M44) -> 40580.41 | N46: =IF(N45="","",N45-N44) -> 35324.81 | O46: =IF(O45="","",O45-O44) -> 46866.56
B47: 24 | C47: 21000 | E47: Caja de Ahorro Santander (ARS) | F47: Salidas a cenar/almorzar | G47: Devolucion LCP | H47: 46241 | J47: Rendimiento (%) | K47: =IF(K46="","",((K45-K44)/K44)) -> 0.0067564636 | L47: =IF(L46="","",((L45-L44)/L44)) -> 0.020405629 | M47: =IF(M46="","",((M45-M44)/M44)) -> 0.024635058 | N47: =IF(N46="","",((N45-N44)/N44)) -> 0.021444553 | O47: =IF(O46="","",((O45-O44)/O44)) -> 0.028451177
B48: 25 | C48: 79000 | E48: Caja de Ahorro Santander (ARS) | F48: Pago de honorarios Axis | G48: Semana 1 agosto | H48: 46244
B49: 26 | C49: 30200 | E49: Caja de Ahorro Santander (ARS) | F49: Pago Claude/Cursor | G49: Pago Igna IA | H49: 46244
B50: 27 | D50: -150000 | E50: Superfondos Santander | F50: Rescates FCI | G50: Rescat p pagar tarjetas | H50: 46244
B51: 28 | C51: 150000 | E51: Caja de Ahorro Santander (ARS) | F51: Rescates FCI | G51: Rescat p pagar tarjetas | H51: 46244
B52: 29 | D52: -226321.54 | E52: Caja de Ahorro Santander (ARS) | F52: Pago tarjetas de crédito | G52: Pago VISA ARS | H52: 46244
B53: 30 | D53: -79496 | E53: Caja de Ahorro Santander (ARS) | F53: Pago tarjetas de crédito | G53: Compra USD p tarjetas | H53: 46244
B54: 31 | D54: -3953.24 | E54: Caja de Ahorro Santander (ARS) | F54: Pago tarjetas de crédito | G54: Pago AMEX ARS | H54: 46244
B55: 32 | C55: 52.3 | E55: Caja de Ahorro Santander (USD) | F55: Pago tarjetas de crédito | G55: Compra USD p tarjetas | H55: 46244
B56: 33 | D56: -37.14 | E56: Caja de Ahorro Santander (USD) | F56: Pago tarjetas de crédito | G56: Pago VISA USD | H56: 46244
B57: 34 | D57: -9.99 | E57: Caja de Ahorro Santander (USD) | F57: Pago tarjetas de crédito | G57: Pago AMEX USD | H57: 46244
B58: 35 | C58: 25000 | E58: Efectivo | F58: Transferencias Jo | G58: Dev Jose | H58: 46244
B59: 36 | C59: 50000 | E59: Efectivo | F59: Auto | G59: Nafta Pa | H59: 46244
B60: 37 | D60: -35000 | E60: Efectivo | F60: Salidas a cenar/almorzar | G60: Cena Agus | H60: 46244
B61: 38 | C61: 340000 | E61: Caja de Ahorro Santander (ARS) | F61: Otros honorarios | G61: Primer pago MV (md) | H61: 46244
B62: 39 | D62: -170000 | E62: Caja de Ahorro Santander (ARS) | F62: Otros honorarios | G62: Transf IM primer pago MV (md) | H62: 46244
B63: 40 | C63: 200000 | E63: Superfondos Santander | F63: Inversiones FCI | G63: Suscripción honorarios md | H63: 46245
B64: 41 | D64: -200000 | E64: Caja de Ahorro Santander (ARS) | F64: Inversiones FCI | G64: Suscripción honorarios md | H64: 46245
B65: 42 | D65: -40000 | E65: Efectivo | F65: Auto | G65: Nafta | H65: 46246
B66: 43 | C66: 30000 | E66: Efectivo | F66: Regalos | G66: Delivery padres | H66: 46246
B67: 44 | D67: -50000 | E67: Superfondos Santander | F67: Rescates FCI | G67: Rescate p finde | H67: 46248
B68: 45 | C68: 50000 | E68: Caja de Ahorro Santander (ARS) | F68: Rescates FCI | G68: Rescate p finde | H68: 46248
B69: 46 | D69: -11180 | E69: Caja de Ahorro Santander (ARS) | F69: Salidas a cenar/almorzar | G69: Vino cena chicas Q | H69: 46248
B70: 47 | D70: -20000 | E70: Caja de Ahorro Santander (ARS) | F70: Salidas a cenar/almorzar | G70: Sushi cena chicas Q | H70: 46248
B71: 48 | D71: -10000 | E71: Caja de Ahorro Santander (ARS) | F71: Auto | G71: Cochera cena chicas Q | H71: 46248
B72: 49 | D72: -13500 | E72: Caja de Ahorro Santander (ARS) | F72: Salidas a tomar algo | G72: Jangadero | H72: 46249
B73: 50 | C73: 79000 | E73: Caja de Ahorro Santander (ARS) | F73: Pago de honorarios Axis | G73: Semana 2 agosto | H73: 46249
B74: 51 | D74: -14700 | E74: Caja de Ahorro Santander (ARS) | F74: Juntadas a cenar/almorzar | G74: Almuerzo Igna sábado | H74: 46249
B75: 52 | C75: 142000 | E75: Caja de Ahorro Santander (ARS) | F75: Juntadas a cenar/almorzar | G75: Asado domingo | H75: 46250
B76: 53 | D76: -142396.27 | E76: Caja de Ahorro Santander (ARS) | F76: Juntadas a cenar/almorzar | G76: Asado domingo super | H76: 46250
B77: 54 | D77: -10998 | E77: Caja de Ahorro Santander (ARS) | F77: Juntadas a cenar/almorzar | G77: Asado domingo carbón | H77: 46250
B78: 55 | D78: -36050 | E78: Caja de Ahorro Santander (ARS) | F78: Juntadas a cenar/almorzar | G78: Devoluc. Igna asado | H78: 46251
B79: 56 | D79: -24020 | E79: Caja de Ahorro Santander (ARS) | F79: Juntadas a cenar/almorzar | G79: Panchos NB | H79: 46251
B80: 57 | D80: -50000 | E80: Superfondos Santander | F80: Rescates FCI | G80: Rescate p pagar monotributo | H80: 46252
B81: 58 | C81: 50000 | E81: Caja de Ahorro Santander (ARS) | F81: Rescates FCI | G81: Rescate p pagar monotributo | H81: 46252
B82: 59 | D82: -56400 | E82: Caja de Ahorro Santander (ARS) | F82: Pago monotributo | G82: Transf a MP | H82: 46252
B83: 60 | D83: -56379.08 | E83: Mercado Pago | F83: Pago monotributo | G83: Pago monotributo | H83: 46252
B84: 61 | C84: 56400 | E84: Mercado Pago | F84: Pago monotributo | G84: Transf desde santander | H84: 46252
B85: 62 | D85: -3200 | E85: Caja de Ahorro Santander (ARS) | F85: Regalos | G85: Transf Bra copas cie | H85: 46253
B86: 63 | D86: -45000 | E86: Caja de Ahorro Santander (ARS) | F86: Psicóloga | G86: Sesión perdida | H86: 46253
B87: 64 | D87: -16000 | E87: Caja de Ahorro Santander (ARS) | F87: Fiestas | G87: Entrada terrafuria | H87: 46253
B88: 65 | D88: -8400 | E88: Caja de Ahorro Santander (ARS) | F88: Salidas a desyunar/merendar | G88: Churros | H88: 46253
B89: 68 | D89: -100000 | E89: Superfondos Santander | F89: Rescates FCI | G89: Rescate | H89: 46253
B90: 69 | C90: 100000 | E90: Caja de Ahorro Santander (ARS) | F90: Rescates FCI | G90: Rescate | H90: 46253
B91: 66 | C91: 366000 | E91: Caja de Ahorro Santander (ARS) | F91: Regalos | G91: Transferencias regalo IM | H91: 46254
B92: 67 | D92: -396750 | E92: Caja de Ahorro Santander (ARS) | F92: Regalos | G92: Entrada IM | H92: 46254
B93: 70 | D93: -100000 | E93: Superfondos Santander | F93: Rescates FCI | G93: Rescate p regalo IM | H93: 46254
B94: 71 | C94: 100000 | E94: Caja de Ahorro Santander (ARS) | F94: Rescates FCI | G94: Rescate p regalo IM | H94: 46254
B95: 72 | D95: -8600 | E95: Caja de Ahorro Santander (ARS) | F95: Fiestas | G95: Transf IM sorpresit | H95: 46255
B96: 73 | D96: -22000 | E96: Caja de Ahorro Santander (ARS) | F96: Salidas a tomar algo | G96: Fernet jangadero | H96: 46256
B97: 74 | C97: 134000 | E97: Caja de Ahorro Santander (ARS) | F97: Pago de honorarios Axis | G97: Semana 3 agosto | H97: 46256
B98: 75 | D98: -10000 | E98: Caja de Ahorro Santander (ARS) | F98: Transferencias Jo | G98: Prestamo Jo | H98: 46256
B99: 76 | D99: -25000 | E99: Efectivo | F99: Auto | G99: Cochera jangadero | H99: 46256
B100: 77 | D100: -5000 | E100: Efectivo | F100: Salidas a cenar/almorzar | G100: Propina el cuadrado | H100: 46257
B101: 78 | C101: 200000 | E101: Superfondos Santander | F101: Inversiones FCI | G101: Inversión lunes 24/8 | H101: 46258
B102: 79 | D102: -200000 | E102: Caja de Ahorro Santander (ARS) | F102: Inversiones FCI | G102: Inversión lunes 24/8 | H102: 46258
B103: 80 | D103: -6700 | E103: Caja de Ahorro Santander (ARS) | F103: Salidas a desyunar/merendar | G103: Roll de canela | H103: 46258
...

Sheet Gastos septiembre
B1: Datos del periodo | J1: Tenencia - Inicio | K1: USD | L1: ARS | N1: Tenencia - Fin | O1: USD | P1: ARS | R1: Diferencia | S1: USD | T1: ARS
B2: Año: | C2: 2026 | J2: Regalo recibida | K2: ='Gastos agosto'!O2 -> 10000 | L2: =K2*D7 -> 15350000 | N2: Regalo recibida | O2: =K2+SUMIF($E$24:$E$173,$N2,$C$24:$C$173)+SUMIF($E$24:$E$173,$N2,$D$24:$D$173) -> 10000 | P2: =O2*$D$7 -> 15350000 | R2: Regalo recibida | S2: =IFERROR(IF(O2>K2,O2-K2,K2-O2),0) -> 0 | T2: =IFERROR(IF(P2>L2,P2-L2,L2-P2),0) -> 0
B3: Mes: | C3: septiembre | J3: Caja de seguridad | K3: ='Gastos agosto'!O3 -> 500 | L3: =K3*D7 -> 767500 | N3: Caja de seguridad | O3: =K3 -> 500 | P3: =L3+SUMIF($E$24:$E$173,$N3,$C$24:$C$173)+SUMIF($E$24:$E$173,$N3,$D$24:$D$173) -> 767500 | R3: Caja de seguridad | S3: =IFERROR(IF(O3>K3,O3-K3,K3-O3),0) -> 0 | T3: =IFERROR(IF(P3>L3,P3-L3,L3-P3),0) -> 0
B4: Cantidad de días: | C4: =DAY(EOMONTH(DATE($C$2,MATCH($C$3,{"enero";"febrero";"marzo";"abril";"mayo";"junio";"julio";"agosto";"septiembre";"octubre";"noviembre";"diciembre"},0),1),0)) -> 30 | J4: Cta. Comitente Petrini | K4: ='Gastos agosto'!O4 -> 1113.0153 | L4: ='Gastos agosto'!P4 -> 1647262.6 | N4: Cta. Comitente Petrini | O4: =IFERROR(P4/$C$8,"") | P4: =L4+SUMIF($E$24:$E$173,$N4,$C$24:$C$173)+SUMIF($E$24:$E$173,$N4,$D$24:$D$173) -> 1647262.6 | R4: Cta. Comitente Petrini | S4: =IFERROR(IF(O4>K4,O4-K4,K4-O4),0) -> 0 | T4: =IFERROR(IF(P4>L4,P4-L4,L4-P4),0) -> 0
J5: Superfondos Santander | K5: ='Gastos agosto'!O5 -> 1950.2492 | L5: ='Gastos agosto'!P5 -> 2886368.8 | N5: Superfondos Santander | O5: =IFERROR(P5/$C$8,"") | P5: =L5+SUMIF($E$24:$E$173,$N5,$C$24:$C$173)+SUMIF($E$24:$E$173,$N5,$D$24:$D$173) -> 3896368.8 | R5: Superfondos Santander | S5: =IFERROR(IF(O5>K5,O5-K5,K5-O5),0) -> 0 | T5: =IFERROR(IF(P5>L5,P5-L5,L5-P5),0) -> 1010000
B6: Tc (BNA) | C6: Compra | D6: Venta | J6: Caja de Ahorro Santander (ARS) | K6: ='Gastos agosto'!O6 -> 1446.3709 | L6: ='Gastos agosto'!P6 -> 2140629 | N6: Caja de Ahorro Santander (ARS) | O6: =IFERROR(P6/$C$8,"") | P6: =L6+SUMIF($E$24:$E$173,$N6,$C$24:$C$173)+SUMIF($E$24:$E$173,$N6,$D$24:$D$173) -> 5648.43 | R6: Caja de Ahorro Santander (ARS) | S6: =IFERROR(IF(O6>K6,O6-K6,K6-O6),0) -> 0 | T6: =IFERROR(IF(P6>L6,P6-L6,L6-P6),0) -> 2134980.6
B7: =DATE($C$2,MATCH($C$3,{"enero";"febrero";"marzo";"abril";"mayo";"junio";"julio";"agosto";"septiembre";"octubre";"noviembre";"diciembre"},0),1) -> 46266 | C7: 1485 | D7: 1535 | J7: Caja de Ahorro Santander (USD) | K7: ='Gastos agosto'!O7 -> 9.91 | L7: =K7*D7 -> 15211.85 | N7: Caja de Ahorro Santander (USD) | O7: =K7+SUM(C17:C19)+SUM(D17:D19) -> 1.88 | P7: =O7*$D$8 -> 0 | R7: Caja de Ahorro Santander (USD) | S7: =IFERROR(IF(O7>K7,O7-K7,K7-O7),0) -> 8.03 | T7: =IFERROR(IF(P7>L7,P7-L7,L7-P7),0) -> 15211.85
B8: =DATE($C$2,MATCH($C$3,{"enero";"febrero";"marzo";"abril";"mayo";"junio";"julio";"agosto";"septiembre";"octubre";"noviembre";"diciembre"},0),C4) -> 46295 | J8: Mercado Pago | K8: ='Gastos agosto'!O8 -> 0.38181757 | L8: ='Gastos agosto'!P8 -> 565.09 | N8: Mercado Libre | O8: =IFERROR(P8/$C$8,"") | P8: =L8+SUMIF($E$24:$E$173,$N8,$C$24:$C$173)+SUMIF($E$24:$E$173,$N8,$D$24:$D$173) -> 565.09 | R8: Mercado Libre | S8: =IFERROR(IF(O8>K8,O8-K8,K8-O8),0) -> 0 | T8: =IFERROR(IF(P8>L8,P8-L8,L8-P8),0) -> 0
J9: Brubank | K9: ='Gastos agosto'!O9 -> 0.00091891892 | L9: ='Gastos agosto'!P9 -> 1.36 | N9: Brubank | O9: =IFERROR(P9/$C$8,"") | P9: =L9+SUMIF($E$24:$E$173,$N9,$C$24:$C$173)+SUMIF($E$24:$E$173,$N9,$D$24:$D$173) -> 1.36 | R9: Brubank | S9: =IFERROR(IF(O9>K9,O9-K9,K9-O9),0) -> 0 | T9: =IFERROR(IF(P9>L9,P9-L9,L9-P9),0) -> 0
J10: Efectivo | K10: ='Gastos agosto'!O10 -> 0 | L10: ='Gastos agosto'!P10 -> 0 | N10: Efectivo | O10: =IFERROR(P10/$C$8,"") | P10: =L10+SUMIF($E$24:$E$173,$N10,$C$24:$C$173)+SUMIF($E$24:$E$173,$N10,$D$24:$D$173) -> 32600 | R10: Efectivo | S10: =IFERROR(IF(O10>K10,O10-K10,K10-O10),0) -> 0 | T10: =IFERROR(IF(P10>L10,P10-L10,L10-P10),0) -> 32600
J12: Total | K12: =SUM(K2:K10) -> 15019.928 | L12: =SUM(L2:L10) -> 22807539 | N12: Total | O12: =SUM(O2:O9) -> 10501.88 | P12: =SUM(P2:P9) -> 21667346 | R12: Total | S12: =SUM(S2:S9) -> 8.03 | T12: =SUM(T2:T9) -> 3160192.4
B15: Compra/venta USD | J15: Análisis gastos e ingresos
B16: Nro. | C16: Ingresos | D16: Gastos | E16: Origen/Destino | F16: Concepto | G16: Descripción | H16: Fecha | J16: Concepto | K16: Acumulado egresos | L16: Acumulado ingresos | M16: Composición egresos | N16: Composición ingresos
B17: 1 | C17: 50 | E17: Caja de Ahorro Santander (USD) | F17: Pago tarjetas de crédito | G17: Compra USD para pagos tarjetas de crédito | H17: 46268 | J17: Pago Claude/Cursor | K17: =SUMIF($F$24:$F$173,$J17,$D$24:$D$173) -> 0 | L17: =SUMIF($F$24:$F$173,$J17,$C$24:$C$173) -> 0 | M17: =IFERROR(K17/SUM(K$17:K$32),"") -> 0 | N17: =IFERROR(L17/SUM(L$17:L$32),"") -> 0
B18: 2 | D18: -48.04 | E18: Caja de Ahorro Santander (USD) | F18: Pago tarjetas de crédito | G18: Pago VISA USD | H18: 46268 | J18: Salidas a cenar/almorzar | K18: =SUMIF($F$24:$F$173,$J18,$C$24:$C$173)+SUMIF($F$24:$F$173,$J18,$D$24:$D$173) -> -39300 | L18: =SUMIF($F$24:$F$173,$J18,$C$24:$C$173) -> 0 | M18: =IFERROR(K18/SUM(K$17:K$32),"") -> 0.33558675 | N18: =IFERROR(L18/SUM(L$17:L$32),"") -> 0
B19: 3 | D19: -9.99 | E19: Caja de Ahorro Santander (USD) | F19: Pago tarjetas de crédito | G19: Pago AMEX USD | H19: 46268 | J19: Salidas a desyunar/merendar | K19: =SUMIF($F$24:$F$173,$J19,$C$24:$C$173)+SUMIF($F$24:$F$173,$J19,$D$24:$D$173) -> -55400 | L19: =SUMIF($F$24:$F$173,$J19,$C$24:$C$173) -> 0 | M19: =IFERROR(K19/SUM(K$17:K$32),"") -> 0.4730663 | N19: =IFERROR(L19/SUM(L$17:L$32),"") -> 0
J20: Salidas a tomar algo | K20: =SUMIF($F$24:$F$173,$J20,$C$24:$C$173)+SUMIF($F$24:$F$173,$J20,$D$24:$D$173) -> -71900 | L20: =SUMIF($F$24:$F$173,$J20,$C$24:$C$173) -> 0 | M20: =IFERROR(K20/SUM(K$17:K$32),"") -> 0.6139615 | N20: =IFERROR(L20/SUM(L$17:L$32),"") -> 0
J21: Fiestas | K21: =SUMIF($F$24:$F$173,$J21,$C$24:$C$173)+SUMIF($F$24:$F$173,$J21,$D$24:$D$173) -> 0 | L21: =SUMIF($F$24:$F$173,$J21,$C$24:$C$173) -> 0 | M21: =IFERROR(K21/SUM(K$17:K$32),"") -> 0 | N21: =IFERROR(L21/SUM(L$17:L$32),"") -> 0
B22: Movimientos en ARS | J22: Auto | K22: =SUMIF($F$24:$F$173,$J22,$C$24:$C$173)+SUMIF($F$24:$F$173,$J22,$D$24:$D$173) -> -56000 | L22: =SUMIF($F$24:$F$173,$J22,$C$24:$C$173) -> 220000 | M22: =IFERROR(K22/SUM(K$17:K$32),"") -> 0.47818976 | N22: =IFERROR(L22/SUM(L$17:L$32),"") -> 0.43912176
B23: Nro. | C23: Ingresos | D23: Gastos | E23: Origen/Destino | F23: Concepto | G23: Descripción | H23: Fecha | J23: Farmacia/Cosméticos | K23: =SUMIF($F$24:$F$173,$J23,$C$24:$C$173)+SUMIF($F$24:$F$173,$J23,$D$24:$D$173) -> -21560.32 | L23: =SUMIF($F$24:$F$173,$J23,$C$24:$C$173) -> 0 | M23: =IFERROR(K23/SUM(K$17:K$32),"") -> 0.18410579 | N23: =IFERROR(L23/SUM(L$17:L$32),"") -> 0
B24: 1 | D24: -50000 | E24: Caja de Ahorro Santander (ARS) | F24: Auto | G24: Nafta | H24: 46266 | J24: Ropa | K24: =SUMIF($F$24:$F$173,$J24,$C$24:$C$173)+SUMIF($F$24:$F$173,$J24,$D$24:$D$173) -> 0 | L24: =SUMIF($F$24:$F$173,$J24,$C$24:$C$173) -> 0 | M24: =IFERROR(K24/SUM(K$17:K$32),"") -> 0 | N24: =IFERROR(L24/SUM(L$17:L$32),"") -> 0
B25: 2 | D25: -6686.32 | E25: Caja de Ahorro Santander (ARS) | F25: Farmacia/Cosméticos | G25: Tampones | H25: 46266 | J25: Súper | K25: =SUMIF($F$24:$F$173,$J25,$C$24:$C$173)+SUMIF($F$24:$F$173,$J25,$D$24:$D$173) -> -34048 | L25: =SUMIF($F$24:$F$173,$J25,$C$24:$C$173) -> 20000 | M25: =IFERROR(K25/SUM(K$17:K$32),"") -> 0.29073938 | N25: =IFERROR(L25/SUM(L$17:L$32),"") -> 0.03992016
B26: 3 | D26: -20000 | E26: Caja de Ahorro Santander (ARS) | F26: Regalos | G26: Lavado auto Jo | H26: 46266 | J26: Delivery | K26: =SUMIF($F$24:$F$173,$J26,$C$24:$C$173)+SUMIF($F$24:$F$173,$J26,$D$24:$D$173) -> 0 | L26: =SUMIF($F$24:$F$173,$J26,$C$24:$C$173) -> 0 | M26: =IFERROR(K26/SUM(K$17:K$32),"") -> 0 | N26: =IFERROR(L26/SUM(L$17:L$32),"") -> 0
B27: 4 | C27: 2000000 | E27: Superfondos Santander | F27: Inversiones FCI | G27: Suscripción honorarios agosto | H27: 46266 | J27: Regalos | K27: =SUMIF($F$24:$F$173,$J27,$C$24:$C$173)+SUMIF($F$24:$F$173,$J27,$D$24:$D$173) -> -39900 | L27: =SUMIF($F$24:$F$173,$J27,$C$24:$C$173) -> 60000 | M27: =IFERROR(K27/SUM(K$17:K$32),"") -> 0.34071021 | N27: =IFERROR(L27/SUM(L$17:L$32),"") -> 0.11976048
B28: 5 | D28: -2000000 | E28: Caja de Ahorro Santander (ARS) | F28: Inversiones FCI | G28: Suscripción honorarios agosto | H28: 46266 | J28: Entradas fiestas/conciertos | K28: =SUMIF($F$24:$F$173,$J28,$C$24:$C$173)+SUMIF($F$24:$F$173,$J28,$D$24:$D$173) -> 0 | L28: =SUMIF($F$24:$F$173,$J28,$C$24:$C$173) -> 0 | M28: =IFERROR(K28/SUM(K$17:K$32),"") -> 0 | N28: =IFERROR(L28/SUM(L$17:L$32),"") -> 0
B29: 6 | D29: -22500 | E29: Caja de Ahorro Santander (ARS) | F29: Juntadas a cenar/almorzar | G29: Sushi cielo y brana | H29: 46266 | J29: Pago de honorarios Quantum | K29: =SUMIF($F$24:$F$173,$J29,$C$24:$C$173)+SUMIF($F$24:$F$173,$J29,$D$24:$D$173) -> 0 | L29: =SUMIF($F$24:$F$173,$J29,$C$24:$C$173) -> 0 | M29: =IFERROR(K29/SUM(K$17:K$32),"") -> 0 | N29: =IFERROR(L29/SUM(L$17:L$32),"") -> 0
B30: 7 | D30: -10000 | E30: Caja de Ahorro Santander (ARS) | F30: Juntadas a cenar/almorzar | G30: Cochera cena cielo y bra | H30: 46266 | J30: Pago de honorarios Axis | K30: =SUMIF($F$24:$F$173,$J30,$C$24:$C$173)+SUMIF($F$24:$F$173,$J30,$D$24:$D$173) -> 201000 | L30: =SUMIF($F$24:$F$173,$J30,$C$24:$C$173) -> 201000 | M30: =IFERROR(K30/SUM(K$17:K$32),"") -> -1.7163597 | N30: =IFERROR(L30/SUM(L$17:L$32),"") -> 0.4011976
B31: 8 | D31: -4900 | E31: Caja de Ahorro Santander (ARS) | F31: Súper | G31: Panadería Cofico | H31: 46267 | J31: Otros honorarios | K31: =SUMIF($F$24:$F$173,$J31,$C$24:$C$173)+SUMIF($F$24:$F$173,$J31,$D$24:$D$173) -> 0 | L31: =SUMIF($F$24:$F$173,$J31,$C$24:$C$173) -> 0 | M31: =IFERROR(K31/SUM(K$17:K$32),"") -> 0 | N31: =IFERROR(L31/SUM(L$17:L$32),"") -> 0
B32: 9 | D32: -14874 | E32: Caja de Ahorro Santander (ARS) | F32: Farmacia/Cosméticos | G32: Corega tabs e hilo dental | H32: 46268 | J32: Ahorros/inversiones | K32: =SUMIF($F$24:$F$173,$J32,$C$24:$C$173)+SUMIF($F$24:$F$173,$J32,$D$24:$D$173) -> 0 | L32: =SUMIF($F$24:$F$173,$J32,$C$24:$C$173) -> 0 | M32: =IFERROR(K32/SUM(K$17:K$32),"") -> 0 | N32: =IFERROR(L32/SUM(L$17:L$32),"") -> 0
B33: 10 | C33: 30000 | E33: Efectivo | F33: Mascotas | G33: Devolución cucha | H33: 46268 | J33: Pago tarjetas de crédito | K33: =SUMIF($F$24:$F$173,$J33,$C$24:$C$173)+SUMIF($F$24:$F$173,$J33,$D$24:$D$173) -> -336416.98 | L33: =SUMIF($F$24:$F$173,$J33,$C$24:$C$173) -> 50 | M33: =IFERROR(K33/SUM(K$17:K$32),"") -> 2.8726992 | N33: =IFERROR(L33/SUM(L$17:L$32),"") -> 9.9800399e-05
B34: 11 | D34: -500000 | E34: Superfondos Santander | F34: Rescates FCI | G34: Rescate p pagar tarjetas de crédito | H34: 46268
B35: 12 | C35: 500000 | E35: Caja de Ahorro Santander (ARS) | F35: Rescates FCI | G35: Rescate p pagar tarjetas de crédito | H35: 46268 | J35: Superfondos Santander
B36: 13 | D36: -46000 | E36: Caja de Ahorro Santander (ARS) | F36: Entradas fiestas/conciertos/otros eventos | G36: An Espil x2 entradas | H36: 46268 | J36: Superfondos Santander | K36: 46272 | L36: 46279 | M36: 46286 | N36: 46293
B37: 14 | D37: -255875.44 | E37: Caja de Ahorro Santander (ARS) | F37: Pago tarjetas de crédito | G37: VISA ARS agosto | H37: 46268 | J37: Calculado | K37: =$L$5+SUMIFS($C$24:$C$173,$E$24:$E$173,$N5,$H$24:$H$173,"<="&K$36)+SUMIFS($D$24:$D$173,$E$24:$E$173,$N5,$H$24:$H$173,"<="&K$36) -> 4386368.8 | L37: =$L$5+SUMIFS($C$24:$C$173,$E$24:$E$173,$N5,$H$24:$H$173,"<"&L$36)+SUMIFS($D$24:$D$173,$E$24:$E$173,$N5,$H$24:$H$173,"<="&L$36) -> 3986368.8 | M37: =$L$5+SUMIFS($C$24:$C$173,$E$24:$E$173,$N5,$H$24:$H$173,"<"&M$36)+SUMIFS($D$24:$D$173,$E$24:$E$173,$N5,$H$24:$H$173,"<="&M$36) -> 3896368.8 | N37: =$L$5+SUMIFS($C$24:$C$173,$E$24:$E$173,$N5,$H$24:$H$173,"<"&N$36)+SUMIFS($D$24:$D$173,$E$24:$E$173,$N5,$H$24:$H$173,"<="&N$36) -> 3896368.8
B38: 15 | D38: -76500 | E38: Caja de Ahorro Santander (ARS) | F38: Pago tarjetas de crédito | G38: Compra USD p tarjetas | H38: 46268 | J38: Real | K38: 4462218.8 | L38: 4078252.3
B39: 16 | C39: 50 | E39: Caja de Ahorro Santander (USD) | F39: Pago tarjetas de crédito | G39: Compra USD para pagos tarjetas de crédito | H39: 46268 | J39: Rendimiento (neto) | K39: =IF(K38="","",K38-K37) -> 75850.08 | L39: =IF(L38="","",L38-L37) -> 91883.57 | M39: =IF(M38="","",M38-M37) | N39: =IF(N38="","",N38-N37)
B40: 17 | D40: -48.04 | E40: Caja de Ahorro Santander (USD) | F40: Pago tarjetas de crédito | G40: Pago VISA USD | H40: 46268 | J40: Rendimiento (%) | K40: =IF(K39="","",((K38-K37)/K37)) -> 0.017292226 | L40: =IF(L39="","",((L38-L37)/L37)) -> 0.023049441 | M40: =IF(M39="","",((M38-M37)/M37)) | N40: =IF(N39="","",((N38-N37)/N37))
B41: 18 | D41: -9.99 | E41: Caja de Ahorro Santander (USD) | F41: Pago tarjetas de crédito | G41: Pago AMEX USD | H41: 46268
B42: 19 | D42: -4033.51 | E42: Caja de Ahorro Santander (ARS) | F42: Pago tarjetas de crédito | G42: Pago AMEX ARS | H42: 46268 | J42: Petrini
B43: 20 | D43: -116670 | E43: Caja de Ahorro Santander (ARS) | F43: Entradas fiestas/conciertos/otros eventos | G43: Service charge y cuota 1 CR2027 | H43: 46268 | J43: Fecha | K43: =K36 -> 46272 | L43: =L36 -> 46279 | M43: =M36 -> 46286 | N43: =N36 -> 46293
B44: 21 | C44: 23000 | E44: Caja de Ahorro Santander (ARS) | F44: Entradas fiestas/conciertos/otros eventos | G44: Dev IM An Espil | H44: 46269 | J44: Tenencia calculada | K44: =$L$4+SUMIFS($D$24:$D$173,$G$24:$G$173,"Transferencia a Petrini",$H$24:$H$173,"<"&K$36)*-1+SUMIFS($D$24:$D$173,$G$24:$G$173,"Transferencia de Petrini",$H$24:$H$173,"<"&K$36) -> 1647262.6 | L44: =$L$4+SUMIFS($D$24:$D$173,$G$24:$G$173,"Transferencia a Petrini",$H$24:$H$173,"<"&L$36)*-1+SUMIFS($D$24:$D$173,$G$24:$G$173,"Transferencia de Petrini",$H$24:$H$173,"<"&L$36) -> 1647262.6 | M44: =$L$4+SUMIFS($D$24:$D$173,$G$24:$G$173,"Transferencia a Petrini",$H$24:$H$173,"<"&M$36)*-1+SUMIFS($D$24:$D$173,$G$24:$G$173,"Transferencia de Petrini",$H$24:$H$173,"<"&M$36) -> 1647262.6 | N44: =$L$4+SUMIFS($D$24:$D$173,$G$24:$G$173,"Transferencia a Petrini",$H$24:$H$173,"<"&N$36)*-1+SUMIFS($D$24:$D$173,$G$24:$G$173,"Transferencia de Petrini",$H$24:$H$173,"<"&N$36) -> 1647262.6
B45: 22 | C45: 100000 | E45: Caja de Ahorro Santander (ARS) | F45: Pago de honorarios Axis | G45: semana 1 septiembre | H45: 46269 | J45: Tenencia real | K45: 1702871 | L45: 1694064.4
B46: 23 | D46: -11400 | E46: Caja de Ahorro Santander (ARS) | F46: Salidas a desyunar/merendar | G46: Café viernes chacana | H46: 46269 | J46: Rendimiento (neto) | K46: =IF(K45="","",K45-K44) -> 55608.39 | L46: =IF(L45="","",L45-L44) -> 46801.8 | M46: =IF(M45="","",M45-M44) | N46: =IF(N45="","",N45-N44)
B47: 24 | D47: -15000 | E47: Caja de Ahorro Santander (ARS) | F47: Salidas a tomar algo | G47: Vermú música a ciegas | H47: 46269 | J47: Rendimiento (%) | K47: =IF(K46="","",((K45-K44)/K44)) -> 0.03375806 | L47: =IF(L46="","",((L45-L44)/L44)) -> 0.028411863 | M47: =IF(M46="","",((M45-M44)/M44)) | N47: =IF(N46="","",((N45-N44)/N44))
B48: 25 | D48: -8790 | E48: Caja de Ahorro Santander (ARS) | F48: Juntadas a cenar/almorzar | G48: Pimienta cena cielo y bra | H48: 46270
B49: 26 | D49: -19450 | E49: Caja de Ahorro Santander (ARS) | F49: Juntadas a cenar/almorzar | G49: Helado | H49: 46270
B50: 27 | C50: 10000 | E50: Caja de Ahorro Santander (ARS) | F50: Juntadas a cenar/almorzar | G50: Dev cielo helado | H50: 46270
B51: 28 | C51: 30000 | E51: Caja de Ahorro Santander (ARS) | F51: Entradas fiestas/conciertos/otros eventos | G51: Dev Igna Abril Olivera | H51: 46271
B52: 29 | D52: -90000 | E52: Caja de Ahorro Santander (ARS) | F52: Entradas fiestas/conciertos/otros eventos | G52: Entradas Abril Olivera | H52: 46271
B53: 30 | C53: 30000 | E53: Caja de Ahorro Santander (ARS) | F53: Entradas fiestas/conciertos/otros eventos | G53: Dev Cho Abril Olivera | H53: 46271
B54: 31 | D54: -7500 | E54: Caja de Ahorro Santander (ARS) | F54: Salidas a tomar algo | G54: Cerveza Pez Volcán | H54: 46271
B55: 32 | D55: -3000 | E55: Efectivo | F55: Juntadas a cenar/almorzar | G55: Coca almuerzo domingo | H55: 46271
B56: 33 | D56: -14400 | E56: Efectivo | F56: Salidas a tomar algo | G56: Cochera pez volcán | H56: 46271
B57: 34 | D57: -11000 | E57: Caja de Ahorro Santander (ARS) | F57: Salidas a tomar algo | G57: Transf a Igna Pez Volcán | H57: 46272
B58: 35 | D58: =-36958-800 -> -37758 | E58: Caja de Ahorro Santander (ARS) | F58: Juntadas a cenar/almorzar | G58: Burgers NB Dean and Dennys | H58: 46273
B59: 36 | D59: -45000 | E59: Caja de Ahorro Santander (ARS) | F59: Psicóloga | G59: Sesión 1 sept | H59: 46274
B60: 37 | D60: -34300 | E60: Caja de Ahorro Santander (ARS) | F60: Salidas a cenar/almorzar | G60: Almuerzo Bros | H60: 46274
B61: 38 | D61: -6000 | E61: Caja de Ahorro Santander (ARS) | F61: Auto | G61: Liquido refrigerante | H61: 46274
B62: 39 | D62: -200000 | E62: Superfondos Santander | F62: Rescates FCI | G62: Rescate | H62: 46274
B63: 40 | C63: 200000 | E63: Caja de Ahorro Santander (ARS) | F63: Rescates FCI | G63: Rescate | H63: 46274
B64: 41 | D64: -40429 | E64: Caja de Ahorro Santander (ARS) | F64: Juntadas a cenar/almorzar | G64: Gohan miércoles zs | H64: 46274
B65: 42 | D65: -8449 | E65: Caja de Ahorro Santander (ARS) | F65: Súper | G65: Desyuno jueves zs | H65: 46275
B66: 43 | D66: -200000 | E66: Superfondos Santander | F66: Rescates FCI | G66: Recate p pagar arreglo auto | H66: 46275
B67: 44 | C67: 200000 | E67: Caja de Ahorro Santander (ARS) | F67: Rescates FCI | G67: Recate p pagar arreglo auto | H67: 46275
B68: 45 | D68: -220000 | E68: Caja de Ahorro Santander (ARS) | F68: Auto | G68: Arreglo auto | H68: 46275
B69: 46 | D69: -10500 | E69: Caja de Ahorro Santander (ARS) | F69: Súper | G69: Leches y chocolates | H69: 46275
B70: 47 | C70: 220000 | E70: Caja de Ahorro Santander (ARS) | F70: Auto | G70: Devolución arreglo auto | H70: 46276
B71: 48 | D71: -4000 | E71: Caja de Ahorro Santander (ARS) | F71: Mascotas | G71: Collar Mufasa | H71: 46276
B72: 49 | D72: -32200 | E72: Caja de Ahorro Santander (ARS) | F72: Entradas fiestas/conciertos/otros eventos | G72: Música a ciegas, In Rainbows | H72: 46276
B73: 50 | D73: -24000 | E73: Caja de Ahorro Santander (ARS) | F73: Salidas a tomar algo | G73: Fernet Club Paraguay | H73: 46276
B74: 51 | D74: =-11899-600 -> -12499 | E74: Caja de Ahorro Santander (ARS) | F74: Súper | G74: Desayuno sábado | H74: 46277
B75: 52 | D75: -29809.2 | E75: Caja de Ahorro Santander (ARS) | F75: Juntadas a cenar/almorzar | G75: Risotto sábado | H75: 46277
B76: 53 | D76: -8700 | E76: Caja de Ahorro Santander (ARS) | F76: Súper | G76: Desyuno domingo | H76: 46278
B77: 54 | C77: 10000 | E77: Efectivo | F77: Súper | G77: Desyuno domingo | H77: 46278
B78: 55 | C78: 59000 | E78: Caja de Ahorro Santander (ARS) | F78: Pago de honorarios Axis | G78: semana 2 septiembre | H78: 46278
B79: 56 | D79: -120000 | E79: Caja de Ahorro Santander (ARS) | F79: Gimnasio | G79: septiembre y octubre | H79: 46279
B80: 57 | D80: -79900 | E80: Caja de Ahorro Santander (ARS) | F80: Regalos | G80: Regalo Chula | H80: 46280
B81: 58 | C81: 60000 | E81: Caja de Ahorro Santander (ARS) | F81: Regalos | G81: Devolución regalo Chula | H81: 46280
B82: 59 | D82: -56379.08 | E82: Caja de Ahorro Santander (ARS) | F82: Pago monotributo | G82: Monotributo septiembre | H82: 46282
B83: 60 | D83: -11778 | E83: Caja de Ahorro Santander (ARS) | F83: Compras varias | G83: Soporte notebook | H83: 46282
B84: 61 | D84: -20000 | E84: Caja de Ahorro Santander (ARS) | F84: Transferencias Jo | G84: Préstamo JO | H84: 46282
B85: 62 | D85: -9000 | E85: Caja de Ahorro Santander (ARS) | F85: Súper | G85: Huevos | H85: 46282
B86: 63 | C86: 10000 | E86: Efectivo | F86: Súper | G86: Devolución huevos | H86: 46282
B87: 64 | D87: -90000 | E87: Superfondos Santander | F87: Rescates FCI | G87: Rescate | H87: 46283
B88: 65 | C88: 90000 | E88: Caja de Ahorro Santander (ARS) | F88: Rescates FCI | G88: Rescate | H88: 46283
B89: 68 | C89: 42000 | E89: Caja de Ahorro Santander (ARS) | F89: Pago de honorarios Axis | G89: semana 3 septiembre | H89: 46283
B90: 69 | D90: -29000 | E90: Caja de Ahorro Santander (ARS) | F90: Salidas a desyunar/merendar | G90: Desayuno shiok | H90: 46284
B91: 66 | D91: -26500 | E91: Caja de Ahorro Santander (ARS) | F91: Compras varias | G91: Soporte celu y mascarillas | H91: 46284
B92: 67 | D92: -5000 | E92: Caja de Ahorro Santander (ARS) | F92: Salidas a cenar/almorzar | G92: Propina Al Malek | H92: 46284
B93: 70 | D93: -21600 | E93: Caja de Ahorro Santander (ARS) | F93: Juntadas a cenar/almorzar | G93: Vinos asado Bra | H93: 46284
B94: 71 | D94: -15000 | E94: Caja de Ahorro Santander (ARS) | F94: Salidas a desyunar/merendar | G94: Desayuno Co | H94: 46285
B95: 72
B96: 73
B97: 74
B98: 75
B99: 76
B100: 77
B101: 78
B102: 79
B103: 80
...

Sheet Gastos octubre
B1: Datos del periodo | J1: Tenencia - Inicio | K1: USD | L1: ARS | N1: Tenencia - Fin | O1: USD | P1: ARS | R1: Diferencia | S1: USD | T1: ARS
B2: Año: | C2: 2026 | J2: Regalo recibida | K2: ='Gastos septiembre'!O2 -> 10000 | L2: =K2*D7 -> 0 | N2: Regalo recibida | O2: =K2+SUMIF($E$24:$E$173,$N2,$C$24:$C$173)+SUMIF($E$24:$E$173,$N2,$D$24:$D$173) -> 10000 | P2: =O2*$D$7 -> 0 | R2: Regalo recibida | S2: =IFERROR(IF(O2>K2,O2-K2,K2-O2),0) -> 0 | T2: =IFERROR(IF(P2>L2,P2-L2,L2-P2),0) -> 0
B3: Mes: | C3: octubre | J3: Caja de seguridad | K3: ='Gastos septiembre'!O3 -> 500 | L3: =K3*D7 -> 0 | N3: Caja de seguridad | O3: =K3 -> 500 | P3: =L3+SUMIF($E$24:$E$173,$N3,$C$24:$C$173)+SUMIF($E$24:$E$173,$N3,$D$24:$D$173) -> 0 | R3: Caja de seguridad | S3: =IFERROR(IF(O3>K3,O3-K3,K3-O3),0) -> 0 | T3: =IFERROR(IF(P3>L3,P3-L3,L3-P3),0) -> 0
B4: Cantidad de días: | C4: =DAY(EOMONTH(DATE($C$2,MATCH($C$3,{"enero";"febrero";"marzo";"abril";"mayo";"junio";"julio";"agosto";"septiembre";"octubre";"noviembre";"diciembre"},0),1),0)) -> 31 | J4: Cta. Comitente Petrini | K4: ='Gastos septiembre'!O4 | L4: ='Gastos septiembre'!P4 -> 1647262.6 | N4: Cta. Comitente Petrini | O4: =IFERROR(P4/$C$8,"") | P4: =L4+SUMIF($E$24:$E$173,$N4,$C$24:$C$173)+SUMIF($E$24:$E$173,$N4,$D$24:$D$173) -> 1647262.6 | R4: Cta. Comitente Petrini | S4: =IFERROR(IF(O4>K4,O4-K4,K4-O4),0) -> 0 | T4: =IFERROR(IF(P4>L4,P4-L4,L4-P4),0) -> 0
J5: Superfondos Santander | K5: ='Gastos septiembre'!O5 | L5: ='Gastos septiembre'!P5 -> 3896368.8 | N5: Superfondos Santander | O5: =IFERROR(P5/$C$8,"") | P5: =L5+SUMIF($E$24:$E$173,$N5,$C$24:$C$173)+SUMIF($E$24:$E$173,$N5,$D$24:$D$173) -> 3896368.8 | R5: Superfondos Santander | S5: =IFERROR(IF(O5>K5,O5-K5,K5-O5),0) -> 0 | T5: =IFERROR(IF(P5>L5,P5-L5,L5-P5),0) -> 0
B6: Tc | C6: Compra | D6: Venta | J6: Caja de Ahorro Santander (ARS) | K6: ='Gastos septiembre'!O6 | L6: ='Gastos septiembre'!P6 -> 5648.43 | N6: Caja de Ahorro Santander (ARS) | O6: =IFERROR(P6/$C$8,"") | P6: =L6+SUMIF($E$24:$E$173,$N6,$C$24:$C$173)+SUMIF($E$24:$E$173,$N6,$D$24:$D$173) -> 5648.43 | R6: Caja de Ahorro Santander (ARS) | S6: =IFERROR(IF(O6>K6,O6-K6,K6-O6),0) -> 0 | T6: =IFERROR(IF(P6>L6,P6-L6,L6-P6),0) -> 0
B7: =DATE($C$2,MATCH($C$3,{"enero";"febrero";"marzo";"abril";"mayo";"junio";"julio";"agosto";"septiembre";"octubre";"noviembre";"diciembre"},0),1) -> 46296 | J7: Caja de Ahorro Santander (USD) | K7: ='Gastos septiembre'!O7 -> 1.88 | L7: =K7*D7 -> 0 | N7: Caja de Ahorro Santander (USD) | O7: =K7+SUM(C17:C19)+SUM(D17:D19) -> 1.88 | P7: =O7*$D$8 -> 0 | R7: Caja de Ahorro Santander (USD) | S7: =IFERROR(IF(O7>K7,O7-K7,K7-O7),0) -> 0 | T7: =IFERROR(IF(P7>L7,P7-L7,L7-P7),0) -> 0
B8: =DATE($C$2,MATCH($C$3,{"enero";"febrero";"marzo";"abril";"mayo";"junio";"julio";"agosto";"septiembre";"octubre";"noviembre";"diciembre"},0),C4) -> 46326 | J8: Mercado Pago | K8: ='Gastos septiembre'!O8 | L8: ='Gastos septiembre'!P8 -> 565.09 | N8: Mercado Libre | O8: =IFERROR(P8/$C$8,"") | P8: =L8+SUMIF($E$24:$E$173,$N8,$C$24:$C$173)+SUMIF($E$24:$E$173,$N8,$D$24:$D$173) -> 565.09 | R8: Mercado Libre | S8: =IFERROR(IF(O8>K8,O8-K8,K8-O8),0) -> 0 | T8: =IFERROR(IF(P8>L8,P8-L8,L8-P8),0) -> 0
J9: Brubank | K9: ='Gastos septiembre'!O9 | L9: ='Gastos septiembre'!P9 -> 1.36 | N9: Brubank | O9: =IFERROR(P9/$C$8,"") | P9: =L9+SUMIF($E$24:$E$173,$N9,$C$24:$C$173)+SUMIF($E$24:$E$173,$N9,$D$24:$D$173) -> 1.36 | R9: Brubank | S9: =IFERROR(IF(O9>K9,O9-K9,K9-O9),0) -> 0 | T9: =IFERROR(IF(P9>L9,P9-L9,L9-P9),0) -> 0
J10: Efectivo | K10: ='Gastos septiembre'!O10 | L10: ='Gastos septiembre'!P10 -> 32600 | N10: Efectivo | O10: =IFERROR(P10/$C$8,"") | P10: =L10+SUMIF($E$24:$E$173,$N10,$C$24:$C$173)+SUMIF($E$24:$E$173,$N10,$D$24:$D$173) -> 32600 | R10: Efectivo | S10: =IFERROR(IF(O10>K10,O10-K10,K10-O10),0) -> 0 | T10: =IFERROR(IF(P10>L10,P10-L10,L10-P10),0) -> 0
J12: Total | K12: =SUM(K2:K10) -> 10501.88 | L12: =SUM(L2:L10) -> 5582446.3 | N12: Total | O12: =SUM(O2:O9) -> 10501.88 | P12: =SUM(P2:P9) -> 5549846.3 | R12: Total | S12: =SUM(S2:S9) -> 0 | T12: =SUM(T2:T9) -> 0
B15: Compra/venta USD | J15: Análisis gastos e ingresos
B16: Nro. | C16: Ingresos | D16: Gastos | E16: Origen/Destino | F16: Concepto | G16: Descripción | H16: Fecha | J16: Concepto | K16: Acumulado egresos | L16: Acumulado ingresos | M16: Composición egresos | N16: Composición ingresos
B17: 1 | J17: Pago Claude/Cursor | K17: =SUMIF($F$24:$F$173,$J17,$D$24:$D$173) -> 0 | L17: =SUMIF($F$24:$F$173,$J17,$C$24:$C$173) -> 0 | M17: =IFERROR(K17/SUM(K$17:K$32),"") | N17: =IFERROR(L17/SUM(L$17:L$32),"")
B18: 2 | J18: Salidas a cenar/almorzar | K18: =SUMIF($F$24:$F$173,$J18,$C$24:$C$173)+SUMIF($F$24:$F$173,$J18,$D$24:$D$173) -> 0 | L18: =SUMIF($F$24:$F$173,$J18,$C$24:$C$173) -> 0 | M18: =IFERROR(K18/SUM(K$17:K$32),"") | N18: =IFERROR(L18/SUM(L$17:L$32),"")
B19: 3 | J19: Salidas a desyunar/merendar | K19: =SUMIF($F$24:$F$173,$J19,$C$24:$C$173)+SUMIF($F$24:$F$173,$J19,$D$24:$D$173) -> 0 | L19: =SUMIF($F$24:$F$173,$J19,$C$24:$C$173) -> 0 | M19: =IFERROR(K19/SUM(K$17:K$32),"") | N19: =IFERROR(L19/SUM(L$17:L$32),"")
J20: Salidas a tomar algo | K20: =SUMIF($F$24:$F$173,$J20,$C$24:$C$173)+SUMIF($F$24:$F$173,$J20,$D$24:$D$173) -> 0 | L20: =SUMIF($F$24:$F$173,$J20,$C$24:$C$173) -> 0 | M20: =IFERROR(K20/SUM(K$17:K$32),"") | N20: =IFERROR(L20/SUM(L$17:L$32),"")
J21: Fiestas | K21: =SUMIF($F$24:$F$173,$J21,$C$24:$C$173)+SUMIF($F$24:$F$173,$J21,$D$24:$D$173) -> 0 | L21: =SUMIF($F$24:$F$173,$J21,$C$24:$C$173) -> 0 | M21: =IFERROR(K21/SUM(K$17:K$32),"") | N21: =IFERROR(L21/SUM(L$17:L$32),"")
B22: Movimientos en ARS | J22: Auto | K22: =SUMIF($F$24:$F$173,$J22,$C$24:$C$173)+SUMIF($F$24:$F$173,$J22,$D$24:$D$173) -> 0 | L22: =SUMIF($F$24:$F$173,$J22,$C$24:$C$173) -> 0 | M22: =IFERROR(K22/SUM(K$17:K$32),"") | N22: =IFERROR(L22/SUM(L$17:L$32),"")
B23: Nro. | C23: Ingresos | D23: Gastos | E23: Origen/Destino | F23: Concepto | G23: Descripción | H23: Fecha | J23: Farmacia/Cosméticos | K23: =SUMIF($F$24:$F$173,$J23,$C$24:$C$173)+SUMIF($F$24:$F$173,$J23,$D$24:$D$173) -> 0 | L23: =SUMIF($F$24:$F$173,$J23,$C$24:$C$173) -> 0 | M23: =IFERROR(K23/SUM(K$17:K$32),"") | N23: =IFERROR(L23/SUM(L$17:L$32),"")
B24: 1 | J24: Ropa | K24: =SUMIF($F$24:$F$173,$J24,$C$24:$C$173)+SUMIF($F$24:$F$173,$J24,$D$24:$D$173) -> 0 | L24: =SUMIF($F$24:$F$173,$J24,$C$24:$C$173) -> 0 | M24: =IFERROR(K24/SUM(K$17:K$32),"") | N24: =IFERROR(L24/SUM(L$17:L$32),"")
B25: 2 | J25: Súper | K25: =SUMIF($F$24:$F$173,$J25,$C$24:$C$173)+SUMIF($F$24:$F$173,$J25,$D$24:$D$173) -> 0 | L25: =SUMIF($F$24:$F$173,$J25,$C$24:$C$173) -> 0 | M25: =IFERROR(K25/SUM(K$17:K$32),"") | N25: =IFERROR(L25/SUM(L$17:L$32),"")
B26: 3 | J26: Delivery | K26: =SUMIF($F$24:$F$173,$J26,$C$24:$C$173)+SUMIF($F$24:$F$173,$J26,$D$24:$D$173) -> 0 | L26: =SUMIF($F$24:$F$173,$J26,$C$24:$C$173) -> 0 | M26: =IFERROR(K26/SUM(K$17:K$32),"") | N26: =IFERROR(L26/SUM(L$17:L$32),"")
B27: 4 | J27: Regalos | K27: =SUMIF($F$24:$F$173,$J27,$C$24:$C$173)+SUMIF($F$24:$F$173,$J27,$D$24:$D$173) -> 0 | L27: =SUMIF($F$24:$F$173,$J27,$C$24:$C$173) -> 0 | M27: =IFERROR(K27/SUM(K$17:K$32),"") | N27: =IFERROR(L27/SUM(L$17:L$32),"")
B28: 5 | J28: Entradas fiestas/conciertos | K28: =SUMIF($F$24:$F$173,$J28,$C$24:$C$173)+SUMIF($F$24:$F$173,$J28,$D$24:$D$173) -> 0 | L28: =SUMIF($F$24:$F$173,$J28,$C$24:$C$173) -> 0 | M28: =IFERROR(K28/SUM(K$17:K$32),"") | N28: =IFERROR(L28/SUM(L$17:L$32),"")
B29: 6 | J29: Pago de honorarios Quantum | K29: =SUMIF($F$24:$F$173,$J29,$C$24:$C$173)+SUMIF($F$24:$F$173,$J29,$D$24:$D$173) -> 0 | L29: =SUMIF($F$24:$F$173,$J29,$C$24:$C$173) -> 0 | M29: =IFERROR(K29/SUM(K$17:K$32),"") | N29: =IFERROR(L29/SUM(L$17:L$32),"")
B30: 7 | J30: Pago de honorarios Axis | K30: =SUMIF($F$24:$F$173,$J30,$C$24:$C$173)+SUMIF($F$24:$F$173,$J30,$D$24:$D$173) -> 0 | L30: =SUMIF($F$24:$F$173,$J30,$C$24:$C$173) -> 0 | M30: =IFERROR(K30/SUM(K$17:K$32),"") | N30: =IFERROR(L30/SUM(L$17:L$32),"")
B31: 8 | J31: Otros honorarios | K31: =SUMIF($F$24:$F$173,$J31,$C$24:$C$173)+SUMIF($F$24:$F$173,$J31,$D$24:$D$173) -> 0 | L31: =SUMIF($F$24:$F$173,$J31,$C$24:$C$173) -> 0 | M31: =IFERROR(K31/SUM(K$17:K$32),"") | N31: =IFERROR(L31/SUM(L$17:L$32),"")
B32: 9 | J32: Ahorros/inversiones | K32: =SUMIF($F$24:$F$173,$J32,$C$24:$C$173)+SUMIF($F$24:$F$173,$J32,$D$24:$D$173) -> 0 | L32: =SUMIF($F$24:$F$173,$J32,$C$24:$C$173) -> 0 | M32: =IFERROR(K32/SUM(K$17:K$32),"") | N32: =IFERROR(L32/SUM(L$17:L$32),"")
B33: 10 | J33: Pago tarjetas de crédito | K33: =SUMIF($F$24:$F$173,$J33,$C$24:$C$173)+SUMIF($F$24:$F$173,$J33,$D$24:$D$173) -> 0 | L33: =SUMIF($F$24:$F$173,$J33,$C$24:$C$173) -> 0 | M33: =IFERROR(K33/SUM(K$17:K$32),"") | N33: =IFERROR(L33/SUM(L$17:L$32),"")
B34: 11
B35: 12 | J35: Superfondos Santander
B36: 13 | J36: Superfondos Santander | K36: 46272 | L36: 46279 | M36: 46286 | N36: 46293
B37: 14 | J37: Calculado | K37: =$L$5+SUMIFS($C$24:$C$173,$E$24:$E$173,$N5,$H$24:$H$173,"<="&K$36)+SUMIFS($D$24:$D$173,$E$24:$E$173,$N5,$H$24:$H$173,"<="&K$36) -> 3896368.8 | L37: =$L$5+SUMIFS($C$24:$C$173,$E$24:$E$173,$N5,$H$24:$H$173,"<"&L$36)+SUMIFS($D$24:$D$173,$E$24:$E$173,$N5,$H$24:$H$173,"<="&L$36) -> 3896368.8 | M37: =$L$5+SUMIFS($C$24:$C$173,$E$24:$E$173,$N5,$H$24:$H$173,"<"&M$36)+SUMIFS($D$24:$D$173,$E$24:$E$173,$N5,$H$24:$H$173,"<="&M$36) -> 3896368.8 | N37: =$L$5+SUMIFS($C$24:$C$173,$E$24:$E$173,$N5,$H$24:$H$173,"<"&N$36)+SUMIFS($D$24:$D$173,$E$24:$E$173,$N5,$H$24:$H$173,"<="&N$36) -> 3896368.8
B38: 15 | J38: Real
B39: 16 | J39: Rendimiento (neto) | K39: =IF(K38="","",K38-K37) | L39: =IF(L38="","",L38-L37) | M39: =IF(M38="","",M38-M37) | N39: =IF(N38="","",N38-N37)
B40: 17 | J40: Rendimiento (%) | K40: =IF(K39="","",((K38-K37)/K37)) | L40: =IF(L39="","",((L38-L37)/L37)) | M40: =IF(M39="","",((M38-M37)/M37)) | N40: =IF(N39="","",((N38-N37)/N37))
B41: 18
B42: 19 | J42: Petrini
B43: 20 | J43: Fecha | K43: =K36 -> 46272 | L43: =L36 -> 46279 | M43: =M36 -> 46286 | N43: =N36 -> 46293
B44: 21 | J44: Tenencia calculada | K44: =$L$4+SUMIFS($D$24:$D$173,$G$24:$G$173,"Transferencia a Petrini",$H$24:$H$173,"<"&K$36)*-1+SUMIFS($D$24:$D$173,$G$24:$G$173,"Transferencia de Petrini",$H$24:$H$173,"<"&K$36) -> 1647262.6 | L44: =$L$4+SUMIFS($D$24:$D$173,$G$24:$G$173,"Transferencia a Petrini",$H$24:$H$173,"<"&L$36)*-1+SUMIFS($D$24:$D$173,$G$24:$G$173,"Transferencia de Petrini",$H$24:$H$173,"<"&L$36) -> 1647262.6 | M44: =$L$4+SUMIFS($D$24:$D$173,$G$24:$G$173,"Transferencia a Petrini",$H$24:$H$173,"<"&M$36)*-1+SUMIFS($D$24:$D$173,$G$24:$G$173,"Transferencia de Petrini",$H$24:$H$173,"<"&M$36) -> 1647262.6 | N44: =$L$4+SUMIFS($D$24:$D$173,$G$24:$G$173,"Transferencia a Petrini",$H$24:$H$173,"<"&N$36)*-1+SUMIFS($D$24:$D$173,$G$24:$G$173,"Transferencia de Petrini",$H$24:$H$173,"<"&N$36) -> 1647262.6
B45: 22 | J45: Tenencia real
B46: 23 | J46: Rendimiento (neto) | K46: =IF(K45="","",K45-K44) | L46: =IF(L45="","",L45-L44) | M46: =IF(M45="","",M45-M44) | N46: =IF(N45="","",N45-N44)
B47: 24 | J47: Rendimiento (%) | K47: =IF(K46="","",((K45-K44)/K44)) | L47: =IF(L46="","",((L45-L44)/L44)) | M47: =IF(M46="","",((M45-M44)/M44)) | N47: =IF(N46="","",((N45-N44)/N44))
B48: 25
B49: 26
B50: 27
B51: 28
B52: 29
B53: 30
B54: 31
B55: 32
B56: 33
B57: 34
B58: 35
B59: 36
... B173: 150

Sheet Gastos noviembre
B1: Datos del periodo | J1: Tenencia - Inicio | K1: USD | L1: ARS | N1: Tenencia - Fin | O1: USD | P1: ARS | R1: Diferencia | S1: USD | T1: ARS
B2: Año: | C2: 2026 | J2: Regalo recibida | K2: ='Gastos octubre'!O2 -> 10000 | L2: =K2*D7 -> 0 | N2: Regalo recibida | O2: =K2+SUMIF($E$24:$E$173,$N2,$C$24:$C$173)+SUMIF($E$24:$E$173,$N2,$D$24:$D$173) -> 10000 | P2: =O2*$D$7 -> 0 | R2: Regalo recibida | S2: =IFERROR(IF(O2>K2,O2-K2,K2-O2),0) -> 0 | T2: =IFERROR(IF(P2>L2,P2-L2,L2-P2),0) -> 0
B3: Mes: | C3: noviembre | J3: Caja de seguridad | K3: ='Gastos octubre'!O3 -> 500 | L3: =K3*D7 -> 0 | N3: Caja de seguridad | O3: =K3 -> 500 | P3: =L3+SUMIF($E$24:$E$173,$N3,$C$24:$C$173)+SUMIF($E$24:$E$173,$N3,$D$24:$D$173) -> 0 | R3: Caja de seguridad | S3: =IFERROR(IF(O3>K3,O3-K3,K3-O3),0) -> 0 | T3: =IFERROR(IF(P3>L3,P3-L3,L3-P3),0) -> 0
B4: Cantidad de días: | C4: =DAY(EOMONTH(DATE($C$2,MATCH($C$3,{"enero";"febrero";"marzo";"abril";"mayo";"junio";"julio";"agosto";"septiembre";"octubre";"noviembre";"diciembre"},0),1),0)) -> 30 | J4: Cta. Comitente Petrini | K4: ='Gastos octubre'!O4 | L4: ='Gastos octubre'!P4 -> 1647262.6 | N4: Cta. Comitente Petrini | O4: =IFERROR(P4/$C$8,"") | P4: =L4+SUMIF($E$24:$E$173,$N4,$C$24:$C$173)+SUMIF($E$24:$E$173,$N4,$D$24:$D$173) -> 1647262.6 | R4: Cta. Comitente Petrini | S4: =IFERROR(IF(O4>K4,O4-K4,K4-O4),0) -> 0 | T4: =IFERROR(IF(P4>L4,P4-L4,L4-P4),0) -> 0
J5: Superfondos Santander | K5: ='Gastos octubre'!O5 | L5: ='Gastos octubre'!P5 -> 3896368.8 | N5: Superfondos Santander | O5: =IFERROR(P5/$C$8,"") | P5: =L5+SUMIF($E$24:$E$173,$N5,$C$24:$C$173)+SUMIF($E$24:$E$173,$N5,$D$24:$D$173) -> 3896368.8 | R5: Superfondos Santander | S5: =IFERROR(IF(O5>K5,O5-K5,K5-O5),0) -> 0 | T5: =IFERROR(IF(P5>L5,P5-L5,L5-P5),0) -> 0
B6: Tc | C6: Compra | D6: Venta | J6: Caja de Ahorro Santander (ARS) | K6: ='Gastos octubre'!O6 | L6: ='Gastos octubre'!P6 -> 5648.43 | N6: Caja de Ahorro Santander (ARS) | O6: =IFERROR(P6/$C$8,"") | P6: =L6+SUMIF($E$24:$E$173,$N6,$C$24:$C$173)+SUMIF($E$24:$E$173,$N6,$D$24:$D$173) -> 5648.43 | R6: Caja de Ahorro Santander (ARS) | S6: =IFERROR(IF(O6>K6,O6-K6,K6-O6),0) -> 0 | T6: =IFERROR(IF(P6>L6,P6-L6,L6-P6),0) -> 0
B7: =DATE($C$2,MATCH($C$3,{"enero";"febrero";"marzo";"abril";"mayo";"junio";"julio";"agosto";"septiembre";"octubre";"noviembre";"diciembre"},0),1) -> 46327 | J7: Caja de Ahorro Santander (USD) | K7: ='Gastos octubre'!O7 -> 1.88 | L7: =K7*D7 -> 0 | N7: Caja de Ahorro Santander (USD) | O7: =K7+SUM(C17:C19)+SUM(D17:D19) -> 1.88 | P7: =O7*$D$8 -> 0 | R7: Caja de Ahorro Santander (USD) | S7: =IFERROR(IF(O7>K7,O7-K7,K7-O7),0) -> 0 | T7: =IFERROR(IF(P7>L7,P7-L7,L7-P7),0) -> 0
B8: =DATE($C$2,MATCH($C$3,{"enero";"febrero";"marzo";"abril";"mayo";"junio";"julio";"agosto";"septiembre";"octubre";"noviembre";"diciembre"},0),C4) -> 46356 | J8: Mercado Pago | K8: ='Gastos octubre'!O8 | L8: ='Gastos octubre'!P8 -> 565.09 | N8: Mercado Libre | O8: =IFERROR(P8/$C$8,"") | P8: =L8+SUMIF($E$24:$E$173,$N8,$C$24:$C$173)+SUMIF($E$24:$E$173,$N8,$D$24:$D$173) -> 565.09 | R8: Mercado Libre | S8: =IFERROR(IF(O8>K8,O8-K8,K8-O8),0) -> 0 | T8: =IFERROR(IF(P8>L8,P8-L8,L8-P8),0) -> 0
J9: Brubank | K9: ='Gastos octubre'!O9 | L9: ='Gastos octubre'!P9 -> 1.36 | N9: Brubank | O9: =IFERROR(P9/$C$8,"") | P9: =L9+SUMIF($E$24:$E$173,$N9,$C$24:$C$173)+SUMIF($E$24:$E$173,$N9,$D$24:$D$173) -> 1.36 | R9: Brubank | S9: =IFERROR(IF(O9>K9,O9-K9,K9-O9),0) -> 0 | T9: =IFERROR(IF(P9>L9,P9-L9,L9-P9),0) -> 0
J10: Efectivo | K10: ='Gastos octubre'!O10 | L10: ='Gastos octubre'!P10 -> 32600 | N10: Efectivo | O10: =IFERROR(P10/$C$8,"") | P10: =L10+SUMIF($E$24:$E$173,$N10,$C$24:$C$173)+SUMIF($E$24:$E$173,$N10,$D$24:$D$173) -> 32600 | R10: Efectivo | S10: =IFERROR(IF(O10>K10,O10-K10,K10-O10),0) -> 0 | T10: =IFERROR(IF(P10>L10,P10-L10,L10-P10),0) -> 0
J12: Total | K12: =SUM(K2:K10) -> 10501.88 | L12: =SUM(L2:L10) -> 5582446.3 | N12: Total | O12: =SUM(O2:O9) -> 10501.88 | P12: =SUM(P2:P9) -> 5549846.3 | R12: Total | S12: =SUM(S2:S9) -> 0 | T12: =SUM(T2:T9) -> 0
B15: Compra/venta USD | J15: Análisis gastos e ingresos
B16: Nro. | C16: Ingresos | D16: Gastos | E16: Origen/Destino | F16: Concepto | G16: Descripción | H16: Fecha | J16: Concepto | K16: Acumulado egresos | L16: Acumulado ingresos | M16: Composición egresos | N16: Composición ingresos
B17: 1 | J17: Pago Claude/Cursor | K17: =SUMIF($F$24:$F$173,$J17,$D$24:$D$173) -> 0 | L17: =SUMIF($F$24:$F$173,$J17,$C$24:$C$173) -> 0 | M17: =IFERROR(K17/SUM(K$17:K$32),"") | N17: =IFERROR(L17/SUM(L$17:L$32),"")
B18: 2 | J18: Salidas a cenar/almorzar | K18: =SUMIF($F$24:$F$173,$J18,$C$24:$C$173)+SUMIF($F$24:$F$173,$J18,$D$24:$D$173) -> 0 | L18: =SUMIF($F$24:$F$173,$J18,$C$24:$C$173) -> 0 | M18: =IFERROR(K18/SUM(K$17:K$32),"") | N18: =IFERROR(L18/SUM(L$17:L$32),"")
B19: 3 | J19: Salidas a desyunar/merendar | K19: =SUMIF($F$24:$F$173,$J19,$C$24:$C$173)+SUMIF($F$24:$F$173,$J19,$D$24:$D$173) -> 0 | L19: =SUMIF($F$24:$F$173,$J19,$C$24:$C$173) -> 0 | M19: =IFERROR(K19/SUM(K$17:K$32),"") | N19: =IFERROR(L19/SUM(L$17:L$32),"")
J20: Salidas a tomar algo | K20: =SUMIF($F$24:$F$173,$J20,$C$24:$C$173)+SUMIF($F$24:$F$173,$J20,$D$24:$D$173) -> 0 | L20: =SUMIF($F$24:$F$173,$J20,$C$24:$C$173) -> 0 | M20: =IFERROR(K20/SUM(K$17:K$32),"") | N20: =IFERROR(L20/SUM(L$17:L$32),"")
J21: Fiestas | K21: =SUMIF($F$24:$F$173,$J21,$C$24:$C$173)+SUMIF($F$24:$F$173,$J21,$D$24:$D$173) -> 0 | L21: =SUMIF($F$24:$F$173,$J21,$C$24:$C$173) -> 0 | M21: =IFERROR(K21/SUM(K$17:K$32),"") | N21: =IFERROR(L21/SUM(L$17:L$32),"")
B22: Movimientos en ARS | J22: Auto | K22: =SUMIF($F$24:$F$173,$J22,$C$24:$C$173)+SUMIF($F$24:$F$173,$J22,$D$24:$D$173) -> 0 | L22: =SUMIF($F$24:$F$173,$J22,$C$24:$C$173) -> 0 | M22: =IFERROR(K22/SUM(K$17:K$32),"") | N22: =IFERROR(L22/SUM(L$17:L$32),"")
B23: Nro. | C23: Ingresos | D23: Gastos | E23: Origen/Destino | F23: Concepto | G23: Descripción | H23: Fecha | J23: Farmacia/Cosméticos | K23: =SUMIF($F$24:$F$173,$J23,$C$24:$C$173)+SUMIF($F$24:$F$173,$J23,$D$24:$D$173) -> 0 | L23: =SUMIF($F$24:$F$173,$J23,$C$24:$C$173) -> 0 | M23: =IFERROR(K23/SUM(K$17:K$32),"") | N23: =IFERROR(L23/SUM(L$17:L$32),"")
B24: 1 | J24: Ropa | K24: =SUMIF($F$24:$F$173,$J24,$C$24:$C$173)+SUMIF($F$24:$F$173,$J24,$D$24:$D$173) -> 0 | L24: =SUMIF($F$24:$F$173,$J24,$C$24:$C$173) -> 0 | M24: =IFERROR(K24/SUM(K$17:K$32),"") | N24: =IFERROR(L24/SUM(L$17:L$32),"")
B25: 2 | J25: Súper | K25: =SUMIF($F$24:$F$173,$J25,$C$24:$C$173)+SUMIF($F$24:$F$173,$J25,$D$24:$D$173) -> 0 | L25: =SUMIF($F$24:$F$173,$J25,$C$24:$C$173) -> 0 | M25: =IFERROR(K25/SUM(K$17:K$32),"") | N25: =IFERROR(L25/SUM(L$17:L$32),"")
B26: 3 | J26: Delivery | K26: =SUMIF($F$24:$F$173,$J26,$C$24:$C$173)+SUMIF($F$24:$F$173,$J26,$D$24:$D$173) -> 0 | L26: =SUMIF($F$24:$F$173,$J26,$C$24:$C$173) -> 0 | M26: =IFERROR(K26/SUM(K$17:K$32),"") | N26: =IFERROR(L26/SUM(L$17:L$32),"")
B27: 4 | J27: Regalos | K27: =SUMIF($F$24:$F$173,$J27,$C$24:$C$173)+SUMIF($F$24:$F$173,$J27,$D$24:$D$173) -> 0 | L27: =SUMIF($F$24:$F$173,$J27,$C$24:$C$173) -> 0 | M27: =IFERROR(K27/SUM(K$17:K$32),"") | N27: =IFERROR(L27/SUM(L$17:L$32),"")
B28: 5 | J28: Entradas fiestas/conciertos | K28: =SUMIF($F$24:$F$173,$J28,$C$24:$C$173)+SUMIF($F$24:$F$173,$J28,$D$24:$D$173) -> 0 | L28: =SUMIF($F$24:$F$173,$J28,$C$24:$C$173) -> 0 | M28: =IFERROR(K28/SUM(K$17:K$32),"") | N28: =IFERROR(L28/SUM(L$17:L$32),"")
B29: 6 | J29: Pago de honorarios Quantum | K29: =SUMIF($F$24:$F$173,$J29,$C$24:$C$173)+SUMIF($F$24:$F$173,$J29,$D$24:$D$173) -> 0 | L29: =SUMIF($F$24:$F$173,$J29,$C$24:$C$173) -> 0 | M29: =IFERROR(K29/SUM(K$17:K$32),"") | N29: =IFERROR(L29/SUM(L$17:L$32),"")
B30: 7 | J30: Pago de honorarios Axis | K30: =SUMIF($F$24:$F$173,$J30,$C$24:$C$173)+SUMIF($F$24:$F$173,$J30,$D$24:$D$173) -> 0 | L30: =SUMIF($F$24:$F$173,$J30,$C$24:$C$173) -> 0 | M30: =IFERROR(K30/SUM(K$17:K$32),"") | N30: =IFERROR(L30/SUM(L$17:L$32),"")
B31: 8 | J31: Otros honorarios | K31: =SUMIF($F$24:$F$173,$J31,$C$24:$C$173)+SUMIF($F$24:$F$173,$J31,$D$24:$D$173) -> 0 | L31: =SUMIF($F$24:$F$173,$J31,$C$24:$C$173) -> 0 | M31: =IFERROR(K31/SUM(K$17:K$32),"") | N31: =IFERROR(L31/SUM(L$17:L$32),"")
B32: 9 | J32: Ahorros/inversiones | K32: =SUMIF($F$24:$F$173,$J32,$C$24:$C$173)+SUMIF($F$24:$F$173,$J32,$D$24:$D$173) -> 0 | L32: =SUMIF($F$24:$F$173,$J32,$C$24:$C$173) -> 0 | M32: =IFERROR(K32/SUM(K$17:K$32),"") | N32: =IFERROR(L32/SUM(L$17:L$32),"")
B33: 10 | J33: Pago tarjetas de crédito | K33: =SUMIF($F$24:$F$173,$J33,$C$24:$C$173)+SUMIF($F$24:$F$173,$J33,$D$24:$D$173) -> 0 | L33: =SUMIF($F$24:$F$173,$J33,$C$24:$C$173) -> 0 | M33: =IFERROR(K33/SUM(K$17:K$32),"") | N33: =IFERROR(L33/SUM(L$17:L$32),"")
B34: 11
B35: 12 | J35: Superfondos Santander
B36: 13 | J36: Superfondos Santander | K36: 46272 | L36: 46279 | M36: 46286 | N36: 46293
B37: 14 | J37: Calculado | K37: =$L$5+SUMIFS($C$24:$C$173,$E$24:$E$173,$N5,$H$24:$H$173,"<="&K$36)+SUMIFS($D$24:$D$173,$E$24:$E$173,$N5,$H$24:$H$173,"<="&K$36) -> 3896368.8 | L37: =$L$5+SUMIFS($C$24:$C$173,$E$24:$E$173,$N5,$H$24:$H$173,"<"&L$36)+SUMIFS($D$24:$D$173,$E$24:$E$173,$N5,$H$24:$H$173,"<="&L$36) -> 3896368.8 | M37: =$L$5+SUMIFS($C$24:$C$173,$E$24:$E$173,$N5,$H$24:$H$173,"<"&M$36)+SUMIFS($D$24:$D$173,$E$24:$E$173,$N5,$H$24:$H$173,"<="&M$36) -> 3896368.8 | N37: =$L$5+SUMIFS($C$24:$C$173,$E$24:$E$173,$N5,$H$24:$H$173,"<"&N$36)+SUMIFS($D$24:$D$173,$E$24:$E$173,$N5,$H$24:$H$173,"<="&N$36) -> 3896368.8
B38: 15 | J38: Real
B39: 16 | J39: Rendimiento (neto) | K39: =IF(K38="","",K38-K37) | L39: =IF(L38="","",L38-L37) | M39: =IF(M38="","",M38-M37) | N39: =IF(N38="","",N38-N37)
B40: 17 | J40: Rendimiento (%) | K40: =IF(K39="","",((K38-K37)/K37)) | L40: =IF(L39="","",((L38-L37)/L37)) | M40: =IF(M39="","",((M38-M37)/M37)) | N40: =IF(N39="","",((N38-N37)/N37))
B41: 18
B42: 19 | J42: Petrini
B43: 20 | J43: Fecha | K43: =K36 -> 46272 | L43: =L36 -> 46279 | M43: =M36 -> 46286 | N43: =N36 -> 46293
B44: 21 | J44: Tenencia calculada | K44: =$L$4+SUMIFS($D$24:$D$173,$G$24:$G$173,"Transferencia a Petrini",$H$24:$H$173,"<"&K$36)*-1+SUMIFS($D$24:$D$173,$G$24:$G$173,"Transferencia de Petrini",$H$24:$H$173,"<"&K$36) -> 1647262.6 | L44: =$L$4+SUMIFS($D$24:$D$173,$G$24:$G$173,"Transferencia a Petrini",$H$24:$H$173,"<"&L$36)*-1+SUMIFS($D$24:$D$173,$G$24:$G$173,"Transferencia de Petrini",$H$24:$H$173,"<"&L$36) -> 1647262.6 | M44: =$L$4+SUMIFS($D$24:$D$173,$G$24:$G$173,"Transferencia a Petrini",$H$24:$H$173,"<"&M$36)*-1+SUMIFS($D$24:$D$173,$G$24:$G$173,"Transferencia de Petrini",$H$24:$H$173,"<"&M$36) -> 1647262.6 | N44: =$L$4+SUMIFS($D$24:$D$173,$G$24:$G$173,"Transferencia a Petrini",$H$24:$H$173,"<"&N$36)*-1+SUMIFS($D$24:$D$173,$G$24:$G$173,"Transferencia de Petrini",$H$24:$H$173,"<"&N$36) -> 1647262.6
B45: 22 | J45: Tenencia real
B46: 23 | J46: Rendimiento (neto) | K46: =IF(K45="","",K45-K44) | L46: =IF(L45="","",L45-L44) | M46: =IF(M45="","",M45-M44) | N46: =IF(N45="","",N45-N44)
B47: 24 | J47: Rendimiento (%) | K47: =IF(K46="","",((K45-K44)/K44)) | L47: =IF(L46="","",((L45-L44)/L44)) | M47: =IF(M46="","",((M45-M44)/M44)) | N47: =IF(N46="","",((N45-N44)/N44))
B48: 25
B49: 26
B50: 27
B51: 28
B52: 29
B53: 30
B54: 31
B55: 32
B56: 33
B57: 34
B58: 35
B59: 36
... B173: 150

Sheet Gastos diciembre
B1: Datos del periodo | J1: Tenencia - Inicio | K1: USD | L1: ARS | N1: Tenencia - Fin | O1: USD | P1: ARS | R1: Diferencia | S1: USD | T1: ARS
B2: Año: | C2: 2026 | J2: Regalo recibida | K2: ='Gastos noviembre'!O2 -> 10000 | L2: =K2*D7 -> 0 | N2: Regalo recibida | O2: =K2+SUMIF($E$24:$E$173,$N2,$C$24:$C$173)+SUMIF($E$24:$E$173,$N2,$D$24:$D$173) -> 10000 | P2: =O2*$D$7 -> 0 | R2: Regalo recibida | S2: =IFERROR(IF(O2>K2,O2-K2,K2-O2),0) -> 0 | T2: =IFERROR(IF(P2>L2,P2-L2,L2-P2),0) -> 0
B3: Mes: | C3: diciembre | J3: Caja de seguridad | K3: ='Gastos noviembre'!O3 -> 500 | L3: =K3*D7 -> 0 | N3: Caja de seguridad | O3: =K3 -> 500 | P3: =L3+SUMIF($E$24:$E$173,$N3,$C$24:$C$173)+SUMIF($E$24:$E$173,$N3,$D$24:$D$173) -> 0 | R3: Caja de seguridad | S3: =IFERROR(IF(O3>K3,O3-K3,K3-O3),0) -> 0 | T3: =IFERROR(IF(P3>L3,P3-L3,L3-P3),0) -> 0
B4: Cantidad de días: | C4: =DAY(EOMONTH(DATE($C$2,MATCH($C$3,{"enero";"febrero";"marzo";"abril";"mayo";"junio";"julio";"agosto";"septiembre";"octubre";"noviembre";"diciembre"},0),1),0)) -> 31 | J4: Cta. Comitente Petrini | K4: ='Gastos noviembre'!O4 | L4: ='Gastos noviembre'!P4 -> 1647262.6 | N4: Cta. Comitente Petrini | O4: =IFERROR(P4/$C$8,"") | P4: =L4+SUMIF($E$24:$E$173,$N4,$C$24:$C$173)+SUMIF($E$24:$E$173,$N4,$D$24:$D$173) -> 1647262.6 | R4: Cta. Comitente Petrini | S4: =IFERROR(IF(O4>K4,O4-K4,K4-O4),0) -> 0 | T4: =IFERROR(IF(P4>L4,P4-L4,L4-P4),0) -> 0
J5: Superfondos Santander | K5: ='Gastos noviembre'!O5 | L5: ='Gastos noviembre'!P5 -> 3896368.8 | N5: Superfondos Santander | O5: =IFERROR(P5/$C$8,"") | P5: =L5+SUMIF($E$24:$E$173,$N5,$C$24:$C$173)+SUMIF($E$24:$E$173,$N5,$D$24:$D$173) -> 3896368.8 | R5: Superfondos Santander | S5: =IFERROR(IF(O5>K5,O5-K5,K5-O5),0) -> 0 | T5: =IFERROR(IF(P5>L5,P5-L5,L5-P5),0) -> 0
B6: Tc | C6: Compra | D6: Venta | J6: Caja de Ahorro Santander (ARS) | K6: ='Gastos noviembre'!O6 | L6: ='Gastos noviembre'!P6 -> 5648.43 | N6: Caja de Ahorro Santander (ARS) | O6: =IFERROR(P6/$C$8,"") | P6: =L6+SUMIF($E$24:$E$173,$N6,$C$24:$C$173)+SUMIF($E$24:$E$173,$N6,$D$24:$D$173) -> 5648.43 | R6: Caja de Ahorro Santander (ARS) | S6: =IFERROR(IF(O6>K6,O6-K6,K6-O6),0) -> 0 | T6: =IFERROR(IF(P6>L6,P6-L6,L6-P6),0) -> 0
B7: =DATE($C$2,MATCH($C$3,{"enero";"febrero";"marzo";"abril";"mayo";"junio";"julio";"agosto";"septiembre";"octubre";"noviembre";"diciembre"},0),1) -> 46357 | J7: Caja de Ahorro Santander (USD) | K7: ='Gastos noviembre'!O7 -> 1.88 | L7: =K7*D7 -> 0 | N7: Caja de Ahorro Santander (USD) | O7: =K7+SUM(C17:C19)+SUM(D17:D19) -> 1.88 | P7: =O7*$D$8 -> 0 | R7: Caja de Ahorro Santander (USD) | S7: =IFERROR(IF(O7>K7,O7-K7,K7-O7),0) -> 0 | T7: =IFERROR(IF(P7>L7,P7-L7,L7-P7),0) -> 0
B8: =DATE($C$2,MATCH($C$3,{"enero";"febrero";"marzo";"abril";"mayo";"junio";"julio";"agosto";"septiembre";"octubre";"noviembre";"diciembre"},0),C4) -> 46387 | J8: Mercado Pago | K8: ='Gastos noviembre'!O8 | L8: ='Gastos noviembre'!P8 -> 565.09 | N8: Mercado Libre | O8: =IFERROR(P8/$C$8,"") | P8: =L8+SUMIF($E$24:$E$173,$N8,$C$24:$C$173)+SUMIF($E$24:$E$173,$N8,$D$24:$D$173) -> 565.09 | R8: Mercado Libre | S8: =IFERROR(IF(O8>K8,O8-K8,K8-O8),0) -> 0 | T8: =IFERROR(IF(P8>L8,P8-L8,L8-P8),0) -> 0
J9: Brubank | K9: ='Gastos noviembre'!O9 | L9: ='Gastos noviembre'!P9 -> 1.36 | N9: Brubank | O9: =IFERROR(P9/$C$8,"") | P9: =L9+SUMIF($E$24:$E$173,$N9,$C$24:$C$173)+SUMIF($E$24:$E$173,$N9,$D$24:$D$173) -> 1.36 | R9: Brubank | S9: =IFERROR(IF(O9>K9,O9-K9,K9-O9),0) -> 0 | T9: =IFERROR(IF(P9>L9,P9-L9,L9-P9),0) -> 0
J10: Efectivo | K10: ='Gastos noviembre'!O10 | L10: ='Gastos noviembre'!P10 -> 32600 | N10: Efectivo | O10: =IFERROR(P10/$C$8,"") | P10: =L10+SUMIF($E$24:$E$173,$N10,$C$24:$C$173)+SUMIF($E$24:$E$173,$N10,$D$24:$D$173) -> 32600 | R10: Efectivo | S10: =IFERROR(IF(O10>K10,O10-K10,K10-O10),0) -> 0 | T10: =IFERROR(IF(P10>L10,P10-L10,L10-P10),0) -> 0
J12: Total | K12: =SUM(K2:K10) -> 10501.88 | L12: =SUM(L2:L10) -> 5582446.3 | N12: Total | O12: =SUM(O2:O9) -> 10501.88 | P12: =SUM(P2:P9) -> 5549846.3 | R12: Total | S12: =SUM(S2:S9) -> 0 | T12: =SUM(T2:T9) -> 0
B15: Compra/venta USD | J15: Análisis gastos e ingresos
B16: Nro. | C16: Ingresos | D16: Gastos | E16: Origen/Destino | F16: Concepto | G16: Descripción | H16: Fecha | J16: Concepto | K16: Acumulado egresos | L16: Acumulado ingresos | M16: Composición egresos | N16: Composición ingresos
B17: 1 | J17: Pago Claude/Cursor | K17: =SUMIF($F$24:$F$173,$J17,$D$24:$D$173) -> 0 | L17: =SUMIF($F$24:$F$173,$J17,$C$24:$C$173) -> 0 | M17: =IFERROR(K17/SUM(K$17:K$32),"") | N17: =IFERROR(L17/SUM(L$17:L$32),"")
B18: 2 | J18: Salidas a cenar/almorzar | K18: =SUMIF($F$24:$F$173,$J18,$C$24:$C$173)+SUMIF($F$24:$F$173,$J18,$D$24:$D$173) -> 0 | L18: =SUMIF($F$24:$F$173,$J18,$C$24:$C$173) -> 0 | M18: =IFERROR(K18/SUM(K$17:K$32),"") | N18: =IFERROR(L18/SUM(L$17:L$32),"")
B19: 3 | J19: Salidas a desyunar/merendar | K19: =SUMIF($F$24:$F$173,$J19,$C$24:$C$173)+SUMIF($F$24:$F$173,$J19,$D$24:$D$173) -> 0 | L19: =SUMIF($F$24:$F$173,$J19,$C$24:$C$173) -> 0 | M19: =IFERROR(K19/SUM(K$17:K$32),"") | N19: =IFERROR(L19/SUM(L$17:L$32),"")
J20: Salidas a tomar algo | K20: =SUMIF($F$24:$F$173,$J20,$C$24:$C$173)+SUMIF($F$24:$F$173,$J20,$D$24:$D$173) -> 0 | L20: =SUMIF($F$24:$F$173,$J20,$C$24:$C$173) -> 0 | M20: =IFERROR(K20/SUM(K$17:K$32),"") | N20: =IFERROR(L20/SUM(L$17:L$32),"")
J21: Fiestas | K21: =SUMIF($F$24:$F$173,$J21,$C$24:$C$173)+SUMIF($F$24:$F$173,$J21,$D$24:$D$173) -> 0 | L21: =SUMIF($F$24:$F$173,$J21,$C$24:$C$173) -> 0 | M21: =IFERROR(K21/SUM(K$17:K$32),"") | N21: =IFERROR(L21/SUM(L$17:L$32),"")
B22: Movimientos en ARS | J22: Auto | K22: =SUMIF($F$24:$F$173,$J22,$C$24:$C$173)+SUMIF($F$24:$F$173,$J22,$D$24:$D$173) -> 0 | L22: =SUMIF($F$24:$F$173,$J22,$C$24:$C$173) -> 0 | M22: =IFERROR(K22/SUM(K$17:K$32),"") | N22: =IFERROR(L22/SUM(L$17:L$32),"")
B23: Nro. | C23: Ingresos | D23: Gastos | E23: Origen/Destino | F23: Concepto | G23: Descripción | H23: Fecha | J23: Farmacia/Cosméticos | K23: =SUMIF($F$24:$F$173,$J23,$C$24:$C$173)+SUMIF($F$24:$F$173,$J23,$D$24:$D$173) -> 0 | L23: =SUMIF($F$24:$F$173,$J23,$C$24:$C$173) -> 0 | M23: =IFERROR(K23/SUM(K$17:K$32),"") | N23: =IFERROR(L23/SUM(L$17:L$32),"")
B24: 1 | J24: Ropa | K24: =SUMIF($F$24:$F$173,$J24,$C$24:$C$173)+SUMIF($F$24:$F$173,$J24,$D$24:$D$173) -> 0 | L24: =SUMIF($F$24:$F$173,$J24,$C$24:$C$173) -> 0 | M24: =IFERROR(K24/SUM(K$17:K$32),"") | N24: =IFERROR(L24/SUM(L$17:L$32),"")
B25: 2 | J25: Súper | K25: =SUMIF($F$24:$F$173,$J25,$C$24:$C$173)+SUMIF($F$24:$F$173,$J25,$D$24:$D$173) -> 0 | L25: =SUMIF($F$24:$F$173,$J25,$C$24:$C$173) -> 0 | M25: =IFERROR(K25/SUM(K$17:K$32),"") | N25: =IFERROR(L25/SUM(L$17:L$32),"")
B26: 3 | J26: Delivery | K26: =SUMIF($F$24:$F$173,$J26,$C$24:$C$173)+SUMIF($F$24:$F$173,$J26,$D$24:$D$173) -> 0 | L26: =SUMIF($F$24:$F$173,$J26,$C$24:$C$173) -> 0 | M26: =IFERROR(K26/SUM(K$17:K$32),"") | N26: =IFERROR(L26/SUM(L$17:L$32),"")
B27: 4 | J27: Regalos | K27: =SUMIF($F$24:$F$173,$J27,$C$24:$C$173)+SUMIF($F$24:$F$173,$J27,$D$24:$D$173) -> 0 | L27: =SUMIF($F$24:$F$173,$J27,$C$24:$C$173) -> 0 | M27: =IFERROR(K27/SUM(K$17:K$32),"") | N27: =IFERROR(L27/SUM(L$17:L$32),"")
B28: 5 | J28: Entradas fiestas/conciertos | K28: =SUMIF($F$24:$F$173,$J28,$C$24:$C$173)+SUMIF($F$24:$F$173,$J28,$D$24:$D$173) -> 0 | L28: =SUMIF($F$24:$F$173,$J28,$C$24:$C$173) -> 0 | M28: =IFERROR(K28/SUM(K$17:K$32),"") | N28: =IFERROR(L28/SUM(L$17:L$32),"")
B29: 6 | J29: Pago de honorarios Quantum | K29: =SUMIF($F$24:$F$173,$J29,$C$24:$C$173)+SUMIF($F$24:$F$173,$J29,$D$24:$D$173) -> 0 | L29: =SUMIF($F$24:$F$173,$J29,$C$24:$C$173) -> 0 | M29: =IFERROR(K29/SUM(K$17:K$32),"") | N29: =IFERROR(L29/SUM(L$17:L$32),"")
B30: 7 | J30: Pago de honorarios Axis | K30: =SUMIF($F$24:$F$173,$J30,$C$24:$C$173)+SUMIF($F$24:$F$173,$J30,$D$24:$D$173) -> 0 | L30: =SUMIF($F$24:$F$173,$J30,$C$24:$C$173) -> 0 | M30: =IFERROR(K30/SUM(K$17:K$32),"") | N30: =IFERROR(L30/SUM(L$17:L$32),"")
B31: 8 | J31: Otros honorarios | K31: =SUMIF($F$24:$F$173,$J31,$C$24:$C$173)+SUMIF($F$24:$F$173,$J31,$D$24:$D$173) -> 0 | L31: =SUMIF($F$24:$F$173,$J31,$C$24:$C$173) -> 0 | M31: =IFERROR(K31/SUM(K$17:K$32),"") | N31: =IFERROR(L31/SUM(L$17:L$32),"")
B32: 9 | J32: Ahorros/inversiones | K32: =SUMIF($F$24:$F$173,$J32,$C$24:$C$173)+SUMIF($F$24:$F$173,$J32,$D$24:$D$173) -> 0 | L32: =SUMIF($F$24:$F$173,$J32,$C$24:$C$173) -> 0 | M32: =IFERROR(K32/SUM(K$17:K$32),"") | N32: =IFERROR(L32/SUM(L$17:L$32),"")
B33: 10 | J33: Pago tarjetas de crédito | K33: =SUMIF($F$24:$F$173,$J33,$C$24:$C$173)+SUMIF($F$24:$F$173,$J33,$D$24:$D$173) -> 0 | L33: =SUMIF($F$24:$F$173,$J33,$C$24:$C$173) -> 0 | M33: =IFERROR(K33/SUM(K$17:K$32),"") | N33: =IFERROR(L33/SUM(L$17:L$32),"")
B34: 11
B35: 12 | J35: Superfondos Santander
B36: 13 | J36: Superfondos Santander | K36: 46272 | L36: 46279 | M36: 46286 | N36: 46293
B37: 14 | J37: Calculado | K37: =$L$5+SUMIFS($C$24:$C$173,$E$24:$E$173,$N5,$H$24:$H$173,"<="&K$36)+SUMIFS($D$24:$D$173,$E$24:$E$173,$N5,$H$24:$H$173,"<="&K$36) -> 3896368.8 | L37: =$L$5+SUMIFS($C$24:$C$173,$E$24:$E$173,$N5,$H$24:$H$173,"<"&L$36)+SUMIFS($D$24:$D$173,$E$24:$E$173,$N5,$H$24:$H$173,"<="&L$36) -> 3896368.8 | M37: =$L$5+SUMIFS($C$24:$C$173,$E$24:$E$173,$N5,$H$24:$H$173,"<"&M$36)+SUMIFS($D$24:$D$173,$E$24:$E$173,$N5,$H$24:$H$173,"<="&M$36) -> 3896368.8 | N37: =$L$5+SUMIFS($C$24:$C$173,$E$24:$E$173,$N5,$H$24:$H$173,"<"&N$36)+SUMIFS($D$24:$D$173,$E$24:$E$173,$N5,$H$24:$H$173,"<="&N$36) -> 3896368.8
B38: 15 | J38: Real
B39: 16 | J39: Rendimiento (neto) | K39: =IF(K38="","",K38-K37) | L39: =IF(L38="","",L38-L37) | M39: =IF(M38="","",M38-M37) | N39: =IF(N38="","",N38-N37)
B40: 17 | J40: Rendimiento (%) | K40: =IF(K39="","",((K38-K37)/K37)) | L40: =IF(L39="","",((L38-L37)/L37)) | M40: =IF(M39="","",((M38-M37)/M37)) | N40: =IF(N39="","",((N38-N37)/N37))
B41: 18
B42: 19 | J42: Petrini
B43: 20 | J43: Fecha | K43: =K36 -> 46272 | L43: =L36 -> 46279 | M43: =M36 -> 46286 | N43: =N36 -> 46293
B44: 21 | J44: Tenencia calculada | K44: =$L$4+SUMIFS($D$24:$D$173,$G$24:$G$173,"Transferencia a Petrini",$H$24:$H$173,"<"&K$36)*-1+SUMIFS($D$24:$D$173,$G$24:$G$173,"Transferencia de Petrini",$H$24:$H$173,"<"&K$36) -> 1647262.6 | L44: =$L$4+SUMIFS($D$24:$D$173,$G$24:$G$173,"Transferencia a Petrini",$H$24:$H$173,"<"&L$36)*-1+SUMIFS($D$24:$D$173,$G$24:$G$173,"Transferencia de Petrini",$H$24:$H$173,"<"&L$36) -> 1647262.6 | M44: =$L$4+SUMIFS($D$24:$D$173,$G$24:$G$173,"Transferencia a Petrini",$H$24:$H$173,"<"&M$36)*-1+SUMIFS($D$24:$D$173,$G$24:$G$173,"Transferencia de Petrini",$H$24:$H$173,"<"&M$36) -> 1647262.6 | N44: =$L$4+SUMIFS($D$24:$D$173,$G$24:$G$173,"Transferencia a Petrini",$H$24:$H$173,"<"&N$36)*-1+SUMIFS($D$24:$D$173,$G$24:$G$173,"Transferencia de Petrini",$H$24:$H$173,"<"&N$36) -> 1647262.6
B45: 22 | J45: Tenencia real
B46: 23 | J46: Rendimiento (neto) | K46: =IF(K45="","",K45-K44) | L46: =IF(L45="","",L45-L44) | M46: =IF(M45="","",M45-M44) | N46: =IF(N45="","",N45-N44)
B47: 24 | J47: Rendimiento (%) | K47: =IF(K46="","",((K45-K44)/K44)) | L47: =IF(L46="","",((L45-L44)/L44)) | M47: =IF(M46="","",((M45-M44)/M44)) | N47: =IF(N46="","",((N45-N44)/N44))
B48: 25
B49: 26
B50: 27
B51: 28
B52: 29
B53: 30
B54: 31
B55: 32
B56: 33
B57: 34
B58: 35
B59: 36
... B173: 150

Sheet Gastos 2026
B2: Consolidado de gastos e ingresos netos 2026 - Movimientos en ARS
B4: Concepto | C4: julio | D4: agosto | E4: septiembre | F4: octubre | G4: noviembre | H4: diciembre | I4: Total año
B5: ='Datos - Gastos'!A2 -> Pago Claude/Cursor | C5: =SUMIF('Gastos julio'!$F$24:$F$173,$B5,'Gastos julio'!$C$24:$C$173)+SUMIF('Gastos julio'!$F$24:$F$173,$B5,'Gastos julio'!$D$24:$D$173) -> 16000 | D5: =SUMIF('Gastos agosto'!$F$24:$F$173,$B5,'Gastos agosto'!$C$24:$C$173)+SUMIF('Gastos agosto'!$F$24:$F$173,$B5,'Gastos agosto'!$D$24:$D$173) -> 60150 | E5: =SUMIF('Gastos septiembre'!$F$24:$F$173,$B5,'Gastos septiembre'!$C$24:$C$173)+SUMIF('Gastos septiembre'!$F$24:$F$173,$B5,'Gastos septiembre'!$D$24:$D$173) -> 0 | F5: =SUMIF('Gastos octubre'!$F$24:$F$173,$B5,'Gastos octubre'!$C$24:$C$173)+SUMIF('Gastos octubre'!$F$24:$F$173,$B5,'Gastos octubre'!$D$24:$D$173) -> 0 | G5: =SUMIF('Gastos noviembre'!$F$24:$F$173,$B5,'Gastos noviembre'!$C$24:$C$173)+SUMIF('Gastos noviembre'!$F$24:$F$173,$B5,'Gastos noviembre'!$D$24:$D$173) -> 0 | H5: =SUMIF('Gastos diciembre'!$F$24:$F$173,$B5,'Gastos diciembre'!$C$24:$C$173)+SUMIF('Gastos diciembre'!$F$24:$F$173,$B5,'Gastos diciembre'!$D$24:$D$173) -> 0 | I5: =SUM(C5:H5) -> 76150
B6: ='Datos - Gastos'!A3 -> Salidas a cenar/almorzar | C6: =SUMIF('Gastos julio'!$F$24:$F$173,$B6,'Gastos julio'!$C$24:$C$173)+SUMIF('Gastos julio'!$F$24:$F$173,$B6,'Gastos julio'!$D$24:$D$173) -> -139930 | D6: =SUMIF('Gastos agosto'!$F$24:$F$173,$B6,'Gastos agosto'!$C$24:$C$173)+SUMIF('Gastos agosto'!$F$24:$F$173,$B6,'Gastos agosto'!$D$24:$D$173) -> -255130.74 | E6: =SUMIF('Gastos septiembre'!$F$24:$F$173,$B6,'Gastos septiembre'!$C$24:$C$173)+SUMIF('Gastos septiembre'!$F$24:$F$173,$B6,'Gastos septiembre'!$D$24:$D$173) -> -39300 | F6: =SUMIF('Gastos octubre'!$F$24:$F$173,$B6,'Gastos octubre'!$C$24:$C$173)+SUMIF('Gastos octubre'!$F$24:$F$173,$B6,'Gastos octubre'!$D$24:$D$173) -> 0 | G6: =SUMIF('Gastos noviembre'!$F$24:$F$173,$B6,'Gastos noviembre'!$C$24:$C$173)+SUMIF('Gastos noviembre'!$F$24:$F$173,$B6,'Gastos noviembre'!$D$24:$D$173) -> 0 | H6: =SUMIF('Gastos diciembre'!$F$24:$F$173,$B6,'Gastos diciembre'!$C$24:$C$173)+SUMIF('Gastos diciembre'!$F$24:$F$173,$B6,'Gastos diciembre'!$D$24:$D$173) -> 0 | I6: =SUM(C6:H6) -> -434360.74
B7: ='Datos - Gastos'!A4 -> Juntadas a cenar/almorzar | C7: =SUMIF('Gastos julio'!$F$24:$F$173,$B7,'Gastos julio'!$C$24:$C$173)+SUMIF('Gastos julio'!$F$24:$F$173,$B7,'Gastos julio'!$D$24:$D$173) -> 0 | D7: =SUMIF('Gastos agosto'!$F$24:$F$173,$B7,'Gastos agosto'!$C$24:$C$173)+SUMIF('Gastos agosto'!$F$24:$F$173,$B7,'Gastos agosto'!$D$24:$D$173) -> -102414.27 | E7: =SUMIF('Gastos septiembre'!$F$24:$F$173,$B7,'Gastos septiembre'!$C$24:$C$173)+SUMIF('Gastos septiembre'!$F$24:$F$173,$B7,'Gastos septiembre'!$D$24:$D$173) -> -183336.2 | F7: =SUMIF('Gastos octubre'!$F$24:$F$173,$B7,'Gastos octubre'!$C$24:$C$173)+SUMIF('Gastos octubre'!$F$24:$F$173,$B7,'Gastos octubre'!$D$24:$D$173) -> 0 | G7: =SUMIF('Gastos noviembre'!$F$24:$F$173,$B7,'Gastos noviembre'!$C$24:$C$173)+SUMIF('Gastos noviembre'!$F$24:$F$173,$B7,'Gastos noviembre'!$D$24:$D$173) -> 0 | H7: =SUMIF('Gastos diciembre'!$F$24:$F$173,$B7,'Gastos diciembre'!$C$24:$C$173)+SUMIF('Gastos diciembre'!$F$24:$F$173,$B7,'Gastos diciembre'!$D$24:$D$173) -> 0 | I7: =SUM(C7:H7) -> -285750.47
B8: ='Datos - Gastos'!A5 -> Salidas a desyunar/merendar | C8: =SUMIF('Gastos julio'!$F$24:$F$173,$B8,'Gastos julio'!$C$24:$C$173)+SUMIF('Gastos julio'!$F$24:$F$173,$B8,'Gastos julio'!$D$24:$D$173) -> -110800 | D8: =SUMIF('Gastos agosto'!$F$24:$F$173,$B8,'Gastos agosto'!$C$24:$C$173)+SUMIF('Gastos agosto'!$F$24:$F$173,$B8,'Gastos agosto'!$D$24:$D$173) -> -25100 | E8: =SUMIF('Gastos septiembre'!$F$24:$F$173,$B8,'Gastos septiembre'!$C$24:$C$173)+SUMIF('Gastos septiembre'!$F$24:$F$173,$B8,'Gastos septiembre'!$D$24:$D$173) -> -55400 | F8: =SUMIF('Gastos octubre'!$F$24:$F$173,$B8,'Gastos octubre'!$C$24:$C$173)+SUMIF('Gastos octubre'!$F$24:$F$173,$B8,'Gastos octubre'!$D$24:$D$173) -> 0 | G8: =SUMIF('Gastos noviembre'!$F$24:$F$173,$B8,'Gastos noviembre'!$C$24:$C$173)+SUMIF('Gastos noviembre'!$F$24:$F$173,$B8,'Gastos noviembre'!$D$24:$D$173) -> 0 | H8: =SUMIF('Gastos diciembre'!$F$24:$F$173,$B8,'Gastos diciembre'!$C$24:$C$173)+SUMIF('Gastos diciembre'!$F$24:$F$173,$B8,'Gastos diciembre'!$D$24:$D$173) -> 0 | I8: =SUM(C8:H8) -> -191300
B9: ='Datos - Gastos'!A6 -> Juntadas a desayunar/merendar | C9: =SUMIF('Gastos julio'!$F$24:$F$173,$B9,'Gastos julio'!$C$24:$C$173)+SUMIF('Gastos julio'!$F$24:$F$173,$B9,'Gastos julio'!$D$24:$D$173) -> 0 | D9: =SUMIF('Gastos agosto'!$F$24:$F$173,$B9,'Gastos agosto'!$C$24:$C$173)+SUMIF('Gastos agosto'!$F$24:$F$173,$B9,'Gastos agosto'!$D$24:$D$173) -> 0 | E9: =SUMIF('Gastos septiembre'!$F$24:$F$173,$B9,'Gastos septiembre'!$C$24:$C$173)+SUMIF('Gastos septiembre'!$F$24:$F$173,$B9,'Gastos septiembre'!$D$24:$D$173) -> 0 | F9: =SUMIF('Gastos octubre'!$F$24:$F$173,$B9,'Gastos octubre'!$C$24:$C$173)+SUMIF('Gastos octubre'!$F$24:$F$173,$B9,'Gastos octubre'!$D$24:$D$173) -> 0 | G9: =SUMIF('Gastos noviembre'!$F$24:$F$173,$B9,'Gastos noviembre'!$C$24:$C$173)+SUMIF('Gastos noviembre'!$F$24:$F$173,$B9,'Gastos noviembre'!$D$24:$D$173) -> 0 | H9: =SUMIF('Gastos diciembre'!$F$24:$F$173,$B9,'Gastos diciembre'!$C$24:$C$173)+SUMIF('Gastos diciembre'!$F$24:$F$173,$B9,'Gastos diciembre'!$D$24:$D$173) -> 0 | I9: =SUM(C9:H9) -> 0
B10: ='Datos - Gastos'!A7 -> Salidas a tomar algo | C10: =SUMIF('Gastos julio'!$F$24:$F$173,$B10,'Gastos julio'!$C$24:$C$173)+SUMIF('Gastos julio'!$F$24:$F$173,$B10,'Gastos julio'!$D$24:$D$173) -> -33000 | D10: =SUMIF('Gastos agosto'!$F$24:$F$173,$B10,'Gastos agosto'!$C$24:$C$173)+SUMIF('Gastos agosto'!$F$24:$F$173,$B10,'Gastos agosto'!$D$24:$D$173) -> -75330 | E10: =SUMIF('Gastos septiembre'!$F$24:$F$173,$B10,'Gastos septiembre'!$C$24:$C$173)+SUMIF('Gastos septiembre'!$F$24:$F$173,$B10,'Gastos septiembre'!$D$24:$D$173) -> -71900 | F10: =SUMIF('Gastos octubre'!$F$24:$F$173,$B10,'Gastos octubre'!$C$24:$C$173)+SUMIF('Gastos octubre'!$F$24:$F$173,$B10,'Gastos octubre'!$D$24:$D$173) -> 0 | G10: =SUMIF('Gastos noviembre'!$F$24:$F$173,$B10,'Gastos noviembre'!$C$24:$C$173)+SUMIF('Gastos noviembre'!$F$24:$F$173,$B10,'Gastos noviembre'!$D$24:$D$173) -> 0 | H10: =SUMIF('Gastos diciembre'!$F$24:$F$173,$B10,'Gastos diciembre'!$C$24:$C$173)+SUMIF('Gastos diciembre'!$F$24:$F$173,$B10,'Gastos diciembre'!$D$24:$D$173) -> 0 | I10: =SUM(C10:H10) -> -180230
B11: ='Datos - Gastos'!A8 -> Fiestas | C11: =SUMIF('Gastos julio'!$F$24:$F$173,$B11,'Gastos julio'!$C$24:$C$173)+SUMIF('Gastos julio'!$F$24:$F$173,$B11,'Gastos julio'!$D$24:$D$173) -> 0 | D11: =SUMIF('Gastos agosto'!$F$24:$F$173,$B11,'Gastos agosto'!$C$24:$C$173)+SUMIF('Gastos agosto'!$F$24:$F$173,$B11,'Gastos agosto'!$D$24:$D$173) -> -24600 | E11: =SUMIF('Gastos septiembre'!$F$24:$F$173,$B11,'Gastos septiembre'!$C$24:$C$173)+SUMIF('Gastos septiembre'!$F$24:$F$173,$B11,'Gastos septiembre'!$D$24:$D$173) -> 0 | F11: =SUMIF('Gastos octubre'!$F$24:$F$173,$B11,'Gastos octubre'!$C$24:$C$173)+SUMIF('Gastos octubre'!$F$24:$F$173,$B11,'Gastos octubre'!$D$24:$D$173) -> 0 | G11: =SUMIF('Gastos noviembre'!$F$24:$F$173,$B11,'Gastos noviembre'!$C$24:$C$173)+SUMIF('Gastos noviembre'!$F$24:$F$173,$B11,'Gastos noviembre'!$D$24:$D$173) -> 0 | H11: =SUMIF('Gastos diciembre'!$F$24:$F$173,$B11,'Gastos diciembre'!$C$24:$C$173)+SUMIF('Gastos diciembre'!$F$24:$F$173,$B11,'Gastos diciembre'!$D$24:$D$173) -> 0 | I11: =SUM(C11:H11) -> -24600
B12: ='Datos - Gastos'!A9 -> Auto | C12: =SUMIF('Gastos julio'!$F$24:$F$173,$B12,'Gastos julio'!$C$24:$C$173)+SUMIF('Gastos julio'!$F$24:$F$173,$B12,'Gastos julio'!$D$24:$D$173) -> -76600 | D12: =SUMIF('Gastos agosto'!$F$24:$F$173,$B12,'Gastos agosto'!$C$24:$C$173)+SUMIF('Gastos agosto'!$F$24:$F$173,$B12,'Gastos agosto'!$D$24:$D$173) -> -125000 | E12: =SUMIF('Gastos septiembre'!$F$24:$F$173,$B12,'Gastos septiembre'!$C$24:$C$173)+SUMIF('Gastos septiembre'!$F$24:$F$173,$B12,'Gastos septiembre'!$D$24:$D$173) -> -56000 | F12: =SUMIF('Gastos octubre'!$F$24:$F$173,$B12,'Gastos octubre'!$C$24:$C$173)+SUMIF('Gastos octubre'!$F$24:$F$173,$B12,'Gastos octubre'!$D$24:$D$173) -> 0 | G12: =SUMIF('Gastos noviembre'!$F$24:$F$173,$B12,'Gastos noviembre'!$C$24:$C$173)+SUMIF('Gastos noviembre'!$F$24:$F$173,$B12,'Gastos noviembre'!$D$24:$D$173) -> 0 | H12: =SUMIF('Gastos diciembre'!$F$24:$F$173,$B12,'Gastos diciembre'!$C$24:$C$173)+SUMIF('Gastos diciembre'!$F$24:$F$173,$B12,'Gastos diciembre'!$D$24:$D$173) -> 0 | I12: =SUM(C12:H12) -> -257600
B13: ='Datos - Gastos'!A10 -> Celular | C13: =SUMIF('Gastos julio'!$F$24:$F$173,$B13,'Gastos julio'!$C$24:$C$173)+SUMIF('Gastos julio'!$F$24:$F$173,$B13,'Gastos julio'!$D$24:$D$173) -> 0 | D13: =SUMIF('Gastos agosto'!$F$24:$F$173,$B13,'Gastos agosto'!$C$24:$C$173)+SUMIF('Gastos agosto'!$F$24:$F$173,$B13,'Gastos agosto'!$D$24:$D$173) -> -7000 | E13: =SUMIF('Gastos septiembre'!$F$24:$F$173,$B13,'Gastos septiembre'!$C$24:$C$173)+SUMIF('Gastos septiembre'!$F$24:$F$173,$B13,'Gastos septiembre'!$D$24:$D$173) -> 0 | F13: =SUMIF('Gastos octubre'!$F$24:$F$173,$B13,'Gastos octubre'!$C$24:$C$173)+SUMIF('Gastos octubre'!$F$24:$F$173,$B13,'Gastos octubre'!$D$24:$D$173) -> 0 | G13: =SUMIF('Gastos noviembre'!$F$24:$F$173,$B13,'Gastos noviembre'!$C$24:$C$173)+SUMIF('Gastos noviembre'!$F$24:$F$173,$B13,'Gastos noviembre'!$D$24:$D$173) -> 0 | H13: =SUMIF('Gastos diciembre'!$F$24:$F$173,$B13,'Gastos diciembre'!$C$24:$C$173)+SUMIF('Gastos diciembre'!$F$24:$F$173,$B13,'Gastos diciembre'!$D$24:$D$173) -> 0 | I13: =SUM(C13:H13) -> -7000
B14: ='Datos - Gastos'!A11 -> Farmacia/Cosméticos | C14: =SUMIF('Gastos julio'!$F$24:$F$173,$B14,'Gastos julio'!$C$24:$C$173)+SUMIF('Gastos julio'!$F$24:$F$173,$B14,'Gastos julio'!$D$24:$D$173) -> -33852.49 | D14: =SUMIF('Gastos agosto'!$F$24:$F$173,$B14,'Gastos agosto'!$C$24:$C$173)+SUMIF('Gastos agosto'!$F$24:$F$173,$B14,'Gastos agosto'!$D$24:$D$173) -> -6686.31 | E14: =SUMIF('Gastos septiembre'!$F$24:$F$173,$B14,'Gastos septiembre'!$C$24:$C$173)+SUMIF('Gastos septiembre'!$F$24:$F$173,$B14,'Gastos septiembre'!$D$24:$D$173) -> -21560.32 | F14: =SUMIF('Gastos octubre'!$F$24:$F$173,$B14,'Gastos octubre'!$C$24:$C$173)+SUMIF('Gastos octubre'!$F$24:$F$173,$B14,'Gastos octubre'!$D$24:$D$173) -> 0 | G14: =SUMIF('Gastos noviembre'!$F$24:$F$173,$B14,'Gastos noviembre'!$C$24:$C$173)+SUMIF('Gastos noviembre'!$F$24:$F$173,$B14,'Gastos noviembre'!$D$24:$D$173) -> 0 | H14: =SUMIF('Gastos diciembre'!$F$24:$F$173,$B14,'Gastos diciembre'!$C$24:$C$173)+SUMIF('Gastos diciembre'!$F$24:$F$173,$B14,'Gastos diciembre'!$D$24:$D$173) -> 0 | I14: =SUM(C14:H14) -> -62099.12
B15: ='Datos - Gastos'!A12 -> Ropa | C15: =SUMIF('Gastos julio'!$F$24:$F$173,$B15,'Gastos julio'!$C$24:$C$173)+SUMIF('Gastos julio'!$F$24:$F$173,$B15,'Gastos julio'!$D$24:$D$173) -> 0 | D15: =SUMIF('Gastos agosto'!$F$24:$F$173,$B15,'Gastos agosto'!$C$24:$C$173)+SUMIF('Gastos agosto'!$F$24:$F$173,$B15,'Gastos agosto'!$D$24:$D$173) -> 0 | E15: =SUMIF('Gastos septiembre'!$F$24:$F$173,$B15,'Gastos septiembre'!$C$24:$C$173)+SUMIF('Gastos septiembre'!$F$24:$F$173,$B15,'Gastos septiembre'!$D$24:$D$173) -> 0 | F15: =SUMIF('Gastos octubre'!$F$24:$F$173,$B15,'Gastos octubre'!$C$24:$C$173)+SUMIF('Gastos octubre'!$F$24:$F$173,$B15,'Gastos octubre'!$D$24:$D$173) -> 0 | G15: =SUMIF('Gastos noviembre'!$F$24:$F$173,$B15,'Gastos noviembre'!$C$24:$C$173)+SUMIF('Gastos noviembre'!$F$24:$F$173,$B15,'Gastos noviembre'!$D$24:$D$173) -> 0 | H15: =SUMIF('Gastos diciembre'!$F$24:$F$173,$B15,'Gastos diciembre'!$C$24:$C$173)+SUMIF('Gastos diciembre'!$F$24:$F$173,$B15,'Gastos diciembre'!$D$24:$D$173) -> 0 | I15: =SUM(C15:H15) -> 0
B16: ='Datos - Gastos'!A13 -> Súper | C16: =SUMIF('Gastos julio'!$F$24:$F$173,$B16,'Gastos julio'!$C$24:$C$173)+SUMIF('Gastos julio'!$F$24:$F$173,$B16,'Gastos julio'!$D$24:$D$173) -> 0 | D16: =SUMIF('Gastos agosto'!$F$24:$F$173,$B16,'Gastos agosto'!$C$24:$C$173)+SUMIF('Gastos agosto'!$F$24:$F$173,$B16,'Gastos agosto'!$D$24:$D$173) -> 0 | E16: =SUMIF('Gastos septiembre'!$F$24:$F$173,$B16,'Gastos septiembre'!$C$24:$C$173)+SUMIF('Gastos septiembre'!$F$24:$F$173,$B16,'Gastos septiembre'!$D$24:$D$173) -> -34048 | F16: =SUMIF('Gastos octubre'!$F$24:$F$173,$B16,'Gastos octubre'!$C$24:$C$173)+SUMIF('Gastos octubre'!$F$24:$F$173,$B16,'Gastos octubre'!$D$24:$D$173) -> 0 | G16: =SUMIF('Gastos noviembre'!$F$24:$F$173,$B16,'Gastos noviembre'!$C$24:$C$173)+SUMIF('Gastos noviembre'!$F$24:$F$173,$B16,'Gastos noviembre'!$D$24:$D$173) -> 0 | H16: =SUMIF('Gastos diciembre'!$F$24:$F$173,$B16,'Gastos diciembre'!$C$24:$C$173)+SUMIF('Gastos diciembre'!$F$24:$F$173,$B16,'Gastos diciembre'!$D$24:$D$173) -> 0 | I16: =SUM(C16:H16) -> -34048
... B20: ='Datos - Gastos'!A17 -> Regalos | C20: =SUMIF('Gastos julio'!$F$24:$F$173,$B20,'Gastos julio'!$C$24:$C$173)+SUMIF('Gastos julio'!$F$24:$F$173,$B20,'Gastos julio'!$D$24:$D$173) -> 53200 | D20: =SUMIF('Gastos agosto'!$F$24:$F$173,$B20,'Gastos agosto'!$C$24:$C$173)+SUMIF('Gastos agosto'!$F$24:$F$173,$B20,'Gastos agosto'!$D$24:$D$173) -> -12850 | E20: =SUMIF('Gastos septiembre'!$F$24:$F$173,$B20,'Gastos septiembre'!$C$24:$C$173)+SUMIF('Gastos septiembre'!$F$24:$F$173,$B20,'Gastos septiembre'!$D$24:$D$173) -> -39900 | F20: =SUMIF('Gastos octubre'!$F$24:$F$173,$B20,'Gastos octubre'!$C$24:$C$173)+SUMIF('Gastos octubre'!$F$24:$F$173,$B20,'Gastos octubre'!$D$24:$D$173) -> 0 | G20: =SUMIF('Gastos noviembre'!$F$24:$F$173,$B20,'Gastos noviembre'!$C$24:$C$173)+SUMIF('Gastos noviembre'!$F$24:$F$173,$B20,'Gastos noviembre'!$D$24:$D$173) -> 0 | H20: =SUMIF('Gastos diciembre'!$F$24:$F$173,$B20,'Gastos diciembre'!$C$24:$C$173)+SUMIF('Gastos diciembre'!$F$24:$F$173,$B20,'Gastos diciembre'!$D$24:$D$173) -> 0 | I20: =SUM(C20:H20) -> 450
B21: ='Datos - Gastos'!A19 -> Entradas fiestas/conciertos/otros eventos | C21: =SUMIF('Gastos julio'!$F$24:$F$173,$B21,'Gastos julio'!$C$24:$C$173)+SUMIF('Gastos julio'!$F$24:$F$173,$B21,'Gastos julio'!$D$24:$D$173) -> 0 | D21: =SUMIF('Gastos agosto'!$F$24:$F$173,$B21,'Gastos agosto'!$C$24:$C$173)+SUMIF('Gastos agosto'!$F$24:$F$173,$B21,'Gastos agosto'!$D$24:$D$173) -> -32220 | E21: =SUMIF('Gastos septiembre'!$F$24:$F$173,$B21,'Gastos septiembre'!$C$24:$C$173)+SUMIF('Gastos septiembre'!$F$24:$F$173,$B21,'Gastos septiembre'!$D$24:$D$173) -> -201870 | F21: =SUMIF('Gastos octubre'!$F$24:$F$173,$B21,'Gastos octubre'!$C$24:$C$173)+SUMIF('Gastos octubre'!$F$24:$F$173,$B21,'Gastos octubre'!$D$24:$D$173) -> 0 | G21: =SUMIF('Gastos noviembre'!$F$24:$F$173,$B21,'Gastos noviembre'!$C$24:$C$173)+SUMIF('Gastos noviembre'!$F$24:$F$173,$B21,'Gastos noviembre'!$D$24:$D$173) -> 0 | H21: =SUMIF('Gastos diciembre'!$F$24:$F$173,$B21,'Gastos diciembre'!$C$24:$C$173)+SUMIF('Gastos diciembre'!$F$24:$F$173,$B21,'Gastos diciembre'!$D$24:$D$173) -> 0 | I21: =SUM(C21:H21) -> -234090
B22: ='Datos - Gastos'!A20 -> Pago de honorarios Quantum | C22: =SUMIF('Gastos julio'!$F$24:$F$173,$B22,'Gastos julio'!$C$24:$C$173)+SUMIF('Gastos julio'!$F$24:$F$173,$B22,'Gastos julio'!$D$24:$D$173) -> 2084047 | D22: =SUMIF('Gastos agosto'!$F$24:$F$173,$B22,'Gastos agosto'!$C$24:$C$173)+SUMIF('Gastos agosto'!$F$24:$F$173,$B22,'Gastos agosto'!$D$24:$D$173) -> 2094451.1 | E22: =SUMIF('Gastos septiembre'!$F$24:$F$173,$B22,'Gastos septiembre'!$C$24:$C$173)+SUMIF('Gastos septiembre'!$F$24:$F$173,$B22,'Gastos septiembre'!$D$24:$D$173) -> 0 | F22: =SUMIF('Gastos octubre'!$F$24:$F$173,$B22,'Gastos octubre'!$C$24:$C$173)+SUMIF('Gastos octubre'!$F$24:$F$173,$B22,'Gastos octubre'!$D$24:$D$173) -> 0 | G22: =SUMIF('Gastos noviembre'!$F$24:$F$173,$B22,'Gastos noviembre'!$C$24:$C$173)+SUMIF('Gastos noviembre'!$F$24:$F$173,$B22,'Gastos noviembre'!$D$24:$D$173) -> 0 | H22: =SUMIF('Gastos diciembre'!$F$24:$F$173,$B22,'Gastos diciembre'!$C$24:$C$173)+SUMIF('Gastos diciembre'!$F$24:$F$173,$B22,'Gastos diciembre'!$D$24:$D$173) -> 0 | I22: =SUM(C22:H22) -> 4178498.1
B23: ='Datos - Gastos'!A21 -> Pago de honorarios Axis | C23: =SUMIF('Gastos julio'!$F$24:$F$173,$B23,'Gastos julio'!$C$24:$C$173)+SUMIF('Gastos julio'!$F$24:$F$173,$B23,'Gastos julio'!$D$24:$D$173) -> 304000 | D23: =SUMIF('Gastos agosto'!$F$24:$F$173,$B23,'Gastos agosto'!$C$24:$C$173)+SUMIF('Gastos agosto'!$F$24:$F$173,$B23,'Gastos agosto'!$D$24:$D$173) -> 423500 | E23: =SUMIF('Gastos septiembre'!$F$24:$F$173,$B23,'Gastos septiembre'!$C$24:$C$173)+SUMIF('Gastos septiembre'!$F$24:$F$173,$B23,'Gastos septiembre'!$D$24:$D$173) -> 201000 | F23: =SUMIF('Gastos octubre'!$F$24:$F$173,$B23,'Gastos octubre'!$C$24:$C$173)+SUMIF('Gastos octubre'!$F$24:$F$173,$B23,'Gastos octubre'!$D$24:$D$173) -> 0 | G23: =SUMIF('Gastos noviembre'!$F$24:$F$173,$B23,'Gastos noviembre'!$C$24:$C$173)+SUMIF('Gastos noviembre'!$F$24:$F$173,$B23,'Gastos noviembre'!$D$24:$D$173) -> 0 | H23: =SUMIF('Gastos diciembre'!$F$24:$F$173,$B23,'Gastos diciembre'!$C$24:$C$173)+SUMIF('Gastos diciembre'!$F$24:$F$173,$B23,'Gastos diciembre'!$D$24:$D$173) -> 0 | I23: =SUM(C23:H23) -> 928500
B24: ='Datos - Gastos'!A22 -> Otros honorarios | C24: =SUMIF('Gastos julio'!$F$24:$F$173,$B24,'Gastos julio'!$C$24:$C$173)+SUMIF('Gastos julio'!$F$24:$F$173,$B24,'Gastos julio'!$D$24:$D$173) -> 0 | D24: =SUMIF('Gastos agosto'!$F$24:$F$173,$B24,'Gastos agosto'!$C$24:$C$173)+SUMIF('Gastos agosto'!$F$24:$F$173,$B24,'Gastos agosto'!$D$24:$D$173) -> 170000 | E24: =SUMIF('Gastos septiembre'!$F$24:$F$173,$B24,'Gastos septiembre'!$C$24:$C$173)+SUMIF('Gastos septiembre'!$F$24:$F$173,$B24,'Gastos septiembre'!$D$24:$D$173) -> 0 | F24: =SUMIF('Gastos octubre'!$F$24:$F$173,$B24,'Gastos octubre'!$C$24:$C$173)+SUMIF('Gastos octubre'!$F$24:$F$173,$B24,'Gastos octubre'!$D$24:$D$173) -> 0 | G24: =SUMIF('Gastos noviembre'!$F$24:$F$173,$B24,'Gastos noviembre'!$C$24:$C$173)+SUMIF('Gastos noviembre'!$F$24:$F$173,$B24,'Gastos noviembre'!$D$24:$D$173) -> 0 | H24: =SUMIF('Gastos diciembre'!$F$24:$F$173,$B24,'Gastos diciembre'!$C$24:$C$173)+SUMIF('Gastos diciembre'!$F$24:$F$173,$B24,'Gastos diciembre'!$D$24:$D$173) -> 0 | I24: =SUM(C24:H24) -> 170000
B25: ='Datos - Gastos'!A23 -> Rescates FCI | C25: =SUMIF('Gastos julio'!$F$24:$F$173,$B25,'Gastos julio'!$C$24:$C$173)+SUMIF('Gastos julio'!$F$24:$F$173,$B25,'Gastos julio'!$D$24:$D$173) -> 0 | D25: =SUMIF('Gastos agosto'!$F$24:$F$173,$B25,'Gastos agosto'!$C$24:$C$173)+SUMIF('Gastos agosto'!$F$24:$F$173,$B25,'Gastos agosto'!$D$24:$D$173) -> 0 | E25: =SUMIF('Gastos septiembre'!$F$24:$F$173,$B25,'Gastos septiembre'!$C$24:$C$173)+SUMIF('Gastos septiembre'!$F$24:$F$173,$B25,'Gastos septiembre'!$D$24:$D$173) -> 0 | F25: =SUMIF('Gastos octubre'!$F$24:$F$173,$B25,'Gastos octubre'!$C$24:$C$173)+SUMIF('Gastos octubre'!$F$24:$F$173,$B25,'Gastos octubre'!$D$24:$D$173) -> 0 | G25: =SUMIF('Gastos noviembre'!$F$24:$F$173,$B25,'Gastos noviembre'!$C$24:$C$173)+SUMIF('Gastos noviembre'!$F$24:$F$173,$B25,'Gastos noviembre'!$D$24:$D$173) -> 0 | H25: =SUMIF('Gastos diciembre'!$F$24:$F$173,$B25,'Gastos diciembre'!$C$24:$C$173)+SUMIF('Gastos diciembre'!$F$24:$F$173,$B25,'Gastos diciembre'!$D$24:$D$173) -> 0 | I25: =SUM(C25:H25) -> 0
B26: ='Datos - Gastos'!A24 -> Inversiones FCI | C26: =SUMIF('Gastos julio'!$F$24:$F$173,$B26,'Gastos julio'!$C$24:$C$173)+SUMIF('Gastos julio'!$F$24:$F$173,$B26,'Gastos julio'!$D$24:$D$173) -> 0 | D26: =SUMIF('Gastos agosto'!$F$24:$F$173,$B26,'Gastos agosto'!$C$24:$C$173)+SUMIF('Gastos agosto'!$F$24:$F$173,$B26,'Gastos agosto'!$D$24:$D$173) -> 0 | E26: =SUMIF('Gastos septiembre'!$F$24:$F$173,$B26,'Gastos septiembre'!$C$24:$C$173)+SUMIF('Gastos septiembre'!$F$24:$F$173,$B26,'Gastos septiembre'!$D$24:$D$173) -> 0 | F26: =SUMIF('Gastos octubre'!$F$24:$F$173,$B26,'Gastos octubre'!$C$24:$C$173)+SUMIF('Gastos octubre'!$F$24:$F$173,$B26,'Gastos octubre'!$D$24:$D$173) -> 0 | G26: =SUMIF('Gastos noviembre'!$F$24:$F$173,$B26,'Gastos noviembre'!$C$24:$C$173)+SUMIF('Gastos noviembre'!$F$24:$F$173,$B26,'Gastos noviembre'!$D$24:$D$173) -> 0 | H26: =SUMIF('Gastos diciembre'!$F$24:$F$173,$B26,'Gastos diciembre'!$C$24:$C$173)+SUMIF('Gastos diciembre'!$F$24:$F$173,$B26,'Gastos diciembre'!$D$24:$D$173) -> 0 | I26: =SUM(C26:H26) -> 0
B27: ='Datos - Gastos'!A25 -> Ahorros/inversiones | C27: =SUMIF('Gastos julio'!$F$24:$F$173,$B27,'Gastos julio'!$C$24:$C$173)+SUMIF('Gastos julio'!$F$24:$F$173,$B27,'Gastos julio'!$D$24:$D$173) -> 0 | D27: =SUMIF('Gastos agosto'!$F$24:$F$173,$B27,'Gastos agosto'!$C$24:$C$173)+SUMIF('Gastos agosto'!$F$24:$F$173,$B27,'Gastos agosto'!$D$24:$D$173) -> 0 | E27: =SUMIF('Gastos septiembre'!$F$24:$F$173,$B27,'Gastos septiembre'!$C$24:$C$173)+SUMIF('Gastos septiembre'!$F$24:$F$173,$B27,'Gastos septiembre'!$D$24:$D$173) -> 0 | F27: =SUMIF('Gastos octubre'!$F$24:$F$173,$B27,'Gastos octubre'!$C$24:$C$173)+SUMIF('Gastos octubre'!$F$24:$F$173,$B27,'Gastos octubre'!$D$24:$D$173) -> 0 | G27: =SUMIF('Gastos noviembre'!$F$24:$F$173,$B27,'Gastos noviembre'!$C$24:$C$173)+SUMIF('Gastos noviembre'!$F$24:$F$173,$B27,'Gastos noviembre'!$D$24:$D$173) -> 0 | H27: =SUMIF('Gastos diciembre'!$F$24:$F$173,$B27,'Gastos diciembre'!$C$24:$C$173)+SUMIF('Gastos diciembre'!$F$24:$F$173,$B27,'Gastos diciembre'!$D$24:$D$173) -> 0 | I27: =SUM(C27:H27) -> 0
B28: ='Datos - Gastos'!A26 -> Pago tarjetas de crédito | C28: =SUMIF('Gastos julio'!$F$24:$F$173,$B28,'Gastos julio'!$C$24:$C$173)+SUMIF('Gastos julio'!$F$24:$F$173,$B28,'Gastos julio'!$D$24:$D$173) -> -692782.22 | D28: =SUMIF('Gastos agosto'!$F$24:$F$173,$B28,'Gastos agosto'!$C$24:$C$173)+SUMIF('Gastos agosto'!$F$24:$F$173,$B28,'Gastos agosto'!$D$24:$D$173) -> -309765.61 | E28: =SUMIF('Gastos septiembre'!$F$24:$F$173,$B28,'Gastos septiembre'!$C$24:$C$173)+SUMIF('Gastos septiembre'!$F$24:$F$173,$B28,'Gastos septiembre'!$D$24:$D$173) -> -336416.98 | F28: =SUMIF('Gastos octubre'!$F$24:$F$173,$B28,'Gastos octubre'!$C$24:$C$173)+SUMIF('Gastos octubre'!$F$24:$F$173,$B28,'Gastos octubre'!$D$24:$D$173) -> 0 | G28: =SUMIF('Gastos noviembre'!$F$24:$F$173,$B28,'Gastos noviembre'!$C$24:$C$173)+SUMIF('Gastos noviembre'!$F$24:$F$173,$B28,'Gastos noviembre'!$D$24:$D$173) -> 0 | H28: =SUMIF('Gastos diciembre'!$F$24:$F$173,$B28,'Gastos diciembre'!$C$24:$C$173)+SUMIF('Gastos diciembre'!$F$24:$F$173,$B28,'Gastos diciembre'!$D$24:$D$173) -> 0 | I28: =SUM(C28:H28) -> -1338964.8
B29: ='Datos - Gastos'!A27 -> Pago monotributo | C29: =SUMIF('Gastos julio'!$F$24:$F$173,$B29,'Gastos julio'!$C$24:$C$173)+SUMIF('Gastos julio'!$F$24:$F$173,$B29,'Gastos julio'!$D$24:$D$173) -> -42386.74 | D29: =SUMIF('Gastos agosto'!$F$24:$F$173,$B29,'Gastos agosto'!$C$24:$C$173)+SUMIF('Gastos agosto'!$F$24:$F$173,$B29,'Gastos agosto'!$D$24:$D$173) -> -56379.08 | E29: =SUMIF('Gastos septiembre'!$F$24:$F$173,$B29,'Gastos septiembre'!$C$24:$C$173)+SUMIF('Gastos septiembre'!$F$24:$F$173,$B29,'Gastos septiembre'!$D$24:$D$173) -> -56379.08 | F29: =SUMIF('Gastos octubre'!$F$24:$F$173,$B29,'Gastos octubre'!$C$24:$C$173)+SUMIF('Gastos octubre'!$F$24:$F$173,$B29,'Gastos octubre'!$D$24:$D$173) -> 0 | G29: =SUMIF('Gastos noviembre'!$F$24:$F$173,$B29,'Gastos noviembre'!$C$24:$C$173)+SUMIF('Gastos noviembre'!$F$24:$F$173,$B29,'Gastos noviembre'!$D$24:$D$173) -> 0 | H29: =SUMIF('Gastos diciembre'!$F$24:$F$173,$B29,'Gastos diciembre'!$C$24:$C$173)+SUMIF('Gastos diciembre'!$F$24:$F$173,$B29,'Gastos diciembre'!$D$24:$D$173) -> 0 | I29: =SUM(C29:H29) -> -155144.9
B30: ='Datos - Gastos'!A28 -> Telas e insumos p costura | C30: =SUMIF('Gastos julio'!$F$24:$F$173,$B30,'Gastos julio'!$C$24:$C$173)+SUMIF('Gastos julio'!$F$24:$F$173,$B30,'Gastos julio'!$D$24:$D$173) -> -32980 | D30: =SUMIF('Gastos agosto'!$F$24:$F$173,$B30,'Gastos agosto'!$C$24:$C$173)+SUMIF('Gastos agosto'!$F$24:$F$173,$B30,'Gastos agosto'!$D$24:$D$173) -> -2400 | E30: =SUMIF('Gastos septiembre'!$F$24:$F$173,$B30,'Gastos septiembre'!$C$24:$C$173)+SUMIF('Gastos septiembre'!$F$24:$F$173,$B30,'Gastos septiembre'!$D$24:$D$173) -> 0 | F30: =SUMIF('Gastos octubre'!$F$24:$F$173,$B30,'Gastos octubre'!$C$24:$C$173)+SUMIF('Gastos octubre'!$F$24:$F$173,$B30,'Gastos octubre'!$D$24:$D$173) -> 0 | G30: =SUMIF('Gastos noviembre'!$F$24:$F$173,$B30,'Gastos noviembre'!$C$24:$C$173)+SUMIF('Gastos noviembre'!$F$24:$F$173,$B30,'Gastos noviembre'!$D$24:$D$173) -> 0 | H30: =SUMIF('Gastos diciembre'!$F$24:$F$173,$B30,'Gastos diciembre'!$C$24:$C$173)+SUMIF('Gastos diciembre'!$F$24:$F$173,$B30,'Gastos diciembre'!$D$24:$D$173) -> 0 | I30: =SUM(C30:H30) -> -35380
B31: ='Datos - Gastos'!A29 -> Transferencias Jo | C31: =SUMIF('Gastos julio'!$F$24:$F$173,$B31,'Gastos julio'!$C$24:$C$173)+SUMIF('Gastos julio'!$F$24:$F$173,$B31,'Gastos julio'!$D$24:$D$173) -> -25000 | D31: =SUMIF('Gastos agosto'!$F$24:$F$173,$B31,'Gastos agosto'!$C$24:$C$173)+SUMIF('Gastos agosto'!$F$24:$F$173,$B31,'Gastos agosto'!$D$24:$D$173) -> 15000 | E31: =SUMIF('Gastos septiembre'!$F$24:$F$173,$B31,'Gastos septiembre'!$C$24:$C$173)+SUMIF('Gastos septiembre'!$F$24:$F$173,$B31,'Gastos septiembre'!$D$24:$D$173) -> -20000 | F31: =SUMIF('Gastos octubre'!$F$24:$F$173,$B31,'Gastos octubre'!$C$24:$C$173)+SUMIF('Gastos octubre'!$F$24:$F$173,$B31,'Gastos octubre'!$D$24:$D$173) -> 0 | G31: =SUMIF('Gastos noviembre'!$F$24:$F$173,$B31,'Gastos noviembre'!$C$24:$C$173)+SUMIF('Gastos noviembre'!$F$24:$F$173,$B31,'Gastos noviembre'!$D$24:$D$173) -> 0 | H31: =SUMIF('Gastos diciembre'!$F$24:$F$173,$B31,'Gastos diciembre'!$C$24:$C$173)+SUMIF('Gastos diciembre'!$F$24:$F$173,$B31,'Gastos diciembre'!$D$24:$D$173) -> 0 | I31: =SUM(C31:H31) -> -30000
B32: Total | C32: =SUM(C5:C31) -> 1037148 | D32: =SUM(D5:D31) -> 1605611.1 | E32: =SUM(E5:E31) -> -1080110.6 | F32: =SUM(F5:F31) -> 0 | G32: =SUM(G5:G31) -> 0 | H32: =SUM(H5:H31) -> 0 | I32: =SUM(I5:I31) -> 1562648.5

Sheet Dashboard financiero
B2: Dashboard financiero 2026 - Análisis y simulación de escenarios
B4: Panel de control | F4: Honorarios / mes | H4: Gastos corrientes / mes | J4: Flujo disponible / mes
B5: Período base | C5: Promedio meses cargados | F5: =$C$13 -> 1758999.4 | H5: =-$C$14 -> 781794.94 | J5: =$C$15 -> 977204.44
B6: Meses con movimientos cargados | C6: {=MAX(1,SUMPRODUCT(('Gastos 2026'!C32:H32<>0)*1))} -> 3
B7: Variación de honorarios (%) | C7: 0 | F7: Tasa de ahorro potencial | H7: Ahorro efectivo / mes | J7: Flujo anualizado
B8: Reducción global de gastos (%) | C8: 0 | F8: =$C$17 -> 0.55554564 | H8: =$C$16 -> 1833333.3 | J8: =$C$19 -> 11726453
B9: Celdas amarillas = supuestos editables. Columna "Tipo" y "% reducción" (azul) también son editables.
B11: Resumen mensual - caso base vs. simulado
B12: Métrica | C12: Base | D12: Simulado | E12: Δ
B13: Ingresos por honorarios | C13: =SUMIF($C$23:$C$49,"Ingreso",$D$23:$D$49) -> 1758999.4 | D13: =SUMIF($C$23:$C$49,"Ingreso",$F$23:$F$49) -> 1758999.4 | E13: =D13-C13 -> 0
B14: Gastos corrientes | C14: =SUMIF($C$23:$C$49,"Gasto",$D$23:$D$49) -> -781794.94 | D14: =SUMIF($C$23:$C$49,"Gasto",$F$23:$F$49) -> -781794.94 | E14: =D14-C14 -> 0
B15: Flujo disponible (ingresos + gastos) | C15: =C13+C14 -> 977204.44 | D15: =D13+D14 -> 977204.44 | E15: =D15-C15 -> 0
B16: Ahorro/inversión efectivo (salidas reales) | C16: =IF($C$5="Promedio meses cargados",SUM($C$58:$H$58)/$C$6,INDEX($C$58:$H$58,MATCH($C$5,$C$54:$H$54,0))) -> 1833333.3 | D16: =C16+(D15-C15) -> 1833333.3 | E16: =D16-C16 -> 0
B17: Tasa de ahorro potencial (% honorarios) | C17: =IFERROR(C15/C13,"") -> 0.55554564 | D17: =IFERROR(D15/D13,"") -> 0.55554564 | E17: =IFERROR(D17-C17,"") -> 0
B18: Tasa de ahorro efectiva (% honorarios) | C18: =IFERROR(C16/C13,"") -> 1.0422592 | D18: =IFERROR(D16/D13,"") -> 1.0422592 | E18: =IFERROR(D18-C18,"") -> 0
B19: Flujo disponible anualizado (x12) | C19: =C15*12 -> 11726453 | D19: =D15*12 -> 11726453 | E19: =D19-C19 -> 0
B21: Simulador por concepto
B22: Concepto | C22: Tipo | D22: Neto mensual base | E22: % reducción | F22: Neto mensual simulado | G22: Impacto mensual | H22: Impacto anualizado | I22: % del gasto total | J22: Ranking gasto | K22: Aux magnitud | L22: Categoría
B23: ='Gastos 2026'!B5 -> Pago Claude/Cursor | C23: Gasto | D23: =IF($C$5="Promedio meses cargados",'Gastos 2026'!I5/$C$6,INDEX('Gastos 2026'!$C5:$H5,MATCH($C$5,'Gastos 2026'!$C$4:$H$4,0))) -> 25383.333 | E23: 0 | F23: =IF($C23="Ingreso",$D23*(1+$C$7),IF($C23="Gasto",$D23*(1-MIN(1,$E23+$C$8)),$D23)) -> 25383.333 | G23: =$F23-$D23 -> 0 | H23: =$G23*12 -> 0 | I23: =IFERROR(IF($C23="Gasto",$D23/SUMIF($C$23:$C$49,"Gasto",$D$23:$D$49),""),"") -> -0.032468019 | J23: =IFERROR(IF($C23="Gasto",RANK($K23,$K$23:$K$49),""),"") -> 19 | K23: =IF($C23="Gasto",-$D23,"") -> -25383.333 | L23: Servicios y suscripciones
B24: ='Gastos 2026'!B6 -> Salidas a cenar/almorzar | C24: Gasto | D24: =IF($C$5="Promedio meses cargados",'Gastos 2026'!I6/$C$6,INDEX('Gastos 2026'!$C6:$H6,MATCH($C$5,'Gastos 2026'!$C$4:$H$4,0))) -> -144786.91 | E24: 0 | F24: =IF($C24="Ingreso",$D24*(1+$C$7),IF($C24="Gasto",$D24*(1-MIN(1,$E24+$C$8)),$D24)) -> -144786.91 | G24: =$F24-$D24 -> 0 | H24: =$G24*12 -> 0 | I24: =IFERROR(IF($C24="Gasto",$D24/SUMIF($C$23:$C$49,"Gasto",$D$23:$D$49),""),"") -> 0.18519807 | J24: =IFERROR(IF($C24="Gasto",RANK($K24,$K$23:$K$49),""),"") -> 1 | K24: =IF($C24="Gasto",-$D24,"") -> 144786.91 | L24: Comidas y salidas
B25: ='Gastos 2026'!B7 -> Juntadas a cenar/almorzar | C25: Gasto | D25: =IF($C$5="Promedio meses cargados",'Gastos 2026'!I7/$C$6,INDEX('Gastos 2026'!$C7:$H7,MATCH($C$5,'Gastos 2026'!$C$4:$H$4,0))) -> -95250.157 | E25: 0 | F25: =IF($C25="Ingreso",$D25*(1+$C$7),IF($C25="Gasto",$D25*(1-MIN(1,$E25+$C$8)),$D25)) -> -95250.157 | G25: =$F25-$D25 -> 0 | H25: =$G25*12 -> 0 | I25: =IFERROR(IF($C25="Gasto",$D25/SUMIF($C$23:$C$49,"Gasto",$D$23:$D$49),""),"") -> 0.12183522 | J25: =IFERROR(IF($C25="Gasto",RANK($K25,$K$23:$K$49),""),"") -> 2 | K25: =IF($C25="Gasto",-$D25,"") -> 95250.157 | L25: Comidas y salidas
B26: ='Gastos 2026'!B8 -> Salidas a desyunar/merendar | C26: Gasto | D26: =IF($C$5="Promedio meses cargados",'Gastos 2026'!I8/$C$6,INDEX('Gastos 2026'!$C8:$H8,MATCH($C$5,'Gastos 2026'!$C$4:$H$4,0))) -> -63766.667 | E26: 0 | F26: =IF($C26="Ingreso",$D26*(1+$C$7),IF($C26="Gasto",$D26*(1-MIN(1,$E26+$C$8)),$D26)) -> -63766.667 | G26: =$F26-$D26 -> 0 | H26: =$G26*12 -> 0 | I26: =IFERROR(IF($C26="Gasto",$D26/SUMIF($C$23:$C$49,"Gasto",$D$23:$D$49),""),"") -> 0.08156444 | J26: =IFERROR(IF($C26="Gasto",RANK($K26,$K$23:$K$49),""),"") -> 7 | K26: =IF($C26="Gasto",-$D26,"") -> 63766.667 | L26: Comidas y salidas
B27: ='Gastos 2026'!B9 -> Juntadas a desayunar/merendar | C27: Gasto | D27: =IF($C$5="Promedio meses cargados",'Gastos 2026'!I9/$C$6,INDEX('Gastos 2026'!$C9:$H9,MATCH($C$5,'Gastos 2026'!$C$4:$H$4,0))) -> 0 | E27: 0 | F27: =IF($C27="Ingreso",$D27*(1+$C$7),IF($C27="Gasto",$D27*(1-MIN(1,$E27+$C$8)),$D27)) -> 0 | G27: =$F27-$D27 -> 0 | H27: =$G27*12 -> 0 | I27: =IFERROR(IF($C27="Gasto",$D27/SUMIF($C$23:$C$49,"Gasto",$D$23:$D$49),""),"") -> 0 | J27: =IFERROR(IF($C27="Gasto",RANK($K27,$K$23:$K$49),""),"") -> 16 | K27: =IF($C27="Gasto",-$D27,"") -> 0 | L27: Comidas y salidas
B28: ='Gastos 2026'!B10 -> Salidas a tomar algo | C28: Gasto | D28: =IF($C$5="Promedio meses cargados",'Gastos 2026'!I10/$C$6,INDEX('Gastos 2026'!$C10:$H10,MATCH($C$5,'Gastos 2026'!$C$4:$H$4,0))) -> -60076.667 | E28: 0 | F28: =IF($C28="Ingreso",$D28*(1+$C$7),IF($C28="Gasto",$D28*(1-MIN(1,$E28+$C$8)),$D28)) -> -60076.667 | G28: =$F28-$D28 -> 0 | H28: =$G28*12 -> 0 | I28: =IFERROR(IF($C28="Gasto",$D28/SUMIF($C$23:$C$49,"Gasto",$D$23:$D$49),""),"") -> 0.076844532 | J28: =IFERROR(IF($C28="Gasto",RANK($K28,$K$23:$K$49),""),"") -> 8 | K28: =IF($C28="Gasto",-$D28,"") -> 60076.667 | L28: Comidas y salidas
B29: ='Gastos 2026'!B11 -> Fiestas | C29: Gasto | D29: =IF($C$5="Promedio meses cargados",'Gastos 2026'!I11/$C$6,INDEX('Gastos 2026'!$C11:$H11,MATCH($C$5,'Gastos 2026'!$C$4:$H$4,0))) -> -8200 | E29: 0 | F29: =IF($C29="Ingreso",$D29*(1+$C$7),IF($C29="Gasto",$D29*(1-MIN(1,$E29+$C$8)),$D29)) -> -8200 | G29: =$F29-$D29 -> 0 | H29: =$G29*12 -> 0 | I29: =IFERROR(IF($C29="Gasto",$D29/SUMIF($C$23:$C$49,"Gasto",$D$23:$D$49),""),"") -> 0.010488684 | J29: =IFERROR(IF($C29="Gasto",RANK($K29,$K$23:$K$49),""),"") -> 14 | K29: =IF($C29="Gasto",-$D29,"") -> 8200 | L29: Regalos y eventos
B30: ='Gastos 2026'!B12 -> Auto | C30: Gasto | D30: =IF($C$5="Promedio meses cargados",'Gastos 2026'!I12/$C$6,INDEX('Gastos 2026'!$C12:$H12,MATCH($C$5,'Gastos 2026'!$C$4:$H$4,0))) -> -85866.667 | E30: 0 | F30: =IF($C30="Ingreso",$D30*(1+$C$7),IF($C30="Gasto",$D30*(1-MIN(1,$E30+$C$8)),$D30)) -> -85866.667 | G30: =$F30-$D30 -> 0 | H30: =$G30*12 -> 0 | I30: =IFERROR(IF($C30="Gasto",$D30/SUMIF($C$23:$C$49,"Gasto",$D$23:$D$49),""),"") -> 0.10983272 | J30: =IFERROR(IF($C30="Gasto",RANK($K30,$K$23:$K$49),""),"") -> 3 | K30: =IF($C30="Gasto",-$D30,"") -> 85866.667 | L30: Transporte
B31: ='Gastos 2026'!B13 -> Celular | C31: Gasto | D31: =IF($C$5="Promedio meses cargados",'Gastos 2026'!I13/$C$6,INDEX('Gastos 2026'!$C13:$H13,MATCH($C$5,'Gastos 2026'!$C$4:$H$4,0))) -> -2333.3333 | E31: 0 | F31: =IF($C31="Ingreso",$D31*(1+$C$7),IF($C31="Gasto",$D31*(1-MIN(1,$E31+$C$8)),$D31)) -> -2333.3333 | G31: =$F31-$D31 -> 0 | H31: =$G31*12 -> 0 | I31: =IFERROR(IF($C31="Gasto",$D31/SUMIF($C$23:$C$49,"Gasto",$D$23:$D$49),""),"") -> 0.0029845848 | J31: =IFERROR(IF($C31="Gasto",RANK($K31,$K$23:$K$49),""),"") -> 15 | K31: =IF($C31="Gasto",-$D31,"") -> 2333.3333 | L31: Servicios y suscripciones
B32: ='Gastos 2026'!B14 -> Farmacia/Cosméticos | C32: Gasto | D32: =IF($C$5="Promedio meses cargados",'Gastos 2026'!I14/$C$6,INDEX('Gastos 2026'!$C14:$H14,MATCH($C$5,'Gastos 2026'!$C$4:$H$4,0))) -> -20699.707 | E32: 0 | F32: =IF($C32="Ingreso",$D32*(1+$C$7),IF($C32="Gasto",$D32*(1-MIN(1,$E32+$C$8)),$D32)) -> -20699.707 | G32: =$F32-$D32 -> 0 | H32: =$G32*12 -> 0 | I32: =IFERROR(IF($C32="Gasto",$D32/SUMIF($C$23:$C$49,"Gasto",$D$23:$D$49),""),"") -> 0.026477156 | J32: =IFERROR(IF($C32="Gasto",RANK($K32,$K$23:$K$49),""),"") -> 11 | K32: =IF($C32="Gasto",-$D32,"") -> 20699.707 | L32: Salud y bienestar
B33: ='Gastos 2026'!B15 -> Ropa | C33: Gasto | D33: =IF($C$5="Promedio meses cargados",'Gastos 2026'!I15/$C$6,INDEX('Gastos 2026'!$C15:$H15,MATCH($C$5,'Gastos 2026'!$C$4:$H$4,0))) -> 0 | E33: 0 | F33: =IF($C33="Ingreso",$D33*(1+$C$7),IF($C33="Gasto",$D33*(1-MIN(1,$E33+$C$8)),$D33)) -> 0 | G33: =$F33-$D33 -> 0 | H33: =$G33*12 -> 0 | I33: =IFERROR(IF($C33="Gasto",$D33/SUMIF($C$23:$C$49,"Gasto",$D$23:$D$49),""),"") -> 0 | J33: =IFERROR(IF($C33="Gasto",RANK($K33,$K$23:$K$49),""),"") -> 16 | K33: =IF($C33="Gasto",-$D33,"") -> 0 | L33: Ropa y personal
B34: ='Gastos 2026'!B16 -> Súper | C34: Gasto | D34: =IF($C$5="Promedio meses cargados",'Gastos 2026'!I16/$C$6,INDEX('Gastos 2026'!$C16:$H16,MATCH($C$5,'Gastos 2026'!$C$4:$H$4,0))) -> -11349.333 | E34: 0 | F34: =IF($C34="Ingreso",$D34*(1+$C$7),IF($C34="Gasto",$D34*(1-MIN(1,$E34+$C$8)),$D34)) -> -11349.333 | G34: =$F34-$D34 -> 0 | H34: =$G34*12 -> 0 | I34: =IFERROR(IF($C34="Gasto",$D34/SUMIF($C$23:$C$49,"Gasto",$D$23:$D$49),""),"") -> 0.014517021 | J34: =IFERROR(IF($C34="Gasto",RANK($K34,$K$23:$K$49),""),"") -> 13 | K34: =IF($C34="Gasto",-$D34,"") -> 11349.333 | L34: Hogar y súper
... B49: ='Gastos 2026'!B31 -> Transferencias Jo | C49: Neutro | D49: =IF($C$5="Promedio meses cargados",'Gastos 2026'!I31/$C$6,INDEX('Gastos 2026'!$C31:$H31,MATCH($C$5,'Gastos 2026'!$C$4:$H$4,0))) -> -10000 | E49: 0 | F49: =IF($C49="Ingreso",$D49*(1+$C$7),IF($C49="Gasto",$D49*(1-MIN(1,$E49+$C$8)),$D49)) -> -10000 | G49: =$F49-$D49 -> 0 | H49: =$G49*12 -> 0 | I49: =IFERROR(IF($C49="Gasto",$D49/SUMIF($C$23:$C$49,"Gasto",$D$23:$D$49),""),"") | J49: =IFERROR(IF($C49="Gasto",RANK($K49,$K$23:$K$49),""),"") | K49: =IF($C49="Gasto",-$D49,"") | L49: Neutro
B50: Total | D50: =SUM(D23:D49) -> 520882.83 | F50: =SUM(F23:F49) -> 520882.83 | G50: =SUM(G23:G49) -> 0 | H50: =SUM(H23:H49) -> 0
B53: Evolución mensual
B54: Métrica | C54: ='Gastos 2026'!C4 -> julio | D54: ='Gastos 2026'!D4 -> agosto | E54: ='Gastos 2026'!E4 -> septiembre | F54: ='Gastos 2026'!F4 -> octubre | G54: ='Gastos 2026'!G4 -> noviembre | H54: ='Gastos 2026'!H4 -> diciembre
B55: Ingresos por honorarios | C55: =SUMIF($C$23:$C$49,"Ingreso",'Gastos 2026'!C$5:C$31) -> 2388047 | D55: =SUMIF($C$23:$C$49,"Ingreso",'Gastos 2026'!D$5:D$31) -> 2687951.1 | E55: =SUMIF($C$23:$C$49,"Ingreso",'Gastos 2026'!E$5:E$31) -> 201000 | F55: =SUMIF($C$23:$C$49,"Ingreso",'Gastos 2026'!F$5:F$31) -> 0 | G55: =SUMIF($C$23:$C$49,"Ingreso",'Gastos 2026'!G$5:G$31) -> 0 | H55: =SUMIF($C$23:$C$49,"Ingreso",'Gastos 2026'!H$5:H$31) -> 0
B56: Gastos corrientes | C56: =-SUMIF($C$23:$C$49,"Gasto",'Gastos 2026'!C$5:C$31) -> 633116.83 | D56: =-SUMIF($C$23:$C$49,"Gasto",'Gastos 2026'!D$5:D$31) -> 787574.4 | E56: =-SUMIF($C$23:$C$49,"Gasto",'Gastos 2026'!E$5:E$31) -> 924693.6 | F56: =-SUMIF($C$23:$C$49,"Gasto",'Gastos 2026'!F$5:F$31) -> 0 | G56: =-SUMIF($C$23:$C$49,"Gasto",'Gastos 2026'!G$5:G$31) -> 0 | H56: =-SUMIF($C$23:$C$49,"Gasto",'Gastos 2026'!H$5:H$31) -> 0
B57: Flujo disponible | C57: =C55-C56 -> 1754930.2 | D57: =D55-D56 -> 1900376.7 | E57: =E55-E56 -> -723693.6 | F57: =F55-F56 -> 0 | G57: =G55-G56 -> 0 | H57: =H55-H56 -> 0
B58: Ahorro/inversión efectivo (salidas reales) | C58: =-(SUMIF('Gastos julio'!$F$24:$F$173,"Inversiones FCI",'Gastos julio'!$D$24:$D$173)+SUMIF('Gastos julio'!$F$24:$F$173,"Ahorros/inversiones",'Gastos julio'!$D$24:$D$173)) -> 1200000 | D58: =-(SUMIF('Gastos agosto'!$F$24:$F$173,"Inversiones FCI",'Gastos agosto'!$D$24:$D$173)+SUMIF('Gastos agosto'!$F$24:$F$173,"Ahorros/inversiones",'Gastos agosto'!$D$24:$D$173)) -> 2300000 | E58: =-(SUMIF('Gastos septiembre'!$F$24:$F$173,"Inversiones FCI",'Gastos septiembre'!$D$24:$D$173)+SUMIF('Gastos septiembre'!$F$24:$F$173,"Ahorros/inversiones",'Gastos septiembre'!$D$24:$D$173)) -> 2000000 | F58: =-(SUMIF('Gastos octubre'!$F$24:$F$173,"Inversiones FCI",'Gastos octubre'!$D$24:$D$173)+SUMIF('Gastos octubre'!$F$24:$F$173,"Ahorros/inversiones",'Gastos octubre'!$D$24:$D$173)) -> 0 | G58: =-(SUMIF('Gastos noviembre'!$F$24:$F$173,"Inversiones FCI",'Gastos noviembre'!$D$24:$D$173)+SUMIF('Gastos noviembre'!$F$24:$F$173,"Ahorros/inversiones",'Gastos noviembre'!$D$24:$D$173)) -> 0 | H58: =-(SUMIF('Gastos diciembre'!$F$24:$F$173,"Inversiones FCI",'Gastos diciembre'!$D$24:$D$173)+SUMIF('Gastos diciembre'!$F$24:$F$173,"Ahorros/inversiones",'Gastos diciembre'!$D$24:$D$173)) -> 0
B59: Tasa de ahorro potencial | C59: =IFERROR(IF(C55=0,"",C57/C55),"") -> 0.73488092 | D59: =IFERROR(IF(D55=0,"",D57/D55),"") -> 0.70699825 | E59: =IFERROR(IF(E55=0,"",E57/E55),"") -> -3.6004657 | F59: =IFERROR(IF(F55=0,"",F57/F55),"") | G59: =IFERROR(IF(G55=0,"",G57/G55),"") | H59: =IFERROR(IF(H55=0,"",H57/H55),"")
B62: Sensibilidad: tasa de ahorro potencial
B63: Gastos con ajustes individuales (sin reducción global) | C63: =SUMIF($C$23:$C$49,"Gasto",$F$23:$F$49)+$C$8*$C$14 -> -781794.94
B65: Reducción gastos ↓ / Var. honorarios → | C65: =$C$7-0.1 -> -0.1 | D65: =$C$7-0.05 -> -0.05 | E65: =$C$7 -> 0 | F65: =$C$7+0.05 -> 0.05 | G65: =$C$7+0.1 -> 0.1
B66: =$C$8-0.1 -> -0.1 | C66: =IFERROR(($C$13*(1+C$65)+($C$63-$B66*$C$14))/($C$13*(1+C$65)),"") -> 0.456778 | D66: =IFERROR(($C$13*(1+D$65)+($C$63-$B66*$C$14))/($C$13*(1+D$65)),"") -> 0.48536864 | E66: =IFERROR(($C$13*(1+E$65)+($C$63-$B66*$C$14))/($C$13*(1+E$65)),"") -> 0.5111002 | F66: =IFERROR(($C$13*(1+F$65)+($C$63-$B66*$C$14))/($C$13*(1+F$65)),"") -> 0.53438115 | G66: =IFERROR(($C$13*(1+G$65)+($C$63-$B66*$C$14))/($C$13*(1+G$65)),"") -> 0.55554564
B67: =$C$8-0.05 -> -0.05 | C67: =IFERROR(($C$13*(1+C$65)+($C$63-$B67*$C$14))/($C$13*(1+C$65)),"") -> 0.48146991 | D67: =IFERROR(($C$13*(1+D$65)+($C$63-$B67*$C$14))/($C$13*(1+D$65)),"") -> 0.50876097 | E67: =IFERROR(($C$13*(1+E$65)+($C$63-$B67*$C$14))/($C$13*(1+E$65)),"") -> 0.53332292 | F67: =IFERROR(($C$13*(1+F$65)+($C$63-$B67*$C$14))/($C$13*(1+F$65)),"") -> 0.55554564 | G67: =IFERROR(($C$13*(1+G$65)+($C$63-$B67*$C$14))/($C$13*(1+G$65)),"") -> 0.57574811
B68: =$C$8 -> 0 | C68: =IFERROR(($C$13*(1+C$65)+($C$63-$B68*$C$14))/($C$13*(1+C$65)),"") -> 0.50616182 | D68: =IFERROR(($C$13*(1+D$65)+($C$63-$B68*$C$14))/($C$13*(1+D$65)),"") -> 0.53215331 | E68: =IFERROR(($C$13*(1+E$65)+($C$63-$B68*$C$14))/($C$13*(1+E$65)),"") -> 0.55554564 | F68: =IFERROR(($C$13*(1+F$65)+($C$63-$B68*$C$14))/($C$13*(1+F$65)),"") -> 0.57671013 | G68: =IFERROR(($C$13*(1+G$65)+($C$63-$B68*$C$14))/($C$13*(1+G$65)),"") -> 0.59595058
B69: =$C$8+0.05 -> 0.05 | C69: =IFERROR(($C$13*(1+C$65)+($C$63-$B69*$C$14))/($C$13*(1+C$65)),"") -> 0.53085373 | D69: =IFERROR(($C$13*(1+D$65)+($C$63-$B69*$C$14))/($C$13*(1+D$65)),"") -> 0.55554564 | E69: =IFERROR(($C$13*(1+E$65)+($C$63-$B69*$C$14))/($C$13*(1+E$65)),"") -> 0.57776836 | F69: =IFERROR(($C$13*(1+F$65)+($C$63-$B69*$C$14))/($C$13*(1+F$65)),"") -> 0.59787463 | G69: =IFERROR(($C$13*(1+G$65)+($C$63-$B69*$C$14))/($C$13*(1+G$65)),"") -> 0.61615305
B70: =$C$8+0.1 -> 0.1 | C70: =IFERROR(($C$13*(1+C$65)+($C$63-$B70*$C$14))/($C$13*(1+C$65)),"") -> 0.55554564 | D70: =IFERROR(($C$13*(1+D$65)+($C$63-$B70*$C$14))/($C$13*(1+D$65)),"") -> 0.57893797 | E70: =IFERROR(($C$13*(1+E$65)+($C$63-$B70*$C$14))/($C$13*(1+E$65)),"") -> 0.59999108 | F70: =IFERROR(($C$13*(1+F$65)+($C$63-$B70*$C$14))/($C$13*(1+F$65)),"") -> 0.61903912 | G70: =IFERROR(($C$13*(1+G$65)+($C$63-$B70*$C$14))/($C$13*(1+G$65)),"") -> 0.63635552
B72: Top gastos por concepto (base mensual)
B73: Concepto | C73: Gasto mensual
B74: =IFERROR(INDEX($B$23:$B$49,MATCH(LARGE($K$23:$K$49,ROWS($B$74:B74)),$K$23:$K$49,0)),"") -> Salidas a cenar/almorzar | C74: =IFERROR(LARGE($K$23:$K$49,ROWS($C$74:C74)),"") -> 144786.91
B75: =IFERROR(INDEX($B$23:$B$49,MATCH(LARGE($K$23:$K$49,ROWS($B$74:B75)),$K$23:$K$49,0)),"") -> Juntadas a cenar/almorzar | C75: =IFERROR(LARGE($K$23:$K$49,ROWS($C$74:C75)),"") -> 95250.157
B76: =IFERROR(INDEX($B$23:$B$49,MATCH(LARGE($K$23:$K$49,ROWS($B$74:B76)),$K$23:$K$49,0)),"") -> Auto | C76: =IFERROR(LARGE($K$23:$K$49,ROWS($C$74:C76)),"") -> 85866.667
B77: =IFERROR(INDEX($B$23:$B$49,MATCH(LARGE($K$23:$K$49,ROWS($B$74:B77)),$K$23:$K$49,0)),"") -> Entradas fiestas/conciertos/otros eventos | C77: =IFERROR(LARGE($K$23:$K$49,ROWS($C$74:C77)),"") -> 78030
B78: =IFERROR(INDEX($B$23:$B$49,MATCH(LARGE($K$23:$K$49,ROWS($B$74:B78)),$K$23:$K$49,0)),"") -> Gimnasio | C78: =IFERROR(LARGE($K$23:$K$49,ROWS($C$74:C78)),"") -> 75333.333
B79: =IFERROR(INDEX($B$23:$B$49,MATCH(LARGE($K$23:$K$49,ROWS($B$74:B79)),$K$23:$K$49,0)),"") -> Psicóloga | C79: =IFERROR(LARGE($K$23:$K$49,ROWS($C$74:C79)),"") -> 68274.667
B80: =IFERROR(INDEX($B$23:$B$49,MATCH(LARGE($K$23:$K$49,ROWS($B$74:B80)),$K$23:$K$49,0)),"") -> Salidas a desyunar/merendar | C80: =IFERROR(LARGE($K$23:$K$49,ROWS($C$74:C80)),"") -> 63766.667
B81: =IFERROR(INDEX($B$23:$B$49,MATCH(LARGE($K$23:$K$49,ROWS($B$74:B81)),$K$23:$K$49,0)),"") -> Salidas a tomar algo | C81: =IFERROR(LARGE($K$23:$K$49,ROWS($C$74:C81)),"") -> 60076.667
B82: =IFERROR(INDEX($B$23:$B$49,MATCH(LARGE($K$23:$K$49,ROWS($B$74:B82)),$K$23:$K$49,0)),"") -> Pago monotributo | C82: =IFERROR(LARGE($K$23:$K$49,ROWS($C$74:C82)),"") -> 51714.967
B83: =IFERROR(INDEX($B$23:$B$49,MATCH(LARGE($K$23:$K$49,ROWS($B$74:B83)),$K$23:$K$49,0)),"") -> Delivery | C83: =IFERROR(LARGE($K$23:$K$49,ROWS($C$74:C83)),"") -> 29852.533
B85: Datos auxiliares para gráficos (agrupados)
B86: Datos para gráficos
B88: Categoría | C88: Gasto mensual base | D88: Gasto mensual simulado
B89: Comidas y salidas | C89: =-SUMIFS($D$23:$D$49,$L$23:$L$49,$B89,$C$23:$C$49,"Gasto") -> 393732.94 | D89: =-SUMIFS($F$23:$F$49,$L$23:$L$49,$B89,$C$23:$C$49,"Gasto") -> 393732.94
B90: Hogar y súper | C90: =-SUMIFS($D$23:$D$49,$L$23:$L$49,$B90,$C$23:$C$49,"Gasto") -> 11349.333 | D90: =-SUMIFS($F$23:$F$49,$L$23:$L$49,$B90,$C$23:$C$49,"Gasto") -> 11349.333
B91: Transporte | C91: =-SUMIFS($D$23:$D$49,$L$23:$L$49,$B91,$C$23:$C$49,"Gasto") -> 85866.667 | D91: =-SUMIFS($F$23:$F$49,$L$23:$L$49,$B91,$C$23:$C$49,"Gasto") -> 85866.667
B92: Salud y bienestar | C92: =-SUMIFS($D$23:$D$49,$L$23:$L$49,$B92,$C$23:$C$49,"Gasto") -> 164307.71 | D92: =-SUMIFS($F$23:$F$49,$L$23:$L$49,$B92,$C$23:$C$49,"Gasto") -> 164307.71
B93: Servicios y suscripciones | C93: =-SUMIFS($D$23:$D$49,$L$23:$L$49,$B93,$C$23:$C$49,"Gasto") -> -23050 | D93: =-SUMIFS($F$23:$F$49,$L$23:$L$49,$B93,$C$23:$C$49,"Gasto") -> -23050
B94: Ropa y personal | C94: =-SUMIFS($D$23:$D$49,$L$23:$L$49,$B94,$C$23:$C$49,"Gasto") -> 11793.333 | D94: =-SUMIFS($F$23:$F$49,$L$23:$L$49,$B94,$C$23:$C$49,"Gasto") -> 11793.333
B95: Regalos y eventos | C95: =-SUMIFS($D$23:$D$49,$L$23:$L$49,$B95,$C$23:$C$49,"Gasto") -> 86080 | D95: =-SUMIFS($F$23:$F$49,$L$23:$L$49,$B95,$C$23:$C$49,"Gasto") -> 86080
B96: Impuestos | C96: =-SUMIFS($D$23:$D$49,$L$23:$L$49,$B96,$C$23:$C$49,"Gasto") -> 51714.967 | D96: =-SUMIFS($F$23:$F$49,$L$23:$L$49,$B96,$C$23:$C$49,"Gasto") -> 51714.967
B98: Métrica | C98: =C$54 -> julio | D98: =D$54 -> agosto | E98: =E$54 -> septiembre | F98: =F$54 -> octubre | G98: =G$54 -> noviembre | H98: =H$54 -> diciembre
B99: Tasa de ahorro potencial | C99: =IF(C$55=0,NA(),C$59) -> 0.73488092 | D99: =IF(D$55=0,NA(),D$59) -> 0.70699825 | E99: =IF(E$55=0,NA(),E$59) -> -3.6004657 | F99: =IF(F$55=0,NA(),F$59) -> #N/A | G99: =IF(G$55=0,NA(),G$59) -> #N/A | H99: =IF(H$55=0,NA(),H$59) -> #N/A
B101: Cascada | C101: Monto
B102: Honorarios | C102: =$C$13 -> 1758999.4
B103: =$B89 -> Comidas y salidas | C103: =-$C89 -> -393732.94
B104: =$B90 -> Hogar y súper | C104: =-$C90 -> -11349.333
B105: =$B91 -> Transporte | C105: =-$C91 -> -85866.667
B106: =$B92 -> Salud y bienestar | C106: =-$C92 -> -164307.71
B107: =$B93 -> Servicios y suscripciones | C107: =-$C93 -> 23050
B108: =$B94 -> Ropa y personal | C108: =-$C94 -> -11793.333
B109: =$B95 -> Regalos y eventos | C109: =-$C95 -> -86080
B110: =$B96 -> Impuestos | C110: =-$C96 -> -51714.967
B111: Flujo disponible | C111: =$C$15 -> 977204.44

Sheet Análisis semanal julio
A1: Gastos por semana y concepto — Julio 2026
A2: Importes en ARS, mostrados en positivo. Fuente: 'Gastos julio'!D24:D99 (gastos), F (concepto), H (fecha).
A4: Concepto | B4: Sem 1 | C4: Sem 2 | D4: Sem 3 | E4: Sem 4 | F4: Sem 5 | G4: Total mes
A5: Desde | B5: 46204 | C5: 46209 | D5: 46216 | E5: 46223 | F5: 46230
A6: Hasta | B6: 46208 | C6: 46215 | D6: 46222 | E6: 46229 | F6: 46234
A7: Delivery | B7: =-SUMIFS('Gastos julio'!$D$24:$D$99,'Gastos julio'!$F$24:$F$99,$A7,'Gastos julio'!$H$24:$H$99,">="&B$5,'Gastos julio'!$H$24:$H$99,"<="&B$6) -> 50559 | C7: =-SUMIFS('Gastos julio'!$D$24:$D$99,'Gastos julio'!$F$24:$F$99,$A7,'Gastos julio'!$H$24:$H$99,">="&C$5,'Gastos julio'!$H$24:$H$99,"<="&C$6) -> 140615 | D7: =-SUMIFS('Gastos julio'!$D$24:$D$99,'Gastos julio'!$F$24:$F$99,$A7,'Gastos julio'!$H$24:$H$99,">="&D$5,'Gastos julio'!$H$24:$H$99,"<="&D$6) -> 6883.6 | E7: =-SUMIFS('Gastos julio'!$D$24:$D$99,'Gastos julio'!$F$24:$F$99,$A7,'Gastos julio'!$H$24:$H$99,">="&E$5,'Gastos julio'!$H$24:$H$99,"<="&E$6) -> 26500 | F7: =-SUMIFS('Gastos julio'!$D$24:$D$99,'Gastos julio'!$F$24:$F$99,$A7,'Gastos julio'!$H$24:$H$99,">="&F$5,'Gastos julio'!$H$24:$H$99,"<="&F$6) -> 0 | G7: =SUM(B7:F7) -> 224557.6
A8: Salidas a cenar/almorzar | B8: =-SUMIFS('Gastos julio'!$D$24:$D$99,'Gastos julio'!$F$24:$F$99,$A8,'Gastos julio'!$H$24:$H$99,">="&B$5,'Gastos julio'!$H$24:$H$99,"<="&B$6) -> 0 | C8: =-SUMIFS('Gastos julio'!$D$24:$D$99,'Gastos julio'!$F$24:$F$99,$A8,'Gastos julio'!$H$24:$H$99,">="&C$5,'Gastos julio'!$H$24:$H$99,"<="&C$6) -> 0 | D8: =-SUMIFS('Gastos julio'!$D$24:$D$99,'Gastos julio'!$F$24:$F$99,$A8,'Gastos julio'!$H$24:$H$99,">="&D$5,'Gastos julio'!$H$24:$H$99,"<="&D$6) -> 132280 | E8: =-SUMIFS('Gastos julio'!$D$24:$D$99,'Gastos julio'!$F$24:$F$99,$A8,'Gastos julio'!$H$24:$H$99,">="&E$5,'Gastos julio'!$H$24:$H$99,"<="&E$6) -> 34100 | F8: =-SUMIFS('Gastos julio'!$D$24:$D$99,'Gastos julio'!$F$24:$F$99,$A8,'Gastos julio'!$H$24:$H$99,">="&F$5,'Gastos julio'!$H$24:$H$99,"<="&F$6) -> 13600 | G8: =SUM(B8:F8) -> 179980
A9: Salidas a desyunar/merendar | B9: =-SUMIFS('Gastos julio'!$D$24:$D$99,'Gastos julio'!$F$24:$F$99,$A9,'Gastos julio'!$H$24:$H$99,">="&B$5,'Gastos julio'!$H$24:$H$99,"<="&B$6) -> 71300 | C9: =-SUMIFS('Gastos julio'!$D$24:$D$99,'Gastos julio'!$F$24:$F$99,$A9,'Gastos julio'!$H$24:$H$99,">="&C$5,'Gastos julio'!$H$24:$H$99,"<="&C$6) -> 0 | D9: =-SUMIFS('Gastos julio'!$D$24:$D$99,'Gastos julio'!$F$24:$F$99,$A9,'Gastos julio'!$H$24:$H$99,">="&D$5,'Gastos julio'!$H$24:$H$99,"<="&D$6) -> 43400 | E9: =-SUMIFS('Gastos julio'!$D$24:$D$99,'Gastos julio'!$F$24:$F$99,$A9,'Gastos julio'!$H$24:$H$99,">="&E$5,'Gastos julio'!$H$24:$H$99,"<="&E$6) -> 30300 | F9: =-SUMIFS('Gastos julio'!$D$24:$D$99,'Gastos julio'!$F$24:$F$99,$A9,'Gastos julio'!$H$24:$H$99,">="&F$5,'Gastos julio'!$H$24:$H$99,"<="&F$6) -> 0 | G9: =SUM(B9:F9) -> 145000
A10: Salidas a tomar algo | B10: =-SUMIFS('Gastos julio'!$D$24:$D$99,'Gastos julio'!$F$24:$F$99,$A10,'Gastos julio'!$H$24:$H$99,">="&B$5,'Gastos julio'!$H$24:$H$99,"<="&B$6) -> 0 | C10: =-SUMIFS('Gastos julio'!$D$24:$D$99,'Gastos julio'!$F$24:$F$99,$A10,'Gastos julio'!$H$24:$H$99,">="&C$5,'Gastos julio'!$H$24:$H$99,"<="&C$6) -> 0 | D10: =-SUMIFS('Gastos julio'!$D$24:$D$99,'Gastos julio'!$F$24:$F$99,$A10,'Gastos julio'!$H$24:$H$99,">="&D$5,'Gastos julio'!$H$24:$H$99,"<="&D$6) -> 0 | E10: =-SUMIFS('Gastos julio'!$D$24:$D$99,'Gastos julio'!$F$24:$F$99,$A10,'Gastos julio'!$H$24:$H$99,">="&E$5,'Gastos julio'!$H$24:$H$99,"<="&E$6) -> 65000 | F10: =-SUMIFS('Gastos julio'!$D$24:$D$99,'Gastos julio'!$F$24:$F$99,$A10,'Gastos julio'!$H$24:$H$99,">="&F$5,'Gastos julio'!$H$24:$H$99,"<="&F$6) -> 0 | G10: =SUM(B10:F10) -> 65000
A11: Auto | B11: =-SUMIFS('Gastos julio'!$D$24:$D$99,'Gastos julio'!$F$24:$F$99,$A11,'Gastos julio'!$H$24:$H$99,">="&B$5,'Gastos julio'!$H$24:$H$99,"<="&B$6) -> 23600 | C11: =-SUMIFS('Gastos julio'!$D$24:$D$99,'Gastos julio'!$F$24:$F$99,$A11,'Gastos julio'!$H$24:$H$99,">="&C$5,'Gastos julio'!$H$24:$H$99,"<="&C$6) -> 0 | D11: =-SUMIFS('Gastos julio'!$D$24:$D$99,'Gastos julio'!$F$24:$F$99,$A11,'Gastos julio'!$H$24:$H$99,">="&D$5,'Gastos julio'!$H$24:$H$99,"<="&D$6) -> 2000 | E11: =-SUMIFS('Gastos julio'!$D$24:$D$99,'Gastos julio'!$F$24:$F$99,$A11,'Gastos julio'!$H$24:$H$99,">="&E$5,'Gastos julio'!$H$24:$H$99,"<="&E$6) -> 4000 | F11: =-SUMIFS('Gastos julio'!$D$24:$D$99,'Gastos julio'!$F$24:$F$99,$A11,'Gastos julio'!$H$24:$H$99,">="&F$5,'Gastos julio'!$H$24:$H$99,"<="&F$6) -> 5000 | G11: =SUM(B11:F11) -> 34600
A12: Regalos | B12: =-SUMIFS('Gastos julio'!$D$24:$D$99,'Gastos julio'!$F$24:$F$99,$A12,'Gastos julio'!$H$24:$H$99,">="&B$5,'Gastos julio'!$H$24:$H$99,"<="&B$6) -> 1300 | C12: =-SUMIFS('Gastos julio'!$D$24:$D$99,'Gastos julio'!$F$24:$F$99,$A12,'Gastos julio'!$H$24:$H$99,">="&C$5,'Gastos julio'!$H$24:$H$99,"<="&C$6) -> 0 | D12: =-SUMIFS('Gastos julio'!$D$24:$D$99,'Gastos julio'!$F$24:$F$99,$A12,'Gastos julio'!$H$24:$H$99,">="&D$5,'Gastos julio'!$H$24:$H$99,"<="&D$6) -> 0 | E12: =-SUMIFS('Gastos julio'!$D$24:$D$99,'Gastos julio'!$F$24:$F$99,$A12,'Gastos julio'!$H$24:$H$99,">="&E$5,'Gastos julio'!$H$24:$H$99,"<="&E$6) -> 13000 | F12: =-SUMIFS('Gastos julio'!$D$24:$D$99,'Gastos julio'!$F$24:$F$99,$A12,'Gastos julio'!$H$24:$H$99,">="&F$5,'Gastos julio'!$H$24:$H$99,"<="&F$6) -> 0 | G12: =SUM(B12:F12) -> 14300
A13: Psicóloga | B13: =-SUMIFS('Gastos julio'!$D$24:$D$99,'Gastos julio'!$F$24:$F$99,$A13,'Gastos julio'!$H$24:$H$99,">="&B$5,'Gastos julio'!$H$24:$H$99,"<="&B$6) -> 0 | C13: =-SUMIFS('Gastos julio'!$D$24:$D$99,'Gastos julio'!$F$24:$F$99,$A13,'Gastos julio'!$H$24:$H$99,">="&C$5,'Gastos julio'!$H$24:$H$99,"<="&C$6) -> 40000 | D13: =-SUMIFS('Gastos julio'!$D$24:$D$99,'Gastos julio'!$F$24:$F$99,$A13,'Gastos julio'!$H$24:$H$99,">="&D$5,'Gastos julio'!$H$24:$H$99,"<="&D$6) -> 0 | E13: =-SUMIFS('Gastos julio'!$D$24:$D$99,'Gastos julio'!$F$24:$F$99,$A13,'Gastos julio'!$H$24:$H$99,">="&E$5,'Gastos julio'!$H$24:$H$99,"<="&E$6) -> 45000 | F13: =-SUMIFS('Gastos julio'!$D$24:$D$99,'Gastos julio'!$F$24:$F$99,$A13,'Gastos julio'!$H$24:$H$99,">="&F$5,'Gastos julio'!$H$24:$H$99,"<="&F$6) -> 0 | G13: =SUM(B13:F13) -> 85000
A14: Gimnasio | B14: =-SUMIFS('Gastos julio'!$D$24:$D$99,'Gastos julio'!$F$24:$F$99,$A14,'Gastos julio'!$H$24:$H$99,">="&B$5,'Gastos julio'!$H$24:$H$99,"<="&B$6) -> 0 | C14: =-SUMIFS('Gastos julio'!$D$24:$D$99,'Gastos julio'!$F$24:$F$99,$A14,'Gastos julio'!$H$24:$H$99,">="&C$5,'Gastos julio'!$H$24:$H$99,"<="&C$6) -> 53000 | D14: =-SUMIFS('Gastos julio'!$D$24:$D$99,'Gastos julio'!$F$24:$F$99,$A14,'Gastos julio'!$H$24:$H$99,">="&D$5,'Gastos julio'!$H$24:$H$99,"<="&D$6) -> 0 | E14: =-SUMIFS('Gastos julio'!$D$24:$D$99,'Gastos julio'!$F$24:$F$99,$A14,'Gastos julio'!$H$24:$H$99,">="&E$5,'Gastos julio'!$H$24:$H$99,"<="&E$6) -> 0 | F14: =-SUMIFS('Gastos julio'!$D$24:$D$99,'Gastos julio'!$F$24:$F$99,$A14,'Gastos julio'!$H$24:$H$99,">="&F$5,'Gastos julio'!$H$24:$H$99,"<="&F$6) -> 53000 | G14: =SUM(B14:F14) -> 106000
A15: Farmacia/Cosméticos | B15: =-SUMIFS('Gastos julio'!$D$24:$D$99,'Gastos julio'!$F$24:$F$99,$A15,'Gastos julio'!$H$24:$H$99,">="&B$5,'Gastos julio'!$H$24:$H$99,"<="&B$6) -> 0 | C15: =-SUMIFS('Gastos julio'!$D$24:$D$99,'Gastos julio'!$F$24:$F$99,$A15,'Gastos julio'!$H$24:$H$99,">="&C$5,'Gastos julio'!$H$24:$H$99,"<="&C$6) -> 0 | D15: =-SUMIFS('Gastos julio'!$D$24:$D$99,'Gastos julio'!$F$24:$F$99,$A15,'Gastos julio'!$H$24:$H$99,">="&D$5,'Gastos julio'!$H$24:$H$99,"<="&D$6) -> 0 | E15: =-SUMIFS('Gastos julio'!$D$24:$D$99,'Gastos julio'!$F$24:$F$99,$A15,'Gastos julio'!$H$24:$H$99,">="&E$5,'Gastos julio'!$H$24:$H$99,"<="&E$6) -> 9599.4 | F15: =-SUMIFS('Gastos julio'!$D$24:$D$99,'Gastos julio'!$F$24:$F$99,$A15,'Gastos julio'!$H$24:$H$99,">="&F$5,'Gastos julio'!$H$24:$H$99,"<="&F$6) -> 25693 | G15: =SUM(B15:F15) -> 35292.4
A16: Telas e insumos p costura | B16: =-SUMIFS('Gastos julio'!$D$24:$D$99,'Gastos julio'!$F$24:$F$99,$A16,'Gastos julio'!$H$24:$H$99,">="&B$5,'Gastos julio'!$H$24:$H$99,"<="&B$6) -> 0 | C16: =-SUMIFS('Gastos julio'!$D$24:$D$99,'Gastos julio'!$F$24:$F$99,$A16,'Gastos julio'!$H$24:$H$99,">="&C$5,'Gastos julio'!$H$24:$H$99,"<="&C$6) -> 0 | D16: =-SUMIFS('Gastos julio'!$D$24:$D$99,'Gastos julio'!$F$24:$F$99,$A16,'Gastos julio'!$H$24:$H$99,">="&D$5,'Gastos julio'!$H$24:$H$99,"<="&D$6) -> 0 | E16: =-SUMIFS('Gastos julio'!$D$24:$D$99,'Gastos julio'!$F$24:$F$99,$A16,'Gastos julio'!$H$24:$H$99,">="&E$5,'Gastos julio'!$H$24:$H$99,"<="&E$6) -> 32980 | F16: =-SUMIFS('Gastos julio'!$D$24:$D$99,'Gastos julio'!$F$24:$F$99,$A16,'Gastos julio'!$H$24:$H$99,">="&F$5,'Gastos julio'!$H$24:$H$99,"<="&F$6) -> 0 | G16: =SUM(B16:F16) -> 32980
A17: Pago monotributo | B17: =-SUMIFS('Gastos julio'!$D$24:$D$99,'Gastos julio'!$F$24:$F$99,$A17,'Gastos julio'!$H$24:$H$99,">="&B$5,'Gastos julio'!$H$24:$H$99,"<="&B$6) -> 0 | C17: =-SUMIFS('Gastos julio'!$D$24:$D$99,'Gastos julio'!$F$24:$F$99,$A17,'Gastos julio'!$H$24:$H$99,">="&C$5,'Gastos julio'!$H$24:$H$99,"<="&C$6) -> 0 | D17: =-SUMIFS('Gastos julio'!$D$24:$D$99,'Gastos julio'!$F$24:$F$99,$A17,'Gastos julio'!$H$24:$H$99,">="&D$5,'Gastos julio'!$H$24:$H$99,"<="&D$6) -> 0 | E17: =-SUMIFS('Gastos julio'!$D$24:$D$99,'Gastos julio'!$F$24:$F$99,$A17,'Gastos julio'!$H$24:$H$99,">="&E$5,'Gastos julio'!$H$24:$H$99,"<="&E$6) -> 42386.74 | F17: =-SUMIFS('Gastos julio'!$D$24:$D$99,'Gastos julio'!$F$24:$F$99,$A17,'Gastos julio'!$H$24:$H$99,">="&F$5,'Gastos julio'!$H$24:$H$99,"<="&F$6) -> 0 | G17: =SUM(B17:F17) -> 42386.74
A18: Transferencias Jo | B18: =-SUMIFS('Gastos julio'!$D$24:$D$99,'Gastos julio'!$F$24:$F$99,$A18,'Gastos julio'!$H$24:$H$99,">="&B$5,'Gastos julio'!$H$24:$H$99,"<="&B$6) -> 0 | C18: =-SUMIFS('Gastos julio'!$D$24:$D$99,'Gastos julio'!$F$24:$F$99,$A18,'Gastos julio'!$H$24:$H$99,">="&C$5,'Gastos julio'!$H$24:$H$99,"<="&C$6) -> 0 | D18: =-SUMIFS('Gastos julio'!$D$24:$D$99,'Gastos julio'!$F$24:$F$99,$A18,'Gastos julio'!$H$24:$H$99,">="&D$5,'Gastos julio'!$H$24:$H$99,"<="&D$6) -> 0 | E18: =-SUMIFS('Gastos julio'!$D$24:$D$99,'Gastos julio'!$F$24:$F$99,$A18,'Gastos julio'!$H$24:$H$99,">="&E$5,'Gastos julio'!$H$24:$H$99,"<="&E$6) -> 0 | F18: =-SUMIFS('Gastos julio'!$D$24:$D$99,'Gastos julio'!$F$24:$F$99,$A18,'Gastos julio'!$H$24:$H$99,">="&F$5,'Gastos julio'!$H$24:$H$99,"<="&F$6) -> 25000 | G18: =SUM(B18:F18) -> 25000
A19: Total gastos corrientes (bruto) | B19: =SUM(B7:B18) -> 146759 | C19: =SUM(C7:C18) -> 233615 | D19: =SUM(D7:D18) -> 184563.6 | E19: =SUM(E7:E18) -> 302866.14 | F19: =SUM(F7:F18) -> 122293 | G19: =SUM(G7:G18) -> 990096.74
A21: Movimientos internos / financieros
A22: Pago tarjetas de crédito | B22: =-SUMIFS('Gastos julio'!$D$24:$D$99,'Gastos julio'!$F$24:$F$99,$A22,'Gastos julio'!$H$24:$H$99,">="&B$5,'Gastos julio'!$H$24:$H$99,"<="&B$6) -> 0 | C22: =-SUMIFS('Gastos julio'!$D$24:$D$99,'Gastos julio'!$F$24:$F$99,$A22,'Gastos julio'!$H$24:$H$99,">="&C$5,'Gastos julio'!$H$24:$H$99,"<="&C$6) -> 692785.84 | D22: =-SUMIFS('Gastos julio'!$D$24:$D$99,'Gastos julio'!$F$24:$F$99,$A22,'Gastos julio'!$H$24:$H$99,">="&D$5,'Gastos julio'!$H$24:$H$99,"<="&D$6) -> 0 | E22: =-SUMIFS('Gastos julio'!$D$24:$D$99,'Gastos julio'!$F$24:$F$99,$A22,'Gastos julio'!$H$24:$H$99,">="&E$5,'Gastos julio'!$H$24:$H$99,"<="&E$6) -> 0 | F22: =-SUMIFS('Gastos julio'!$D$24:$D$99,'Gastos julio'!$F$24:$F$99,$A22,'Gastos julio'!$H$24:$H$99,">="&F$5,'Gastos julio'!$H$24:$H$99,"<="&F$6) -> 0 | G22: =SUM(B22:F22) -> 692785.84
A23: Ahorros/inversiones | B23: =-SUMIFS('Gastos julio'!$D$24:$D$99,'Gastos julio'!$F$24:$F$99,$A23,'Gastos julio'!$H$24:$H$99,">="&B$5,'Gastos julio'!$H$24:$H$99,"<="&B$6) -> 1200000 | C23: =-SUMIFS('Gastos julio'!$D$24:$D$99,'Gastos julio'!$F$24:$F$99,$A23,'Gastos julio'!$H$24:$H$99,">="&C$5,'Gastos julio'!$H$24:$H$99,"<="&C$6) -> 0 | D23: =-SUMIFS('Gastos julio'!$D$24:$D$99,'Gastos julio'!$F$24:$F$99,$A23,'Gastos julio'!$H$24:$H$99,">="&D$5,'Gastos julio'!$H$24:$H$99,"<="&D$6) -> 0 | E23: =-SUMIFS('Gastos julio'!$D$24:$D$99,'Gastos julio'!$F$24:$F$99,$A23,'Gastos julio'!$H$24:$H$99,">="&E$5,'Gastos julio'!$H$24:$H$99,"<="&E$6) -> 0 | F23: =-SUMIFS('Gastos julio'!$D$24:$D$99,'Gastos julio'!$F$24:$F$99,$A23,'Gastos julio'!$H$24:$H$99,">="&F$5,'Gastos julio'!$H$24:$H$99,"<="&F$6) -> 0 | G23: =SUM(B23:F23) -> 1200000
A24: Rescates FCI | B24: =-SUMIFS('Gastos julio'!$D$24:$D$99,'Gastos julio'!$F$24:$F$99,$A24,'Gastos julio'!$H$24:$H$99,">="&B$5,'Gastos julio'!$H$24:$H$99,"<="&B$6) -> 1000524.3 | C24: =-SUMIFS('Gastos julio'!$D$24:$D$99,'Gastos julio'!$F$24:$F$99,$A24,'Gastos julio'!$H$24:$H$99,">="&C$5,'Gastos julio'!$H$24:$H$99,"<="&C$6) -> 700000 | D24: =-SUMIFS('Gastos julio'!$D$24:$D$99,'Gastos julio'!$F$24:$F$99,$A24,'Gastos julio'!$H$24:$H$99,">="&D$5,'Gastos julio'!$H$24:$H$99,"<="&D$6) -> 0 | E24: =-SUMIFS('Gastos julio'!$D$24:$D$99,'Gastos julio'!$F$24:$F$99,$A24,'Gastos julio'!$H$24:$H$99,">="&E$5,'Gastos julio'!$H$24:$H$99,"<="&E$6) -> 140000 | F24: =-SUMIFS('Gastos julio'!$D$24:$D$99,'Gastos julio'!$F$24:$F$99,$A24,'Gastos julio'!$H$24:$H$99,">="&F$5,'Gastos julio'!$H$24:$H$99,"<="&F$6) -> 0 | G24: =SUM(B24:F24) -> 1840524.3
A25: Total movimientos internos | B25: =SUM(B22:B24) -> 2200524.3 | C25: =SUM(C22:C24) -> 1392785.8 | D25: =SUM(D22:D24) -> 0 | E25: =SUM(E22:E24) -> 140000 | F25: =SUM(F22:F24) -> 0 | G25: =SUM(G22:G24) -> 3733310.1
A27: TOTAL GENERAL | B27: =B19+B25 -> 2347283.3 | C27: =C19+C25 -> 1626400.8 | D27: =D19+D25 -> 184563.6 | E27: =E19+E25 -> 442866.14 | F27: =F19+F25 -> 122293 | G27: =G19+G25 -> 4723406.8
A29: Control: total gastos julio (columna D) | B29: =-SUMIFS('Gastos julio'!$D$24:$D$99,'Gastos julio'!$H$24:$H$99,">="&$B$5,'Gastos julio'!$H$24:$H$99,"<="&$F$6) -> 4723406.8
A30: Diferencia vs. total general (debe ser 0) | B30: =B29-G27 -> 0
A31: Gastos fuera del rango de julio (fecha inválida) | B31: =-SUMIFS('Gastos julio'!$D$24:$D$99,'Gastos julio'!$H$24:$H$99,">"&$F$6)-SUMIFS('Gastos julio'!$D$24:$D$99,'Gastos julio'!$H$24:$H$99,"<"&$B$5) -> 42000
A33: Reintegros / devoluciones recibidas (columna C de 'Gastos julio')
A34: Concepto | B34: Sem 1 | C34: Sem 2 | D34: Sem 3 | E34: Sem 4 | F34: Sem 5 | G34: Total mes
A35: =$A7 -> Delivery | B35: =SUMIFS('Gastos julio'!$C$24:$C$99,'Gastos julio'!$F$24:$F$99,$A35,'Gastos julio'!$H$24:$H$99,">="&B$5,'Gastos julio'!$H$24:$H$99,"<="&B$6) -> 20000 | C35: =SUMIFS('Gastos julio'!$C$24:$C$99,'Gastos julio'!$F$24:$F$99,$A35,'Gastos julio'!$H$24:$H$99,">="&C$5,'Gastos julio'!$H$24:$H$99,"<="&C$6) -> 133000 | D35: =SUMIFS('Gastos julio'!$C$24:$C$99,'Gastos julio'!$F$24:$F$99,$A35,'Gastos julio'!$H$24:$H$99,">="&D$5,'Gastos julio'!$H$24:$H$99,"<="&D$6) -> 0 | E35: =SUMIFS('Gastos julio'!$C$24:$C$99,'Gastos julio'!$F$24:$F$99,$A35,'Gastos julio'!$H$24:$H$99,">="&E$5,'Gastos julio'!$H$24:$H$99,"<="&E$6) -> 0 | F35: =SUMIFS('Gastos julio'!$C$24:$C$99,'Gastos julio'!$F$24:$F$99,$A35,'Gastos julio'!$H$24:$H$99,">="&F$5,'Gastos julio'!$H$24:$H$99,"<="&F$6) -> 0 | G35: =SUM(B35:F35) -> 153000
A36: =$A8 -> Salidas a cenar/almorzar | B36: =SUMIFS('Gastos julio'!$C$24:$C$99,'Gastos julio'!$F$24:$F$99,$A36,'Gastos julio'!$H$24:$H$99,">="&B$5,'Gastos julio'!$H$24:$H$99,"<="&B$6) -> 0 | C36: =SUMIFS('Gastos julio'!$C$24:$C$99,'Gastos julio'!$F$24:$F$99,$A36,'Gastos julio'!$H$24:$H$99,">="&C$5,'Gastos julio'!$H$24:$H$99,"<="&C$6) -> 0 | D36: =SUMIFS('Gastos julio'!$C$24:$C$99,'Gastos julio'!$F$24:$F$99,$A36,'Gastos julio'!$H$24:$H$99,">="&D$5,'Gastos julio'!$H$24:$H$99,"<="&D$6) -> 40050 | E36: =SUMIFS('Gastos julio'!$C$24:$C$99,'Gastos julio'!$F$24:$F$99,$A36,'Gastos julio'!$H$24:$H$99,">="&E$5,'Gastos julio'!$H$24:$H$99,"<="&E$6) -> 0 | F36: =SUMIFS('Gastos julio'!$C$24:$C$99,'Gastos julio'!$F$24:$F$99,$A36,'Gastos julio'!$H$24:$H$99,">="&F$5,'Gastos julio'!$H$24:$H$99,"<="&F$6) -> 0 | G36: =SUM(B36:F36) -> 40050
A37: =$A9 -> Salidas a desyunar/merendar | B37: =SUMIFS('Gastos julio'!$C$24:$C$99,'Gastos julio'!$F$24:$F$99,$A37,'Gastos julio'!$H$24:$H$99,">="&B$5,'Gastos julio'!$H$24:$H$99,"<="&B$6) -> 17200 | C37: =SUMIFS('Gastos julio'!$C$24:$C$99,'Gastos julio'!$F$24:$F$99,$A37,'Gastos julio'!$H$24:$H$99,">="&C$5,'Gastos julio'!$H$24:$H$99,"<="&C$6) -> 0 | D37: =SUMIFS('Gastos julio'!$C$24:$C$99,'Gastos julio'!$F$24:$F$99,$A37,'Gastos julio'!$H$24:$H$99,">="&D$5,'Gastos julio'!$H$24:$H$99,"<="&D$6) -> 17000 | E37: =SUMIFS('Gastos julio'!$C$24:$C$99,'Gastos julio'!$F$24:$F$99,$A37,'Gastos julio'!$H$24:$H$99,">="&E$5,'Gastos julio'!$H$24:$H$99,"<="&E$6) -> 0 | F37: =SUMIFS('Gastos julio'!$C$24:$C$99,'Gastos julio'!$F$24:$F$99,$A37,'Gastos julio'!$H$24:$H$99,">="&F$5,'Gastos julio'!$H$24:$H$99,"<="&F$6) -> 0 | G37: =SUM(B37:F37) -> 34200
A38: =$A10 -> Salidas a tomar algo | B38: =SUMIFS('Gastos julio'!$C$24:$C$99,'Gastos julio'!$F$24:$F$99,$A38,'Gastos julio'!$H$24:$H$99,">="&B$5,'Gastos julio'!$H$24:$H$99,"<="&B$6) -> 0 | C38: =SUMIFS('Gastos julio'!$C$24:$C$99,'Gastos julio'!$F$24:$F$99,$A38,'Gastos julio'!$H$24:$H$99,">="&C$5,'Gastos julio'!$H$24:$H$99,"<="&C$6) -> 0 | D38: =SUMIFS('Gastos julio'!$C$24:$C$99,'Gastos julio'!$F$24:$F$99,$A38,'Gastos julio'!$H$24:$H$99,">="&D$5,'Gastos julio'!$H$24:$H$99,"<="&D$6) -> 0 | E38: =SUMIFS('Gastos julio'!$C$24:$C$99,'Gastos julio'!$F$24:$F$99,$A38,'Gastos julio'!$H$24:$H$99,">="&E$5,'Gastos julio'!$H$24:$H$99,"<="&E$6) -> 32000 | F38: =SUMIFS('Gastos julio'!$C$24:$C$99,'Gastos julio'!$F$24:$F$99,$A38,'Gastos julio'!$H$24:$H$99,">="&F$5,'Gastos julio'!$H$24:$H$99,"<="&F$6) -> 0 | G38: =SUM(B38:F38) -> 32000
A39: =$A11 -> Auto | B39: =SUMIFS('Gastos julio'!$C$24:$C$99,'Gastos julio'!$F$24:$F$99,$A39,'Gastos julio'!$H$24:$H$99,">="&B$5,'Gastos julio'!$H$24:$H$99,"<="&B$6) -> 0 | C39: =SUMIFS('Gastos julio'!$C$24:$C$99,'Gastos julio'!$F$24:$F$99,$A39,'Gastos julio'!$H$24:$H$99,">="&C$5,'Gastos julio'!$H$24:$H$99,"<="&C$6) -> 0 | D39: =SUMIFS('Gastos julio'!$C$24:$C$99,'Gastos julio'!$F$24:$F$99,$A39,'Gastos julio'!$H$24:$H$99,">="&D$5,'Gastos julio'!$H$24:$H$99,"<="&D$6) -> 0 | E39: =SUMIFS('Gastos julio'!$C$24:$C$99,'Gastos julio'!$F$24:$F$99,$A39,'Gastos julio'!$H$24:$H$99,">="&E$5,'Gastos julio'!$H$24:$H$99,"<="&E$6) -> 0 | F39: =SUMIFS('Gastos julio'!$C$24:$C$99,'Gastos julio'!$F$24:$F$99,$A39,'Gastos julio'!$H$24:$H$99,">="&F$5,'Gastos julio'!$H$24:$H$99,"<="&F$6) -> 0 | G39: =SUM(B39:F39) -> 0
A40: =$A12 -> Regalos | B40: =SUMIFS('Gastos julio'!$C$24:$C$99,'Gastos julio'!$F$24:$F$99,$A40,'Gastos julio'!$H$24:$H$99,">="&B$5,'Gastos julio'!$H$24:$H$99,"<="&B$6) -> 0 | C40: =SUMIFS('Gastos julio'!$C$24:$C$99,'Gastos julio'!$F$24:$F$99,$A40,'Gastos julio'!$H$24:$H$99,">="&C$5,'Gastos julio'!$H$24:$H$99,"<="&C$6) -> 0 | D40: =SUMIFS('Gastos julio'!$C$24:$C$99,'Gastos julio'!$F$24:$F$99,$A40,'Gastos julio'!$H$24:$H$99,">="&D$5,'Gastos julio'!$H$24:$H$99,"<="&D$6) -> 0 | E40: =SUMIFS('Gastos julio'!$C$24:$C$99,'Gastos julio'!$F$24:$F$99,$A40,'Gastos julio'!$H$24:$H$99,">="&E$5,'Gastos julio'!$H$24:$H$99,"<="&E$6) -> 67500 | F40: =SUMIFS('Gastos julio'!$C$24:$C$99,'Gastos julio'!$F$24:$F$99,$A40,'Gastos julio'!$H$24:$H$99,">="&F$5,'Gastos julio'!$H$24:$H$99,"<="&F$6) -> 0 | G40: =SUM(B40:F40) -> 67500
A41: =$A13 -> Psicóloga | B41: =SUMIFS('Gastos julio'!$C$24:$C$99,'Gastos julio'!$F$24:$F$99,$A41,'Gastos julio'!$H$24:$H$99,">="&B$5,'Gastos julio'!$H$24:$H$99,"<="&B$6) -> 0 | C41: =SUMIFS('Gastos julio'!$C$24:$C$99,'Gastos julio'!$F$24:$F$99,$A41,'Gastos julio'!$H$24:$H$99,">="&C$5,'Gastos julio'!$H$24:$H$99,"<="&C$6) -> 0 | D41: =SUMIFS('Gastos julio'!$C$24:$C$99,'Gastos julio'!$F$24:$F$99,$A41,'Gastos julio'!$H$24:$H$99,">="&D$5,'Gastos julio'!$H$24:$H$99,"<="&D$6) -> 0 | E41: =SUMIFS('Gastos julio'!$C$24:$C$99,'Gastos julio'!$F$24:$F$99,$A41,'Gastos julio'!$H$24:$H$99,">="&E$5,'Gastos julio'!$H$24:$H$99,"<="&E$6) -> 0 | F41: =SUMIFS('Gastos julio'!$C$24:$C$99,'Gastos julio'!$F$24:$F$99,$A41,'Gastos julio'!$H$24:$H$99,">="&F$5,'Gastos julio'!$H$24:$H$99,"<="&F$6) -> 29790 | G41: =SUM(B41:F41) -> 29790
A42: =$A14 -> Gimnasio | B42: =SUMIFS('Gastos julio'!$C$24:$C$99,'Gastos julio'!$F$24:$F$99,$A42,'Gastos julio'!$H$24:$H$99,">="&B$5,'Gastos julio'!$H$24:$H$99,"<="&B$6) -> 0 | C42: =SUMIFS('Gastos julio'!$C$24:$C$99,'Gastos julio'!$F$24:$F$99,$A42,'Gastos julio'!$H$24:$H$99,">="&C$5,'Gastos julio'!$H$24:$H$99,"<="&C$6) -> 0 | D42: =SUMIFS('Gastos julio'!$C$24:$C$99,'Gastos julio'!$F$24:$F$99,$A42,'Gastos julio'!$H$24:$H$99,">="&D$5,'Gastos julio'!$H$24:$H$99,"<="&D$6) -> 0 | E42: =SUMIFS('Gastos julio'!$C$24:$C$99,'Gastos julio'!$F$24:$F$99,$A42,'Gastos julio'!$H$24:$H$99,">="&E$5,'Gastos julio'!$H$24:$H$99,"<="&E$6) -> 0 | F42: =SUMIFS('Gastos julio'!$C$24:$C$99,'Gastos julio'!$F$24:$F$99,$A42,'Gastos julio'!$H$24:$H$99,">="&F$5,'Gastos julio'!$H$24:$H$99,"<="&F$6) -> 0 | G42: =SUM(B42:F42) -> 0
A43: =$A15 -> Farmacia/Cosméticos | B43: =SUMIFS('Gastos julio'!$C$24:$C$99,'Gastos julio'!$F$24:$F$99,$A43,'Gastos julio'!$H$24:$H$99,">="&B$5,'Gastos julio'!$H$24:$H$99,"<="&B$6) -> 0 | C43: =SUMIFS('Gastos julio'!$C$24:$C$99,'Gastos julio'!$F$24:$F$99,$A43,'Gastos julio'!$H$24:$H$99,">="&C$5,'Gastos julio'!$H$24:$H$99,"<="&C$6) -> 0 | D43: =SUMIFS('Gastos julio'!$C$24:$C$99,'Gastos julio'!$F$24:$F$99,$A43,'Gastos julio'!$H$24:$H$99,">="&D$5,'Gastos julio'!$H$24:$H$99,"<="&D$6) -> 0 | E43: =SUMIFS('Gastos julio'!$C$24:$C$99,'Gastos julio'!$F$24:$F$99,$A43,'Gastos julio'!$H$24:$H$99,">="&E$5,'Gastos julio'!$H$24:$H$99,"<="&E$6) -> 1439.91 | F43: =SUMIFS('Gastos julio'!$C$24:$C$99,'Gastos julio'!$F$24:$F$99,$A43,'Gastos julio'!$H$24:$H$99,">="&F$5,'Gastos julio'!$H$24:$H$99,"<="&F$6) -> 0 | G43: =SUM(B43:F43) -> 1439.91
A44: =$A16 -> Telas e insumos p costura | B44: =SUMIFS('Gastos julio'!$C$24:$C$99,'Gastos julio'!$F$24:$F$99,$A44,'Gastos julio'!$H$24:$H$99,">="&B$5,'Gastos julio'!$H$24:$H$99,"<="&B$6) -> 0 | C44: =SUMIFS('Gastos julio'!$C$24:$C$99,'Gastos julio'!$F$24:$F$99,$A44,'Gastos julio'!$H$24:$H$99,">="&C$5,'Gastos julio'!$H$24:$H$99,"<="&C$6) -> 0 | D44: =SUMIFS('Gastos julio'!$C$24:$C$99,'Gastos julio'!$F$24:$F$99,$A44,'Gastos julio'!$H$24:$H$99,">="&D$5,'Gastos julio'!$H$24:$H$99,"<="&D$6) -> 0 | E44: =SUMIFS('Gastos julio'!$C$24:$C$99,'Gastos julio'!$F$24:$F$99,$A44,'Gastos julio'!$H$24:$H$99,">="&E$5,'Gastos julio'!$H$24:$H$99,"<="&E$6) -> 0 | F44: =SUMIFS('Gastos julio'!$C$24:$C$99,'Gastos julio'!$F$24:$F$99,$A44,'Gastos julio'!$H$24:$H$99,">="&F$5,'Gastos julio'!$H$24:$H$99,"<="&F$6) -> 0 | G44: =SUM(B44:F44) -> 0
A45: =$A17 -> Pago monotributo | B45: =SUMIFS('Gastos julio'!$C$24:$C$99,'Gastos julio'!$F$24:$F$99,$A45,'Gastos julio'!$H$24:$H$99,">="&B$5,'Gastos julio'!$H$24:$H$99,"<="&B$6) -> 0 | C45: =SUMIFS('Gastos julio'!$C$24:$C$99,'Gastos julio'!$F$24:$F$99,$A45,'Gastos julio'!$H$24:$H$99,">="&C$5,'Gastos julio'!$H$24:$H$99,"<="&C$6) -> 0 | D45: =SUMIFS('Gastos julio'!$C$24:$C$99,'Gastos julio'!$F$24:$F$99,$A45,'Gastos julio'!$H$24:$H$99,">="&D$5,'Gastos julio'!$H$24:$H$99,"<="&D$6) -> 0 | E45: =SUMIFS('Gastos julio'!$C$24:$C$99,'Gastos julio'!$F$24:$F$99,$A45,'Gastos julio'!$H$24:$H$99,">="&E$5,'Gastos julio'!$H$24:$H$99,"<="&E$6) -> 0 | F45: =SUMIFS('Gastos julio'!$C$24:$C$99,'Gastos julio'!$F$24:$F$99,$A45,'Gastos julio'!$H$24:$H$99,">="&F$5,'Gastos julio'!$H$24:$H$99,"<="&F$6) -> 0 | G45: =SUM(B45:F45) -> 0
A46: =$A18 -> Transferencias Jo | B46: =SUMIFS('Gastos julio'!$C$24:$C$99,'Gastos julio'!$F$24:$F$99,$A46,'Gastos julio'!$H$24:$H$99,">="&B$5,'Gastos julio'!$H$24:$H$99,"<="&B$6) -> 0 | C46: =SUMIFS('Gastos julio'!$C$24:$C$99,'Gastos julio'!$F$24:$F$99,$A46,'Gastos julio'!$H$24:$H$99,">="&C$5,'Gastos julio'!$H$24:$H$99,"<="&C$6) -> 0 | D46: =SUMIFS('Gastos julio'!$C$24:$C$99,'Gastos julio'!$F$24:$F$99,$A46,'Gastos julio'!$H$24:$H$99,">="&D$5,'Gastos julio'!$H$24:$H$99,"<="&D$6) -> 0 | E46: =SUMIFS('Gastos julio'!$C$24:$C$99,'Gastos julio'!$F$24:$F$99,$A46,'Gastos julio'!$H$24:$H$99,">="&E$5,'Gastos julio'!$H$24:$H$99,"<="&E$6) -> 0 | F46: =SUMIFS('Gastos julio'!$C$24:$C$99,'Gastos julio'!$F$24:$F$99,$A46,'Gastos julio'!$H$24:$H$99,">="&F$5,'Gastos julio'!$H$24:$H$99,"<="&F$6) -> 0 | G46: =SUM(B46:F46) -> 0
A47: Total reintegros | B47: =SUM(B35:B46) -> 37200 | C47: =SUM(C35:C46) -> 133000 | D47: =SUM(D35:D46) -> 57050 | E47: =SUM(E35:E46) -> 100939.91 | F47: =SUM(F35:F46) -> 29790 | G47: =SUM(G35:G46) -> 357979.91
A50: GASTO NETO por semana (bruto − reintegros)
A51: Concepto | B51: Sem 1 | C51: Sem 2 | D51: Sem 3 | E51: Sem 4 | F51: Sem 5 | G51: Total mes
A52: =$A7 -> Delivery | B52: =B7-B35 -> 30559 | C52: =C7-C35 -> 7615 | D52: =D7-D35 -> 6883.6 | E52: =E7-E35 -> 26500 | F52: =F7-F35 -> 0 | G52: =SUM(B52:F52) -> 71557.6
A53: =$A8 -> Salidas a cenar/almorzar | B53: =B8-B36 -> 0 | C53: =C8-C36 -> 0 | D53: =D8-D36 -> 92230 | E53: =E8-E36 -> 34100 | F53: =F8-F36 -> 13600 | G53: =SUM(B53:F53) -> 139930
A54: =$A9 -> Salidas a desyunar/merendar | B54: =B9-B37 -> 54100 | C54: =C9-C37 -> 0 | D54: =D9-D37 -> 26400 | E54: =E9-E37 -> 30300 | F54: =F9-F37 -> 0 | G54: =SUM(B54:F54) -> 110800
A55: =$A10 -> Salidas a tomar algo | B55: =B10-B38 -> 0 | C55: =C10-C38 -> 0 | D55: =D10-D38 -> 0 | E55: =E10-E38 -> 33000 | F55: =F10-F38 -> 0 | G55: =SUM(B55:F55) -> 33000
A56: =$A11 -> Auto | B56: =B11-B39 -> 23600 | C56: =C11-C39 -> 0 | D56: =D11-D39 -> 2000 | E56: =E11-E39 -> 4000 | F56: =F11-F39 -> 5000 | G56: =SUM(B56:F56) -> 34600
A57: =$A12 -> Regalos | B57: =B12-B40 -> 1300 | C57: =C12-C40 -> 0 | D57: =D12-D40 -> 0 | E57: =E12-E40 -> -54500 | F57: =F12-F40 -> 0 | G57: =SUM(B57:F57) -> -53200
A58: =$A13 -> Psicóloga | B58: =B13-B41 -> 0 | C58: =C13-C41 -> 40000 | D58: =D13-D41 -> 0 | E58: =E13-E41 -> 45000 | F58: =F13-F41 -> -29790 | G58: =SUM(B58:F58) -> 55210
A59: =$A14 -> Gimnasio | B59: =B14-B42 -> 0 | C59: =C14-C42 -> 53000 | D59: =D14-D42 -> 0 | E59: =E14-E42 -> 0 | F59: =F14-F42 -> 53000 | G59: =SUM(B59:F59) -> 106000
A60: =$A15 -> Farmacia/Cosméticos | B60: =B15-B43 -> 0 | C60: =C15-C43 -> 0 | D60: =D15-D43 -> 0 | E60: =E15-E43 -> 8159.49 | F60: =F15-F43 -> 25693 | G60: =SUM(B60:F60) -> 33852.49
A61: =$A16 -> Telas e insumos p costura | B61: =B16-B44 -> 0 | C61: =C16-C44 -> 0 | D61: =D16-D44 -> 0 | E61: =E16-E44 -> 32980 | F61: =F16-F44 -> 0 | G61: =SUM(B61:F61) -> 32980
A62: =$A17 -> Pago monotributo | B62: =B17-B45 -> 0 | C62: =C17-C45 -> 0 | D62: =D17-D45 -> 0 | E62: =E17-E45 -> 42386.74 | F62: =F17-F45 -> 0 | G62: =SUM(B62:F62) -> 42386.74
A63: =$A18 -> Transferencias Jo | B63: =B18-B46 -> 0 | C63: =C18-C46 -> 0 | D63: =D18-D46 -> 0 | E63: =E18-E46 -> 0 | F63: =F18-F46 -> 25000 | G63: =SUM(B63:F63) -> 25000
A64: Total gasto neto | B64: =SUM(B52:B63) -> 109559 | C64: =SUM(C52:C63) -> 100615 | D64: =SUM(D52:D63) -> 127513.6 | E64: =SUM(E52:E63) -> 201926.23 | F64: =SUM(F52:F63) -> 92503 | G64: =SUM(G52:G63) -> 632116.83
A66: Nota: un neto negativo indica que el reintegro recibido supera el gasto registrado con ese concepto (ej. Regalos: llegaron $67.500 por 'regalo Co' pero el desembolso no está cargado como Regalos; y en Delivery hay un reintegro de $30.000 rotulado 'Regalo padres').

Sheet Análisis semanal agosto
A1: Gastos por semana y concepto — Agosto 2026
A2: Importes en ARS, mostrados en positivo. Fuente: 'Gastos agosto'!D24:D110 (gastos), F (concepto), H (fecha). Mes parcial: datos hasta el 26/08.
A4: Concepto | B4: Sem 1 | C4: Sem 2 | D4: Sem 3 | E4: Sem 4 | F4: Sem 5 | G4: Total mes
A5: Desde | B5: 46235 | C5: 46237 | D5: 46244 | E5: 46251 | F5: 46258
A6: Hasta | B6: 46236 | C6: 46243 | D6: 46250 | E6: 46257 | F6: 46265
A7: Salidas a cenar/almorzar | B7: =-SUMIFS('Gastos agosto'!$D$24:$D$110,'Gastos agosto'!$F$24:$F$110,$A7,'Gastos agosto'!$H$24:$H$110,">="&B$5,'Gastos agosto'!$H$24:$H$110,"<="&B$6) -> 45000 | C7: =-SUMIFS('Gastos agosto'!$D$24:$D$110,'Gastos agosto'!$F$24:$F$110,$A7,'Gastos agosto'!$H$24:$H$110,">="&C$5,'Gastos agosto'!$H$24:$H$110,"<="&C$6) -> 159950.74 | D7: =-SUMIFS('Gastos agosto'!$D$24:$D$110,'Gastos agosto'!$F$24:$F$110,$A7,'Gastos agosto'!$H$24:$H$110,">="&D$5,'Gastos agosto'!$H$24:$H$110,"<="&D$6) -> 66180 | E7: =-SUMIFS('Gastos agosto'!$D$24:$D$110,'Gastos agosto'!$F$24:$F$110,$A7,'Gastos agosto'!$H$24:$H$110,">="&E$5,'Gastos agosto'!$H$24:$H$110,"<="&E$6) -> 5000 | F7: =-SUMIFS('Gastos agosto'!$D$24:$D$110,'Gastos agosto'!$F$24:$F$110,$A7,'Gastos agosto'!$H$24:$H$110,">="&F$5,'Gastos agosto'!$H$24:$H$110,"<="&F$6) -> 0 | G7: =SUM(B7:F7) -> 276130.74
A8: Juntadas a cenar/almorzar | B8: =-SUMIFS('Gastos agosto'!$D$24:$D$110,'Gastos agosto'!$F$24:$F$110,$A8,'Gastos agosto'!$H$24:$H$110,">="&B$5,'Gastos agosto'!$H$24:$H$110,"<="&B$6) -> 0 | C8: =-SUMIFS('Gastos agosto'!$D$24:$D$110,'Gastos agosto'!$F$24:$F$110,$A8,'Gastos agosto'!$H$24:$H$110,">="&C$5,'Gastos agosto'!$H$24:$H$110,"<="&C$6) -> 0 | D8: =-SUMIFS('Gastos agosto'!$D$24:$D$110,'Gastos agosto'!$F$24:$F$110,$A8,'Gastos agosto'!$H$24:$H$110,">="&D$5,'Gastos agosto'!$H$24:$H$110,"<="&D$6) -> 168094.27 | E8: =-SUMIFS('Gastos agosto'!$D$24:$D$110,'Gastos agosto'!$F$24:$F$110,$A8,'Gastos agosto'!$H$24:$H$110,">="&E$5,'Gastos agosto'!$H$24:$H$110,"<="&E$6) -> 60070 | F8: =-SUMIFS('Gastos agosto'!$D$24:$D$110,'Gastos agosto'!$F$24:$F$110,$A8,'Gastos agosto'!$H$24:$H$110,">="&F$5,'Gastos agosto'!$H$24:$H$110,"<="&F$6) -> 33100 | G8: =SUM(B8:F8) -> 261264.27
A9: Salidas a desyunar/merendar | B9: =-SUMIFS('Gastos agosto'!$D$24:$D$110,'Gastos agosto'!$F$24:$F$110,$A9,'Gastos agosto'!$H$24:$H$110,">="&B$5,'Gastos agosto'!$H$24:$H$110,"<="&B$6) -> 10000 | C9: =-SUMIFS('Gastos agosto'!$D$24:$D$110,'Gastos agosto'!$F$24:$F$110,$A9,'Gastos agosto'!$H$24:$H$110,">="&C$5,'Gastos agosto'!$H$24:$H$110,"<="&C$6) -> 0 | D9: =-SUMIFS('Gastos agosto'!$D$24:$D$110,'Gastos agosto'!$F$24:$F$110,$A9,'Gastos agosto'!$H$24:$H$110,">="&D$5,'Gastos agosto'!$H$24:$H$110,"<="&D$6) -> 0 | E9: =-SUMIFS('Gastos agosto'!$D$24:$D$110,'Gastos agosto'!$F$24:$F$110,$A9,'Gastos agosto'!$H$24:$H$110,">="&E$5,'Gastos agosto'!$H$24:$H$110,"<="&E$6) -> 8400 | F9: =-SUMIFS('Gastos agosto'!$D$24:$D$110,'Gastos agosto'!$F$24:$F$110,$A9,'Gastos agosto'!$H$24:$H$110,">="&F$5,'Gastos agosto'!$H$24:$H$110,"<="&F$6) -> 6700 | G9: =SUM(B9:F9) -> 25100
A10: Salidas a tomar algo | B10: =-SUMIFS('Gastos agosto'!$D$24:$D$110,'Gastos agosto'!$F$24:$F$110,$A10,'Gastos agosto'!$H$24:$H$110,">="&B$5,'Gastos agosto'!$H$24:$H$110,"<="&B$6) -> 61200 | C10: =-SUMIFS('Gastos agosto'!$D$24:$D$110,'Gastos agosto'!$F$24:$F$110,$A10,'Gastos agosto'!$H$24:$H$110,">="&C$5,'Gastos agosto'!$H$24:$H$110,"<="&C$6) -> 0 | D10: =-SUMIFS('Gastos agosto'!$D$24:$D$110,'Gastos agosto'!$F$24:$F$110,$A10,'Gastos agosto'!$H$24:$H$110,">="&D$5,'Gastos agosto'!$H$24:$H$110,"<="&D$6) -> 13500 | E10: =-SUMIFS('Gastos agosto'!$D$24:$D$110,'Gastos agosto'!$F$24:$F$110,$A10,'Gastos agosto'!$H$24:$H$110,">="&E$5,'Gastos agosto'!$H$24:$H$110,"<="&E$6) -> 22000 | F10: =-SUMIFS('Gastos agosto'!$D$24:$D$110,'Gastos agosto'!$F$24:$F$110,$A10,'Gastos agosto'!$H$24:$H$110,">="&F$5,'Gastos agosto'!$H$24:$H$110,"<="&F$6) -> 0 | G10: =SUM(B10:F10) -> 96700
A11: Delivery | B11: =-SUMIFS('Gastos agosto'!$D$24:$D$110,'Gastos agosto'!$F$24:$F$110,$A11,'Gastos agosto'!$H$24:$H$110,">="&B$5,'Gastos agosto'!$H$24:$H$110,"<="&B$6) -> 0 | C11: =-SUMIFS('Gastos agosto'!$D$24:$D$110,'Gastos agosto'!$F$24:$F$110,$A11,'Gastos agosto'!$H$24:$H$110,">="&C$5,'Gastos agosto'!$H$24:$H$110,"<="&C$6) -> 37500 | D11: =-SUMIFS('Gastos agosto'!$D$24:$D$110,'Gastos agosto'!$F$24:$F$110,$A11,'Gastos agosto'!$H$24:$H$110,">="&D$5,'Gastos agosto'!$H$24:$H$110,"<="&D$6) -> 0 | E11: =-SUMIFS('Gastos agosto'!$D$24:$D$110,'Gastos agosto'!$F$24:$F$110,$A11,'Gastos agosto'!$H$24:$H$110,">="&E$5,'Gastos agosto'!$H$24:$H$110,"<="&E$6) -> 0 | F11: =-SUMIFS('Gastos agosto'!$D$24:$D$110,'Gastos agosto'!$F$24:$F$110,$A11,'Gastos agosto'!$H$24:$H$110,">="&F$5,'Gastos agosto'!$H$24:$H$110,"<="&F$6) -> 0 | G11: =SUM(B11:F11) -> 37500
A12: Auto | B12: =-SUMIFS('Gastos agosto'!$D$24:$D$110,'Gastos agosto'!$F$24:$F$110,$A12,'Gastos agosto'!$H$24:$H$110,">="&B$5,'Gastos agosto'!$H$24:$H$110,"<="&B$6) -> 50000 | C12: =-SUMIFS('Gastos agosto'!$D$24:$D$110,'Gastos agosto'!$F$24:$F$110,$A12,'Gastos agosto'!$H$24:$H$110,">="&C$5,'Gastos agosto'!$H$24:$H$110,"<="&C$6) -> 20000 | D12: =-SUMIFS('Gastos agosto'!$D$24:$D$110,'Gastos agosto'!$F$24:$F$110,$A12,'Gastos agosto'!$H$24:$H$110,">="&D$5,'Gastos agosto'!$H$24:$H$110,"<="&D$6) -> 50000 | E12: =-SUMIFS('Gastos agosto'!$D$24:$D$110,'Gastos agosto'!$F$24:$F$110,$A12,'Gastos agosto'!$H$24:$H$110,">="&E$5,'Gastos agosto'!$H$24:$H$110,"<="&E$6) -> 25000 | F12: =-SUMIFS('Gastos agosto'!$D$24:$D$110,'Gastos agosto'!$F$24:$F$110,$A12,'Gastos agosto'!$H$24:$H$110,">="&F$5,'Gastos agosto'!$H$24:$H$110,"<="&F$6) -> 0 | G12: =SUM(B12:F12) -> 145000
A13: Regalos | B13: =-SUMIFS('Gastos agosto'!$D$24:$D$110,'Gastos agosto'!$F$24:$F$110,$A13,'Gastos agosto'!$H$24:$H$110,">="&B$5,'Gastos agosto'!$H$24:$H$110,"<="&B$6) -> 0 | C13: =-SUMIFS('Gastos agosto'!$D$24:$D$110,'Gastos agosto'!$F$24:$F$110,$A13,'Gastos agosto'!$H$24:$H$110,">="&C$5,'Gastos agosto'!$H$24:$H$110,"<="&C$6) -> 0 | D13: =-SUMIFS('Gastos agosto'!$D$24:$D$110,'Gastos agosto'!$F$24:$F$110,$A13,'Gastos agosto'!$H$24:$H$110,">="&D$5,'Gastos agosto'!$H$24:$H$110,"<="&D$6) -> 0 | E13: =-SUMIFS('Gastos agosto'!$D$24:$D$110,'Gastos agosto'!$F$24:$F$110,$A13,'Gastos agosto'!$H$24:$H$110,">="&E$5,'Gastos agosto'!$H$24:$H$110,"<="&E$6) -> 399950 | F13: =-SUMIFS('Gastos agosto'!$D$24:$D$110,'Gastos agosto'!$F$24:$F$110,$A13,'Gastos agosto'!$H$24:$H$110,">="&F$5,'Gastos agosto'!$H$24:$H$110,"<="&F$6) -> 0 | G13: =SUM(B13:F13) -> 399950
A14: Fiestas | B14: =-SUMIFS('Gastos agosto'!$D$24:$D$110,'Gastos agosto'!$F$24:$F$110,$A14,'Gastos agosto'!$H$24:$H$110,">="&B$5,'Gastos agosto'!$H$24:$H$110,"<="&B$6) -> 0 | C14: =-SUMIFS('Gastos agosto'!$D$24:$D$110,'Gastos agosto'!$F$24:$F$110,$A14,'Gastos agosto'!$H$24:$H$110,">="&C$5,'Gastos agosto'!$H$24:$H$110,"<="&C$6) -> 0 | D14: =-SUMIFS('Gastos agosto'!$D$24:$D$110,'Gastos agosto'!$F$24:$F$110,$A14,'Gastos agosto'!$H$24:$H$110,">="&D$5,'Gastos agosto'!$H$24:$H$110,"<="&D$6) -> 0 | E14: =-SUMIFS('Gastos agosto'!$D$24:$D$110,'Gastos agosto'!$F$24:$F$110,$A14,'Gastos agosto'!$H$24:$H$110,">="&E$5,'Gastos agosto'!$H$24:$H$110,"<="&E$6) -> 24600 | F14: =-SUMIFS('Gastos agosto'!$D$24:$D$110,'Gastos agosto'!$F$24:$F$110,$A14,'Gastos agosto'!$H$24:$H$110,">="&F$5,'Gastos agosto'!$H$24:$H$110,"<="&F$6) -> 0 | G14: =SUM(B14:F14) -> 24600
A15: Psicóloga | B15: =-SUMIFS('Gastos agosto'!$D$24:$D$110,'Gastos agosto'!$F$24:$F$110,$A15,'Gastos agosto'!$H$24:$H$110,">="&B$5,'Gastos agosto'!$H$24:$H$110,"<="&B$6) -> 0 | C15: =-SUMIFS('Gastos agosto'!$D$24:$D$110,'Gastos agosto'!$F$24:$F$110,$A15,'Gastos agosto'!$H$24:$H$110,">="&C$5,'Gastos agosto'!$H$24:$H$110,"<="&C$6) -> 45000 | D15: =-SUMIFS('Gastos agosto'!$D$24:$D$110,'Gastos agosto'!$F$24:$F$110,$A15,'Gastos agosto'!$H$24:$H$110,">="&D$5,'Gastos agosto'!$H$24:$H$110,"<="&D$6) -> 0 | E15: =-SUMIFS('Gastos agosto'!$D$24:$D$110,'Gastos agosto'!$F$24:$F$110,$A15,'Gastos agosto'!$H$24:$H$110,">="&E$5,'Gastos agosto'!$H$24:$H$110,"<="&E$6) -> 45000 | F15: =-SUMIFS('Gastos agosto'!$D$24:$D$110,'Gastos agosto'!$F$24:$F$110,$A15,'Gastos agosto'!$H$24:$H$110,">="&F$5,'Gastos agosto'!$H$24:$H$110,"<="&F$6) -> 45000 | G15: =SUM(B15:F15) -> 135000
A16: Farmacia/Cosméticos | B16: =-SUMIFS('Gastos agosto'!$D$24:$D$110,'Gastos agosto'!$F$24:$F$110,$A16,'Gastos agosto'!$H$24:$H$110,">="&B$5,'Gastos agosto'!$H$24:$H$110,"<="&B$6) -> 0 | C16: =-SUMIFS('Gastos agosto'!$D$24:$D$110,'Gastos agosto'!$F$24:$F$110,$A16,'Gastos agosto'!$H$24:$H$110,">="&C$5,'Gastos agosto'!$H$24:$H$110,"<="&C$6) -> 6686.31 | D16: =-SUMIFS('Gastos agosto'!$D$24:$D$110,'Gastos agosto'!$F$24:$F$110,$A16,'Gastos agosto'!$H$24:$H$110,">="&D$5,'Gastos agosto'!$H$24:$H$110,"<="&D$6) -> 0 | E16: =-SUMIFS('Gastos agosto'!$D$24:$D$110,'Gastos agosto'!$F$24:$F$110,$A16,'Gastos agosto'!$H$24:$H$110,">="&E$5,'Gastos agosto'!$H$24:$H$110,"<="&E$6) -> 0 | F16: =-SUMIFS('Gastos agosto'!$D$24:$D$110,'Gastos agosto'!$F$24:$F$110,$A16,'Gastos agosto'!$H$24:$H$110,">="&F$5,'Gastos agosto'!$H$24:$H$110,"<="&F$6) -> 0 | G16: =SUM(B16:F16) -> 6686.31
A17: Celular | B17: =-SUMIFS('Gastos agosto'!$D$24:$D$110,'Gastos agosto'!$F$24:$F$110,$A17,'Gastos agosto'!$H$24:$H$110,">="&B$5,'Gastos agosto'!$H$24:$H$110,"<="&B$6) -> 0 | C17: =-SUMIFS('Gastos agosto'!$D$24:$D$110,'Gastos agosto'!$F$24:$F$110,$A17,'Gastos agosto'!$H$24:$H$110,">="&C$5,'Gastos agosto'!$H$24:$H$110,"<="&C$6) -> 7000 | D17: =-SUMIFS('Gastos agosto'!$D$24:$D$110,'Gastos agosto'!$F$24:$F$110,$A17,'Gastos agosto'!$H$24:$H$110,">="&D$5,'Gastos agosto'!$H$24:$H$110,"<="&D$6) -> 0 | E17: =-SUMIFS('Gastos agosto'!$D$24:$D$110,'Gastos agosto'!$F$24:$F$110,$A17,'Gastos agosto'!$H$24:$H$110,">="&E$5,'Gastos agosto'!$H$24:$H$110,"<="&E$6) -> 0 | F17: =-SUMIFS('Gastos agosto'!$D$24:$D$110,'Gastos agosto'!$F$24:$F$110,$A17,'Gastos agosto'!$H$24:$H$110,">="&F$5,'Gastos agosto'!$H$24:$H$110,"<="&F$6) -> 0 | G17: =SUM(B17:F17) -> 7000
A18: Pago monotributo | B18: =-SUMIFS('Gastos agosto'!$D$24:$D$110,'Gastos agosto'!$F$24:$F$110,$A18,'Gastos agosto'!$H$24:$H$110,">="&B$5,'Gastos agosto'!$H$24:$H$110,"<="&B$6) -> 0 | C18: =-SUMIFS('Gastos agosto'!$D$24:$D$110,'Gastos agosto'!$F$24:$F$110,$A18,'Gastos agosto'!$H$24:$H$110,">="&C$5,'Gastos agosto'!$H$24:$H$110,"<="&C$6) -> 0 | D18: =-SUMIFS('Gastos agosto'!$D$24:$D$110,'Gastos agosto'!$F$24:$F$110,$A18,'Gastos agosto'!$H$24:$H$110,">="&D$5,'Gastos agosto'!$H$24:$H$110,"<="&D$6) -> 0 | E18: =-SUMIFS('Gastos agosto'!$D$24:$D$110,'Gastos agosto'!$F$24:$F$110,$A18,'Gastos agosto'!$H$24:$H$110,">="&E$5,'Gastos agosto'!$H$24:$H$110,"<="&E$6) -> 112779.08 | F18: =-SUMIFS('Gastos agosto'!$D$24:$D$110,'Gastos agosto'!$F$24:$F$110,$A18,'Gastos agosto'!$H$24:$H$110,">="&F$5,'Gastos agosto'!$H$24:$H$110,"<="&F$6) -> 0 | G18: =SUM(B18:F18) -> 112779.08
A19: Transferencias Jo | B19: =-SUMIFS('Gastos agosto'!$D$24:$D$110,'Gastos agosto'!$F$24:$F$110,$A19,'Gastos agosto'!$H$24:$H$110,">="&B$5,'Gastos agosto'!$H$24:$H$110,"<="&B$6) -> 0 | C19: =-SUMIFS('Gastos agosto'!$D$24:$D$110,'Gastos agosto'!$F$24:$F$110,$A19,'Gastos agosto'!$H$24:$H$110,">="&C$5,'Gastos agosto'!$H$24:$H$110,"<="&C$6) -> 0 | D19: =-SUMIFS('Gastos agosto'!$D$24:$D$110,'Gastos agosto'!$F$24:$F$110,$A19,'Gastos agosto'!$H$24:$H$110,">="&D$5,'Gastos agosto'!$H$24:$H$110,"<="&D$6) -> 0 | E19: =-SUMIFS('Gastos agosto'!$D$24:$D$110,'Gastos agosto'!$F$24:$F$110,$A19,'Gastos agosto'!$H$24:$H$110,">="&E$5,'Gastos agosto'!$H$24:$H$110,"<="&E$6) -> 10000 | F19: =-SUMIFS('Gastos agosto'!$D$24:$D$110,'Gastos agosto'!$F$24:$F$110,$A19,'Gastos agosto'!$H$24:$H$110,">="&F$5,'Gastos agosto'!$H$24:$H$110,"<="&F$6) -> 0 | G19: =SUM(B19:F19) -> 10000
A20: Total gastos corrientes (bruto) | B20: =SUM(B7:B19) -> 166200 | C20: =SUM(C7:C19) -> 276137.05 | D20: =SUM(D7:D19) -> 297774.27 | E20: =SUM(E7:E19) -> 712799.08 | F20: =SUM(F7:F19) -> 84800 | G20: =SUM(G7:G19) -> 1537710.4
A22: Movimientos internos / financieros
A23: Pago tarjetas de crédito | B23: =-SUMIFS('Gastos agosto'!$D$24:$D$110,'Gastos agosto'!$F$24:$F$110,$A23,'Gastos agosto'!$H$24:$H$110,">="&B$5,'Gastos agosto'!$H$24:$H$110,"<="&B$6) -> 0 | C23: =-SUMIFS('Gastos agosto'!$D$24:$D$110,'Gastos agosto'!$F$24:$F$110,$A23,'Gastos agosto'!$H$24:$H$110,">="&C$5,'Gastos agosto'!$H$24:$H$110,"<="&C$6) -> 0 | D23: =-SUMIFS('Gastos agosto'!$D$24:$D$110,'Gastos agosto'!$F$24:$F$110,$A23,'Gastos agosto'!$H$24:$H$110,">="&D$5,'Gastos agosto'!$H$24:$H$110,"<="&D$6) -> 309817.91 | E23: =-SUMIFS('Gastos agosto'!$D$24:$D$110,'Gastos agosto'!$F$24:$F$110,$A23,'Gastos agosto'!$H$24:$H$110,">="&E$5,'Gastos agosto'!$H$24:$H$110,"<="&E$6) -> 0 | F23: =-SUMIFS('Gastos agosto'!$D$24:$D$110,'Gastos agosto'!$F$24:$F$110,$A23,'Gastos agosto'!$H$24:$H$110,">="&F$5,'Gastos agosto'!$H$24:$H$110,"<="&F$6) -> 0 | G23: =SUM(B23:F23) -> 309817.91
A24: Inversiones FCI | B24: =-SUMIFS('Gastos agosto'!$D$24:$D$110,'Gastos agosto'!$F$24:$F$110,$A24,'Gastos agosto'!$H$24:$H$110,">="&B$5,'Gastos agosto'!$H$24:$H$110,"<="&B$6) -> 0 | C24: =-SUMIFS('Gastos agosto'!$D$24:$D$110,'Gastos agosto'!$F$24:$F$110,$A24,'Gastos agosto'!$H$24:$H$110,">="&C$5,'Gastos agosto'!$H$24:$H$110,"<="&C$6) -> 1900000 | D24: =-SUMIFS('Gastos agosto'!$D$24:$D$110,'Gastos agosto'!$F$24:$F$110,$A24,'Gastos agosto'!$H$24:$H$110,">="&D$5,'Gastos agosto'!$H$24:$H$110,"<="&D$6) -> 200000 | E24: =-SUMIFS('Gastos agosto'!$D$24:$D$110,'Gastos agosto'!$F$24:$F$110,$A24,'Gastos agosto'!$H$24:$H$110,">="&E$5,'Gastos agosto'!$H$24:$H$110,"<="&E$6) -> 0 | F24: =-SUMIFS('Gastos agosto'!$D$24:$D$110,'Gastos agosto'!$F$24:$F$110,$A24,'Gastos agosto'!$H$24:$H$110,">="&F$5,'Gastos agosto'!$H$24:$H$110,"<="&F$6) -> 200000 | G24: =SUM(B24:F24) -> 2300000
A25: Rescates FCI | B25: =-SUMIFS('Gastos agosto'!$D$24:$D$110,'Gastos agosto'!$F$24:$F$110,$A25,'Gastos agosto'!$H$24:$H$110,">="&B$5,'Gastos agosto'!$H$24:$H$110,"<="&B$6) -> 0 | C25: =-SUMIFS('Gastos agosto'!$D$24:$D$110,'Gastos agosto'!$F$24:$F$110,$A25,'Gastos agosto'!$H$24:$H$110,">="&C$5,'Gastos agosto'!$H$24:$H$110,"<="&C$6) -> 230000 | D25: =-SUMIFS('Gastos agosto'!$D$24:$D$110,'Gastos agosto'!$F$24:$F$110,$A25,'Gastos agosto'!$H$24:$H$110,">="&D$5,'Gastos agosto'!$H$24:$H$110,"<="&D$6) -> 200000 | E25: =-SUMIFS('Gastos agosto'!$D$24:$D$110,'Gastos agosto'!$F$24:$F$110,$A25,'Gastos agosto'!$H$24:$H$110,">="&E$5,'Gastos agosto'!$H$24:$H$110,"<="&E$6) -> 250000 | F25: =-SUMIFS('Gastos agosto'!$D$24:$D$110,'Gastos agosto'!$F$24:$F$110,$A25,'Gastos agosto'!$H$24:$H$110,">="&F$5,'Gastos agosto'!$H$24:$H$110,"<="&F$6) -> 60000 | G25: =SUM(B25:F25) -> 740000
A26: Otros honorarios | B26: =-SUMIFS('Gastos agosto'!$D$24:$D$110,'Gastos agosto'!$F$24:$F$110,$A26,'Gastos agosto'!$H$24:$H$110,">="&B$5,'Gastos agosto'!$H$24:$H$110,"<="&B$6) -> 0 | C26: =-SUMIFS('Gastos agosto'!$D$24:$D$110,'Gastos agosto'!$F$24:$F$110,$A26,'Gastos agosto'!$H$24:$H$110,">="&C$5,'Gastos agosto'!$H$24:$H$110,"<="&C$6) -> 0 | D26: =-SUMIFS('Gastos agosto'!$D$24:$D$110,'Gastos agosto'!$F$24:$F$110,$A26,'Gastos agosto'!$H$24:$H$110,">="&D$5,'Gastos agosto'!$H$24:$H$110,"<="&D$6) -> 170000 | E26: =-SUMIFS('Gastos agosto'!$D$24:$D$110,'Gastos agosto'!$F$24:$F$110,$A26,'Gastos agosto'!$H$24:$H$110,">="&E$5,'Gastos agosto'!$H$24:$H$110,"<="&E$6) -> 0 | F26: =-SUMIFS('Gastos agosto'!$D$24:$D$110,'Gastos agosto'!$F$24:$F$110,$A26,'Gastos agosto'!$H$24:$H$110,">="&F$5,'Gastos agosto'!$H$24:$H$110,"<="&F$6) -> 0 | G26: =SUM(B26:F26) -> 170000
A27: Total movimientos internos | B27: =SUM(B23:B26) -> 0 | C27: =SUM(C23:C26) -> 2130000 | D27: =SUM(D23:D26) -> 879817.91 | E27: =SUM(E23:E26) -> 250000 | F27: =SUM(F23:F26) -> 260000 | G27: =SUM(G23:G26) -> 3519817.9
A29: TOTAL GENERAL | B29: =B20+B27 -> 166200 | C29: =C20+C27 -> 2406137 | D29: =D20+D27 -> 1177592.2 | E29: =E20+E27 -> 962799.08 | F29: =F20+F27 -> 344800 | G29: =G20+G27 -> 5057528.3
A31: Control: total gastos agosto (columna D) | B31: =-SUMIFS('Gastos agosto'!$D$24:$D$110,'Gastos agosto'!$H$24:$H$110,">="&$B$5,'Gastos agosto'!$H$24:$H$110,"<="&$F$6) -> 5057528.3
A32: Diferencia vs. total general (debe ser 0) | B32: =B31-G29 -> 0
A33: Gastos fuera del rango del mes (fecha inválida) | B33: =-SUMIFS('Gastos agosto'!$D$24:$D$110,'Gastos agosto'!$H$24:$H$110,">"&$F$6)-SUMIFS('Gastos agosto'!$D$24:$D$110,'Gastos agosto'!$H$24:$H$110,"<"&$B$5) -> 0
A36: Reintegros / devoluciones recibidas (columna C de 'Gastos agosto')
A37: Concepto | B37: Sem 1 | C37: Sem 2 | D37: Sem 3 | E37: Sem 4 | F37: Sem 5 | G37: Total mes
A38: =$A7 -> Salidas a cenar/almorzar | B38: =SUMIFS('Gastos agosto'!$C$24:$C$110,'Gastos agosto'!$F$24:$F$110,$A38,'Gastos agosto'!$H$24:$H$110,">="&B$5,'Gastos agosto'!$H$24:$H$110,"<="&B$6) -> 0 | C38: =SUMIFS('Gastos agosto'!$C$24:$C$110,'Gastos agosto'!$F$24:$F$110,$A38,'Gastos agosto'!$H$24:$H$110,">="&C$5,'Gastos agosto'!$H$24:$H$110,"<="&C$6) -> 21000 | D38: =SUMIFS('Gastos agosto'!$C$24:$C$110,'Gastos agosto'!$F$24:$F$110,$A38,'Gastos agosto'!$H$24:$H$110,">="&D$5,'Gastos agosto'!$H$24:$H$110,"<="&D$6) -> 0 | E38: =SUMIFS('Gastos agosto'!$C$24:$C$110,'Gastos agosto'!$F$24:$F$110,$A38,'Gastos agosto'!$H$24:$H$110,">="&E$5,'Gastos agosto'!$H$24:$H$110,"<="&E$6) -> 0 | F38: =SUMIFS('Gastos agosto'!$C$24:$C$110,'Gastos agosto'!$F$24:$F$110,$A38,'Gastos agosto'!$H$24:$H$110,">="&F$5,'Gastos agosto'!$H$24:$H$110,"<="&F$6) -> 0 | G38: =SUM(B38:F38) -> 21000
A39: =$A8 -> Juntadas a cenar/almorzar | B39: =SUMIFS('Gastos agosto'!$C$24:$C$110,'Gastos agosto'!$F$24:$F$110,$A39,'Gastos agosto'!$H$24:$H$110,">="&B$5,'Gastos agosto'!$H$24:$H$110,"<="&B$6) -> 0 | C39: =SUMIFS('Gastos agosto'!$C$24:$C$110,'Gastos agosto'!$F$24:$F$110,$A39,'Gastos agosto'!$H$24:$H$110,">="&C$5,'Gastos agosto'!$H$24:$H$110,"<="&C$6) -> 0 | D39: =SUMIFS('Gastos agosto'!$C$24:$C$110,'Gastos agosto'!$F$24:$F$110,$A39,'Gastos agosto'!$H$24:$H$110,">="&D$5,'Gastos agosto'!$H$24:$H$110,"<="&D$6) -> 142000 | E39: =SUMIFS('Gastos agosto'!$C$24:$C$110,'Gastos agosto'!$F$24:$F$110,$A39,'Gastos agosto'!$H$24:$H$110,">="&E$5,'Gastos agosto'!$H$24:$H$110,"<="&E$6) -> 0 | F39: =SUMIFS('Gastos agosto'!$C$24:$C$110,'Gastos agosto'!$F$24:$F$110,$A39,'Gastos agosto'!$H$24:$H$110,">="&F$5,'Gastos agosto'!$H$24:$H$110,"<="&F$6) -> 600 | G39: =SUM(B39:F39) -> 142600
A40: =$A9 -> Salidas a desyunar/merendar | B40: =SUMIFS('Gastos agosto'!$C$24:$C$110,'Gastos agosto'!$F$24:$F$110,$A40,'Gastos agosto'!$H$24:$H$110,">="&B$5,'Gastos agosto'!$H$24:$H$110,"<="&B$6) -> 0 | C40: =SUMIFS('Gastos agosto'!$C$24:$C$110,'Gastos agosto'!$F$24:$F$110,$A40,'Gastos agosto'!$H$24:$H$110,">="&C$5,'Gastos agosto'!$H$24:$H$110,"<="&C$6) -> 0 | D40: =SUMIFS('Gastos agosto'!$C$24:$C$110,'Gastos agosto'!$F$24:$F$110,$A40,'Gastos agosto'!$H$24:$H$110,">="&D$5,'Gastos agosto'!$H$24:$H$110,"<="&D$6) -> 0 | E40: =SUMIFS('Gastos agosto'!$C$24:$C$110,'Gastos agosto'!$F$24:$F$110,$A40,'Gastos agosto'!$H$24:$H$110,">="&E$5,'Gastos agosto'!$H$24:$H$110,"<="&E$6) -> 0 | F40: =SUMIFS('Gastos agosto'!$C$24:$C$110,'Gastos agosto'!$F$24:$F$110,$A40,'Gastos agosto'!$H$24:$H$110,">="&F$5,'Gastos agosto'!$H$24:$H$110,"<="&F$6) -> 0 | G40: =SUM(B40:F40) -> 0
A41: =$A10 -> Salidas a tomar algo | B41: =SUMIFS('Gastos agosto'!$C$24:$C$110,'Gastos agosto'!$F$24:$F$110,$A41,'Gastos agosto'!$H$24:$H$110,">="&B$5,'Gastos agosto'!$H$24:$H$110,"<="&B$6) -> 29700 | C41: =SUMIFS('Gastos agosto'!$C$24:$C$110,'Gastos agosto'!$F$24:$F$110,$A41,'Gastos agosto'!$H$24:$H$110,">="&C$5,'Gastos agosto'!$H$24:$H$110,"<="&C$6) -> 0 | D41: =SUMIFS('Gastos agosto'!$C$24:$C$110,'Gastos agosto'!$F$24:$F$110,$A41,'Gastos agosto'!$H$24:$H$110,">="&D$5,'Gastos agosto'!$H$24:$H$110,"<="&D$6) -> 0 | E41: =SUMIFS('Gastos agosto'!$C$24:$C$110,'Gastos agosto'!$F$24:$F$110,$A41,'Gastos agosto'!$H$24:$H$110,">="&E$5,'Gastos agosto'!$H$24:$H$110,"<="&E$6) -> 0 | F41: =SUMIFS('Gastos agosto'!$C$24:$C$110,'Gastos agosto'!$F$24:$F$110,$A41,'Gastos agosto'!$H$24:$H$110,">="&F$5,'Gastos agosto'!$H$24:$H$110,"<="&F$6) -> 0 | G41: =SUM(B41:F41) -> 29700
A42: =$A11 -> Delivery | B42: =SUMIFS('Gastos agosto'!$C$24:$C$110,'Gastos agosto'!$F$24:$F$110,$A42,'Gastos agosto'!$H$24:$H$110,">="&B$5,'Gastos agosto'!$H$24:$H$110,"<="&B$6) -> 0 | C42: =SUMIFS('Gastos agosto'!$C$24:$C$110,'Gastos agosto'!$F$24:$F$110,$A42,'Gastos agosto'!$H$24:$H$110,">="&C$5,'Gastos agosto'!$H$24:$H$110,"<="&C$6) -> 19500 | D42: =SUMIFS('Gastos agosto'!$C$24:$C$110,'Gastos agosto'!$F$24:$F$110,$A42,'Gastos agosto'!$H$24:$H$110,">="&D$5,'Gastos agosto'!$H$24:$H$110,"<="&D$6) -> 0 | E42: =SUMIFS('Gastos agosto'!$C$24:$C$110,'Gastos agosto'!$F$24:$F$110,$A42,'Gastos agosto'!$H$24:$H$110,">="&E$5,'Gastos agosto'!$H$24:$H$110,"<="&E$6) -> 0 | F42: =SUMIFS('Gastos agosto'!$C$24:$C$110,'Gastos agosto'!$F$24:$F$110,$A42,'Gastos agosto'!$H$24:$H$110,">="&F$5,'Gastos agosto'!$H$24:$H$110,"<="&F$6) -> 0 | G42: =SUM(B42:F42) -> 19500
A43: =$A12 -> Auto | B43: =SUMIFS('Gastos agosto'!$C$24:$C$110,'Gastos agosto'!$F$24:$F$110,$A43,'Gastos agosto'!$H$24:$H$110,">="&B$5,'Gastos agosto'!$H$24:$H$110,"<="&B$6) -> 0 | C43: =SUMIFS('Gastos agosto'!$C$24:$C$110,'Gastos agosto'!$F$24:$F$110,$A43,'Gastos agosto'!$H$24:$H$110,">="&C$5,'Gastos agosto'!$H$24:$H$110,"<="&C$6) -> 0 | D43: =SUMIFS('Gastos agosto'!$C$24:$C$110,'Gastos agosto'!$F$24:$F$110,$A43,'Gastos agosto'!$H$24:$H$110,">="&D$5,'Gastos agosto'!$H$24:$H$110,"<="&D$6) -> 50000 | E43: =SUMIFS('Gastos agosto'!$C$24:$C$110,'Gastos agosto'!$F$24:$F$110,$A43,'Gastos agosto'!$H$24:$H$110,">="&E$5,'Gastos agosto'!$H$24:$H$110,"<="&E$6) -> 0 | F43: =SUMIFS('Gastos agosto'!$C$24:$C$110,'Gastos agosto'!$F$24:$F$110,$A43,'Gastos agosto'!$H$24:$H$110,">="&F$5,'Gastos agosto'!$H$24:$H$110,"<="&F$6) -> 0 | G43: =SUM(B43:F43) -> 50000
A44: =$A13 -> Regalos | B44: =SUMIFS('Gastos agosto'!$C$24:$C$110,'Gastos agosto'!$F$24:$F$110,$A44,'Gastos agosto'!$H$24:$H$110,">="&B$5,'Gastos agosto'!$H$24:$H$110,"<="&B$6) -> 0 | C44: =SUMIFS('Gastos agosto'!$C$24:$C$110,'Gastos agosto'!$F$24:$F$110,$A44,'Gastos agosto'!$H$24:$H$110,">="&C$5,'Gastos agosto'!$H$24:$H$110,"<="&C$6) -> 0 | D44: =SUMIFS('Gastos agosto'!$C$24:$C$110,'Gastos agosto'!$F$24:$F$110,$A44,'Gastos agosto'!$H$24:$H$110,">="&D$5,'Gastos agosto'!$H$24:$H$110,"<="&D$6) -> 30000 | E44: =SUMIFS('Gastos agosto'!$C$24:$C$110,'Gastos agosto'!$F$24:$F$110,$A44,'Gastos agosto'!$H$24:$H$110,">="&E$5,'Gastos agosto'!$H$24:$H$110,"<="&E$6) -> 366000 | F44: =SUMIFS('Gastos agosto'!$C$24:$C$110,'Gastos agosto'!$F$24:$F$110,$A44,'Gastos agosto'!$H$24:$H$110,">="&F$5,'Gastos agosto'!$H$24:$H$110,"<="&F$6) -> 0 | G44: =SUM(B44:F44) -> 396000
A45: =$A14 -> Fiestas | B45: =SUMIFS('Gastos agosto'!$C$24:$C$110,'Gastos agosto'!$F$24:$F$110,$A45,'Gastos agosto'!$H$24:$H$110,">="&B$5,'Gastos agosto'!$H$24:$H$110,"<="&B$6) -> 0 | C45: =SUMIFS('Gastos agosto'!$C$24:$C$110,'Gastos agosto'!$F$24:$F$110,$A45,'Gastos agosto'!$H$24:$H$110,">="&C$5,'Gastos agosto'!$H$24:$H$110,"<="&C$6) -> 0 | D45: =SUMIFS('Gastos agosto'!$C$24:$C$110,'Gastos agosto'!$F$24:$F$110,$A45,'Gastos agosto'!$H$24:$H$110,">="&D$5,'Gastos agosto'!$H$24:$H$110,"<="&D$6) -> 0 | E45: =SUMIFS('Gastos agosto'!$C$24:$C$110,'Gastos agosto'!$F$24:$F$110,$A45,'Gastos agosto'!$H$24:$H$110,">="&E$5,'Gastos agosto'!$H$24:$H$110,"<="&E$6) -> 0 | F45: =SUMIFS('Gastos agosto'!$C$24:$C$110,'Gastos agosto'!$F$24:$F$110,$A45,'Gastos agosto'!$H$24:$H$110,">="&F$5,'Gastos agosto'!$H$24:$H$110,"<="&F$6) -> 0 | G45: =SUM(B45:F45) -> 0
A46: =$A15 -> Psicóloga | B46: =SUMIFS('Gastos agosto'!$C$24:$C$110,'Gastos agosto'!$F$24:$F$110,$A46,'Gastos agosto'!$H$24:$H$110,">="&B$5,'Gastos agosto'!$H$24:$H$110,"<="&B$6) -> 0 | C46: =SUMIFS('Gastos agosto'!$C$24:$C$110,'Gastos agosto'!$F$24:$F$110,$A46,'Gastos agosto'!$H$24:$H$110,">="&C$5,'Gastos agosto'!$H$24:$H$110,"<="&C$6) -> 0 | D46: =SUMIFS('Gastos agosto'!$C$24:$C$110,'Gastos agosto'!$F$24:$F$110,$A46,'Gastos agosto'!$H$24:$H$110,">="&D$5,'Gastos agosto'!$H$24:$H$110,"<="&D$6) -> 0 | E46: =SUMIFS('Gastos agosto'!$C$24:$C$110,'Gastos agosto'!$F$24:$F$110,$A46,'Gastos agosto'!$H$24:$H$110,">="&E$5,'Gastos agosto'!$H$24:$H$110,"<="&E$6) -> 0 | F46: =SUMIFS('Gastos agosto'!$C$24:$C$110,'Gastos agosto'!$F$24:$F$110,$A46,'Gastos agosto'!$H$24:$H$110,">="&F$5,'Gastos agosto'!$H$24:$H$110,"<="&F$6) -> 30386 | G46: =SUM(B46:F46) -> 30386
A47: =$A16 -> Farmacia/Cosméticos | B47: =SUMIFS('Gastos agosto'!$C$24:$C$110,'Gastos agosto'!$F$24:$F$110,$A47,'Gastos agosto'!$H$24:$H$110,">="&B$5,'Gastos agosto'!$H$24:$H$110,"<="&B$6) -> 0 | C47: =SUMIFS('Gastos agosto'!$C$24:$C$110,'Gastos agosto'!$F$24:$F$110,$A47,'Gastos agosto'!$H$24:$H$110,">="&C$5,'Gastos agosto'!$H$24:$H$110,"<="&C$6) -> 0 | D47: =SUMIFS('Gastos agosto'!$C$24:$C$110,'Gastos agosto'!$F$24:$F$110,$A47,'Gastos agosto'!$H$24:$H$110,">="&D$5,'Gastos agosto'!$H$24:$H$110,"<="&D$6) -> 0 | E47: =SUMIFS('Gastos agosto'!$C$24:$C$110,'Gastos agosto'!$F$24:$F$110,$A47,'Gastos agosto'!$H$24:$H$110,">="&E$5,'Gastos agosto'!$H$24:$H$110,"<="&E$6) -> 0 | F47: =SUMIFS('Gastos agosto'!$C$24:$C$110,'Gastos agosto'!$F$24:$F$110,$A47,'Gastos agosto'!$H$24:$H$110,">="&F$5,'Gastos agosto'!$H$24:$H$110,"<="&F$6) -> 0 | G47: =SUM(B47:F47) -> 0
A48: =$A17 -> Celular | B48: =SUMIFS('Gastos agosto'!$C$24:$C$110,'Gastos agosto'!$F$24:$F$110,$A48,'Gastos agosto'!$H$24:$H$110,">="&B$5,'Gastos agosto'!$H$24:$H$110,"<="&B$6) -> 0 | C48: =SUMIFS('Gastos agosto'!$C$24:$C$110,'Gastos agosto'!$F$24:$F$110,$A48,'Gastos agosto'!$H$24:$H$110,">="&C$5,'Gastos agosto'!$H$24:$H$110,"<="&C$6) -> 0 | D48: =SUMIFS('Gastos agosto'!$C$24:$C$110,'Gastos agosto'!$F$24:$F$110,$A48,'Gastos agosto'!$H$24:$H$110,">="&D$5,'Gastos agosto'!$H$24:$H$110,"<="&D$6) -> 0 | E48: =SUMIFS('Gastos agosto'!$C$24:$C$110,'Gastos agosto'!$F$24:$F$110,$A48,'Gastos agosto'!$H$24:$H$110,">="&E$5,'Gastos agosto'!$H$24:$H$110,"<="&E$6) -> 0 | F48: =SUMIFS('Gastos agosto'!$C$24:$C$110,'Gastos agosto'!$F$24:$F$110,$A48,'Gastos agosto'!$H$24:$H$110,">="&F$5,'Gastos agosto'!$H$24:$H$110,"<="&F$6) -> 0 | G48: =SUM(B48:F48) -> 0
A49: =$A18 -> Pago monotributo | B49: =SUMIFS('Gastos agosto'!$C$24:$C$110,'Gastos agosto'!$F$24:$F$110,$A49,'Gastos agosto'!$H$24:$H$110,">="&B$5,'Gastos agosto'!$H$24:$H$110,"<="&B$6) -> 0 | C49: =SUMIFS('Gastos agosto'!$C$24:$C$110,'Gastos agosto'!$F$24:$F$110,$A49,'Gastos agosto'!$H$24:$H$110,">="&C$5,'Gastos agosto'!$H$24:$H$110,"<="&C$6) -> 0 | D49: =SUMIFS('Gastos agosto'!$C$24:$C$110,'Gastos agosto'!$F$24:$F$110,$A49,'Gastos agosto'!$H$24:$H$110,">="&D$5,'Gastos agosto'!$H$24:$H$110,"<="&D$6) -> 0 | E49: =SUMIFS('Gastos agosto'!$C$24:$C$110,'Gastos agosto'!$F$24:$F$110,$A49,'Gastos agosto'!$H$24:$H$110,">="&E$5,'Gastos agosto'!$H$24:$H$110,"<="&E$6) -> 56400 | F49: =SUMIFS('Gastos agosto'!$C$24:$C$110,'Gastos agosto'!$F$24:$F$110,$A49,'Gastos agosto'!$H$24:$H$110,">="&F$5,'Gastos agosto'!$H$24:$H$110,"<="&F$6) -> 0 | G49: =SUM(B49:F49) -> 56400
A50: =$A19 -> Transferencias Jo | B50: =SUMIFS('Gastos agosto'!$C$24:$C$110,'Gastos agosto'!$F$24:$F$110,$A50,'Gastos agosto'!$H$24:$H$110,">="&B$5,'Gastos agosto'!$H$24:$H$110,"<="&B$6) -> 0 | C50: =SUMIFS('Gastos agosto'!$C$24:$C$110,'Gastos agosto'!$F$24:$F$110,$A50,'Gastos agosto'!$H$24:$H$110,">="&C$5,'Gastos agosto'!$H$24:$H$110,"<="&C$6) -> 0 | D50: =SUMIFS('Gastos agosto'!$C$24:$C$110,'Gastos agosto'!$F$24:$F$110,$A50,'Gastos agosto'!$H$24:$H$110,">="&D$5,'Gastos agosto'!$H$24:$H$110,"<="&D$6) -> 25000 | E50: =SUMIFS('Gastos agosto'!$C$24:$C$110,'Gastos agosto'!$F$24:$F$110,$A50,'Gastos agosto'!$H$24:$H$110,">="&E$5,'Gastos agosto'!$H$24:$H$110,"<="&E$6) -> 0 | F50: =SUMIFS('Gastos agosto'!$C$24:$C$110,'Gastos agosto'!$F$24:$F$110,$A50,'Gastos agosto'!$H$24:$H$110,">="&F$5,'Gastos agosto'!$H$24:$H$110,"<="&F$6) -> 0 | G50: =SUM(B50:F50) -> 25000
A51: Total reintegros | B51: =SUM(B38:B50) -> 29700 | C51: =SUM(C38:C50) -> 40500 | D51: =SUM(D38:D50) -> 247000 | E51: =SUM(E38:E50) -> 422400 | F51: =SUM(F38:F50) -> 30986 | G51: =SUM(G38:G50) -> 770586
A54: GASTO NETO por semana (bruto − reintegros)
A55: Concepto | B55: Sem 1 | C55: Sem 2 | D55: Sem 3 | E55: Sem 4 | F55: Sem 5 | G55: Total mes
A56: =$A7 -> Salidas a cenar/almorzar | B56: =B7-B38 -> 45000 | C56: =C7-C38 -> 138950.74 | D56: =D7-D38 -> 66180 | E56: =E7-E38 -> 5000 | F56: =F7-F38 -> 0 | G56: =SUM(B56:F56) -> 255130.74
A57: =$A8 -> Juntadas a cenar/almorzar | B57: =B8-B39 -> 0 | C57: =C8-C39 -> 0 | D57: =D8-D39 -> 26094.27 | E57: =E8-E39 -> 60070 | F57: =F8-F39 -> 32500 | G57: =SUM(B57:F57) -> 118664.27
A58: =$A9 -> Salidas a desyunar/merendar | B58: =B9-B40 -> 10000 | C58: =C9-C40 -> 0 | D58: =D9-D40 -> 0 | E58: =E9-E40 -> 8400 | F58: =F9-F40 -> 6700 | G58: =SUM(B58:F58) -> 25100
A59: =$A10 -> Salidas a tomar algo | B59: =B10-B41 -> 31500 | C59: =C10-C41 -> 0 | D59: =D10-D41 -> 13500 | E59: =E10-E41 -> 22000 | F59: =F10-F41 -> 0 | G59: =SUM(B59:F59) -> 67000
A60: =$A11 -> Delivery | B60: =B11-B42 -> 0 | C60: =C11-C42 -> 18000 | D60: =D11-D42 -> 0 | E60: =E11-E42 -> 0 | F60: =F11-F42 -> 0 | G60: =SUM(B60:F60) -> 18000
A61: =$A12 -> Auto | B61: =B12-B43 -> 50000 | C61: =C12-C43 -> 20000 | D61: =D12-D43 -> 0 | E61: =E12-E43 -> 25000 | F61: =F12-F43 -> 0 | G61: =SUM(B61:F61) -> 95000
